Workbook

Sheet Referencias
A1: Grupo | B1: Produto | C1: Qtd Pacote | D1: Vlr Pacote | E1: Unidade | F1: Unitário
A2: Fios | B2: Barroco MultiColor 200g | C2: 200 | D2: 18.99 | E2: gramas | F2: =ROUND(D2/C2,2) -> 0.09
A3: Armarinhos | B3: Bolinha 6,5 | C3: 100 | D3: 104.49 | E3: Unidade | F3: =ROUND(D3/C3,2) -> 1.04
A4: Armarinhos | B4: Cordão Dourado | C4: 50 | D4: 7.49 | E4: m | F4: =ROUND(D4/C4,2) -> 0.15
A5: Fios | B5: Cordão Encerado Settanyl | C5: 100 | D5: 15.9 | E5: m | F5: =ROUND(D5/C5,2) -> 0.16
A6: Armarinhos | B6: Elastico | C6: 10 | D6: 6.9 | E6: m | F6: =ROUND(D6/C6,2) -> 0.69
A7: Fios | B7: Fio Clea 1000 160g | C7: 160 | D7: 16.99 | E7: gramas | F7: =ROUND(D7/C7,2) -> 0.11
A8: Fitas | B8: Fita 7mm | C8: 100 | D8: 9.99 | E8: m | F8: =ROUND(D8/C8,2) -> 0.1
A9: Fitas | B9: Fita cetim | C9: 100 | D9: 12.99 | E9: m | F9: =ROUND(D9/C9,2) -> 0.13
A10: Armarinhos | B10: Ilhos | C10: 100 | D10: 4.89 | E10: Unidade | F10: =ROUND(D10/C10,2) -> 0.05
A11: Armarinhos | B11: Pano de Prato Pé de Galinha | C11: 1 | D11: 4 | E11: Unidade | F11: =ROUND(D11/C11,2) -> 4
A12: Armarinhos | B12: Pano de Prato Atoalhado | C12: 3 | D12: 21.09 | E12: Unidade | F12: =ROUND(D12/C12,2) -> 7.03
A13: Desgaste (Impressora, Encadernadora, Laminadora) | B13: Desgaste Agenda | C13: 1 | D13: 1 | E13: Unidade | F13: =ROUND(D13/C13,2) -> 1
... A32: Laminação e Plastificação | B32: Polaseal A4 Divisórias | C32: 20 | D32: 1.7 | E32: Folha A4 | F32: =ROUND(D32/C32,2) -> 0.09
A33: Laminação e Plastificação | B33: Polaseal marcador 1/4 A4 | C33: =20*4 -> 80 | D33: 1.7 | E33: 1/4 A4 | F33: =ROUND(D33/C33,2) -> 0.02
A34: OffSet 180g | B34: Bolso offset 180gr | C34: 100 | D34: 31.65 | E34: Folha A4 | F34: =ROUND(D34/C34,2) -> 0.32
A35: OffSet 180g | B35: divisórias offset 180gr | C35: 100 | D35: 31.65 | E35: Folha A4 | F35: =ROUND(D35/C35,2) -> 0.32
A36: OffSet 180g | B36: miolo 180g A5 | C36: =100*2 -> 200 | D36: 31.65 | E36: Folha A5 | F36: =ROUND(D36/C36,2) -> 0.16
A37: OffSet 180g | B37: miolo 180gr A4 | C37: 100 | D37: 31.65 | E37: Folha A4 | F37: =ROUND(D37/C37,2) -> 0.32
A38: OffSet 240g | B38: Papel 240g A4 | C38: 100 | D38: 42.2 | E38: Folha A4 | F38: =ROUND(D38/C38,2) -> 0.42
A39: OffSet 75g | B39: miolo 75gr A4 | C39: 500 | D39: 32 | E39: Folha A4 | F39: =ROUND(D39/C39,2) -> 0.06
A40: OffSet 75g | B40: miolo 75gr A5 | C40: =500*2 -> 1000 | D40: 32 | E40: Folha A5 | F40: =ROUND(D40/C40,2) -> 0.03
A41: OffSet 75g | B41: Sulfite 75g A4 | C41: 500 | D41: 32 | E41: Folha A4 | F41: =ROUND(D41/C41,2) -> 0.06
A42: OffSet 75g | B42: Sulfite 75g A5 | C42: =500*2 -> 1000 | D42: 32 | E42: Folha A5 | F42: =ROUND(D42/C42,2) -> 0.03
A43: OffSet 90g | B43: Marcador 90g A6 | C43: =500*4 -> 2000 | D43: 50 | E43: Folha A6 | F43: =ROUND(D43/C43,2) -> 0.03
A44: OffSet 90g | B44: miolo 90gr A4 dobrado no meio | C44: 500 | D44: 50 | E44: Folha A4 | F44: =ROUND(D44/C44,2) -> 0.1
A45: OffSet 90g | B45: miolo 90gr A5 | C45: =500*2 -> 1000 | D45: 50 | E45: Folha A5 | F45: =ROUND(D45/C45,2) -> 0.05
A46: OffSet 90g | B46: miolo 90gr A5 14x18 | C46: =500*2 -> 1000 | D46: 50 | E46: Folha A5 | F46: =ROUND(D46/C46,2) -> 0.05
A47: OffSet Adesivado | B47: Papel guarda 14,5x18 offset adesivo | C47: 40 | D47: 29.8 | E47: Folha A4 | F47: =ROUND(D47/C47,2) -> 0.75
A48: OffSet Adesivado | B48: Papel guarda 15,5x21,5 offset adesivo | C48: 40 | D48: 29.8 | E48: Folha A4 | F48: =ROUND(D48/C48,2) -> 0.75
A49: OffSet Adesivado | B49: Papel guarda 16,5x21,5 offset adesivo | C49: 40 | D49: 29.8 | E49: Folha A4 | F49: =ROUND(D49/C49,2) -> 0.75
A50: OffSet Adesivado | B50: Papel guarda 20x20 offset adesivo | C50: 40 | D50: 29.8 | E50: Folha A4 | F50: =ROUND(D50/C50,2) -> 0.75
A51: OffSet Adesivado | B51: Papel offset adesivo + guarda | C51: 40 | D51: 29.8 | E51: Folha A4 | F51: =ROUND(D51/C51,2) -> 0.75
A52: OffSet Adesivado | B52: Papel offset adesivo A4 | C52: 40 | D52: 29.8 | E52: Folha A4 | F52: =ROUND(D52/C52,2) -> 0.75
A53: Papel Fotográfico | B53: Papel fotografico A4 | C53: 20 | D53: 15.9 | E53: Folha A4 | F53: =ROUND(D53/C53,2) -> 0.8
A54: Papel Kraft | B54: Papel Kraft A4 | C54: 30 | D54: 16.1 | E54: Folha A4 | F54: =ROUND(D54/C54,2) -> 0.54
A55: Papel Kraft | B55: Papel Kraft A5 | C55: =30*2 -> 60 | D55: 16.1 | E55: Folha A5 | F55: =ROUND(D55/C55,2) -> 0.27
A56: Papelão Cinza | B56: Papelão 15,5x21,5+2,5x21,5 | C56: 20 | D56: 29.9 | E56: Folha A4 | F56: =ROUND(D56/C56,2) -> 1.5
A57: Papelão Cinza | B57: Papelão 15x18,5 | C57: 20 | D57: 29.9 | E57: Folha A4 | F57: =ROUND(D57/C57,2) -> 1.5
A58: Papelão Cinza | B58: Papelão 16x22 | C58: 20 | D58: 29.9 | E58: Folha A4 | F58: =ROUND(D58/C58,2) -> 1.5
A59: Papelão Cinza | B59: Papelão 17x22 | C59: 20 | D59: 29.9 | E59: Folha A4 | F59: =ROUND(D59/C59,2) -> 1.5
A60: Papelão Cinza | B60: Papelão 7,7x8,5+7,7x2,5 | C60: =20*2 -> 40 | D60: 29.9 | E60: Folha A5 | F60: =ROUND(D60/C60,2) -> 0.75
A61: Papelão Cinza | B61: Papelão 9,5x10,5+9,5x2 | C61: 20 | D61: 29.9 | E61: Folha A4 | F61: =ROUND(D61/C61,2) -> 1.5
A62: Outros | B62: Frete | C62: 1 | D62: 0 | E62: Unidade | F62: =ROUND(D62/C62,2) -> 0
A63: Impressão | B63: Impressao Miolo Frente A4 | C63: 1 | D63: 0.06 | E63: Unidade | F63: =ROUND(D63/C63,2) -> 0.06
A64: Impressão | B64: Impressao Divisória A4 | C64: 1 | D64: 1 | E64: Unidade | F64: =ROUND(D64/C64,2) -> 1
A65: Papelão Cinza | B65: Papelão A4 | C65: 20 | D65: 29.9 | E65: Folha A4 | F65: =ROUND(D65/C65,2) -> 1.5
A66: OffSet Adesivado | B66: Papel guarda offset adesivo A4 | C66: 40 | D66: 29.8 | E66: Folha A4 | F66: =ROUND(D66/C66,2) -> 0.75
A67: Papelão Cinza | B67: Papelão 10,5x7,5 | C67: =20*4 -> 80 | D67: 29.9 | E67: Folha A4 | F67: =ROUND(D67/C67,2) -> 0.37
A68: OffSet 75g | B68: miolo 75gr A7 | C68: =500*8 -> 4000 | D68: 32 | E68: Folha A5 | F68: =ROUND(D68/C68,2) -> 0.01
A69: Espiral | B69: Espiral 20mm | C69: 50 | D69: 32.2 | E69: unidade 30cm | F69: =ROUND(D69/C69,2) -> 0.64
A70: Armarinhos | B70: Ima 3x15 (1mx0,62m) | C70: 1 | D70: 32.9 | E70: m | F70: =ROUND(D70/C70,2) -> 32.9
A71: Armarinhos | B71: caneta quadro branco | C71: 1 | D71: =1.7 -> 1.7 | E71: Unidade | F71: =ROUND(D71/C71,2) -> 1.7
A72: Papelão Cinza | B72: Papelão 19x27 | C72: 20 | D72: 29.9 | E72: Folha A4 | F72: =ROUND(D72/C72,2) -> 1.5
A73: OffSet Adesivado | B73: Papel guarda 18,5x26,5 offset adesivo | C73: 40 | D73: 29.8 | E73: Folha A4 | F73: =ROUND(D73/C73,2) -> 0.75
A74: OffSet 75g | B74: miolo 75gr 18x26 | C74: 500 | D74: 32 | E74: Folha A4 | F74: =ROUND(D74/C74,2) -> 0.06
A75: Armarinhos | B75: Plástico Cristal 1mx1,4m | C75: 1 | D75: 14.9 | E75: m | F75: =ROUND(D75/C75,2) -> 14.9
A76: Tricoline | B76: Tecido Tricoline 1mx1,4m trevo | C76: 1 | D76: 33.8 | E76: m | F76: =ROUND(D76/C76,2) -> 33.8
A77: Armarinhos | B77: Botão de Pressão | C77: 200 | D77: 14.15 | E77: caixa | F77: =ROUND(D77/C77,2) -> 0.07
A78: Armarinhos | B78: Manta R2 1mx1,4m | C78: 1 | D78: 27.8 | E78: m | F78: =ROUND(D78/C78,2) -> 27.8
A79: Armarinhos | B79: Vies 20m | C79: 20 | D79: 6.35 | E79: m | F79: =ROUND(D79/C79,2) -> 0.32
A80: Armarinhos | B80: Linha Dinner | C80: 3600 | D80: 6.7 | E80: m | F80: 0.1
A81: Armarinhos | B81: Etiqueta Cetim 1,5 10m | C81: 10 | D81: 2.5 | E81: m | F81: =ROUND(D81/C81,2) -> 0.25
A82: Papel Transfer | B82: Papel Transfer | C82: 10 | D82: 54.9 | E82: Folha A4 | F82: =ROUND(D82/C82,2) -> 5.49
A83: Impressão | B83: Impressão A4 | C83: 1 | D83: 0.5 | E83: Unidade | F83: =ROUND(D83/C83,2) -> 0.5
A84: OffSet 180g | B84: Papel 180gr A4 | C84: 100 | D84: 31.65 | E84: Folha A4 | F84: =ROUND(D84/C84,2) -> 0.32
A85: Armarinhos | B85: Alça - Fio Nautico circulo branco | C85: 208 | D85: 28.9 | E85: m | F85: =ROUND(D85/C85,2) -> 0.14
A86: OffSet 180g | B86: Papel 180gr A4 Reciclado | C86: 100 | D86: 25.1 | E86: Folha A4 | F86: =ROUND(D86/C86,2) -> 0.25
A87: Armarinhos | B87: Alça - Cordão de Algodão | C87: 50 | D87: 25.9 | E87: m | F87: =ROUND(D87/C87,2) -> 0.52
A88: Armarinhos | B88: Linha Circulo Maxi Mouline | C88: 8 | D88: 1.4 | E88: m | F88: =ROUND(D88/C88,2) -> 0.18
A89: Caderno | B89: Caderno Brochura Foroni A5 | C89: 1 | D89: 4.1 | E89: Unidade | F89: =ROUND(D89/C89,2) -> 4.1
A90: Contact | B90: Contact 200x45 | C90: =2*0.45 -> 0.9 | D90: 13.5 | E90: Unidade | F90: =ROUND(D90/C90,2) -> 15
A91: EVA | B91: EVA 40x47 | C91: 10 | D91: 11.9 | E91: Unidade | F91: =ROUND(D91/C91,2) -> 1.19
A92: Papelão Cinza | B92: Papelão 12x12+12x12+12x1 | C92: 20 | D92: 29.9 | E92: Folha A4 | F92: =ROUND(D92/C92,2) -> 1.5
A93: OffSet 90g | B93: Sulfite 90gr 11,5x11,5 | C93: =500*2 -> 1000 | D93: 50 | E93: Folha A5 | F93: =ROUND(D93/C93,2) -> 0.05
A94: Armarinhos | B94: Cola Branca 1kg | C94: 1000 | D94: 35 | E94: gramas | F94: =ROUND(D94/C94,2) -> 0.04
A95: Armarinhos | B95: Linha Urso | C95: 183 | D95: 42.9 | E95: m | F95: =ROUND(D95/C95,2) -> 0.23
A96: Papelão Cinza | B96: Papelão 11,5x15,5 | C96: =20*2 -> 40 | D96: 29.9 | E96: Folha A5 | F96: =ROUND(D96/C96,2) -> 0.75
A97: OffSet Adesivado | B97: Papel guarda 11x14,5 offset adesivo | C97: 80 | D97: 29.8 | E97: Folha A4 | F97: =ROUND(D97/C97,2) -> 0.37
A98: OffSet 75g | B98: Sulfite 75g A6 | C98: =500*4 -> 2000 | D98: 32 | E98: Folha A6 | F98: =ROUND(D98/C98,2) -> 0.02
A99: Color Plus | B99: Color Plus Guarda A4 | C99: 9 | D99: 5.59 | E99: Folha A4 | F99: =ROUND(D99/C99,2) -> 0.62
A100: OffSet 180g | B100: Papel 180gr A6 | C100: 400 | D100: 31.65 | E100: Folha A4 | F100: =ROUND(D100/C100,2) -> 0.08
A101: Outros | B101: Máscara Facial de Limpeza | C101: 1 | D101: 1.02 | E101: Unidade | F101: =ROUND(D101/C101,2) -> 1.02
A102: Doces | B102: Chocolate Talento 25g | C102: 15 | D102: 26.5 | E102: Caixa | F102: =ROUND(D102/C102,2) -> 1.77
A103: Doces | B103: Goma de Mascar Trident 168g | C103: 21 | D103: 30.99 | E103: Caixa | F103: =ROUND(D103/C103,2) -> 1.48
A104: Armarinhos | B104: Barroco Natural 8 700g | C104: 700 | D104: 18.99 | E104: gramas | F104: =ROUND(D104/C104,2) -> 0.03
A105: Armarinhos | B105: Fio Anne 500 147g | C105: 147 | D105: 18.06 | E105: gramas | F105: =ROUND(D105/C105,2) -> 0.12
A106: OffSet 180g | B106: Papel 180gr Capa 6x6 | C106: 400 | D106: 31.65 | E106: Folha A4 | F106: =ROUND(D106/C106,2) -> 0.08
A107: Embalagem (Seda, Plastico, Perfume, Sacola) | B107: Embalagem Atacado | C107: 1 | D107: 0.5 | E107: Unidade | F107: =ROUND(D107/C107,2) -> 0.5
A108: Pró-labore | B108: Pró-Labore Priscilla por Hora | C108: 1 | D108: =#REF! -> #REF! | E108: Unidade | F108: =ROUND(D108/C108,2) -> #REF!
A109: Custos Fixos | B109: Custos Fixos por Hora | C109: 1 | D109: =#REF! -> #REF! | E109: Unidade | F109: =ROUND(D109/C109,2) -> #REF!
A110: Doces | B110: Chocolate Baton 16g | C110: 30 | D110: 27.99 | E110: Caixa | F110: =ROUND(D110/C110,2) -> 0.93
A111: OffSet 180g | B111: Card OffSet 180gr | C111: =100*6 -> 600 | D111: 31.65 | E111: Folha A4 | F111: =ROUND(D111/C111,2) -> 0.05
A112: Impressão | B112: Impressao Card | C112: 6 | D112: 0.5 | E112: Unidade | F112: =ROUND(D112/C112,2) -> 0.08
A113: Doces | B113: Bon Bon Arcor 15g | C113: 50 | D113: 31.99 | E113: Pacote | F113: =ROUND(D113/C113,2) -> 0.64
A114: Doces | B114: Sonho de Valsa 15g | C114: 48 | D114: 55.99 | E114: Pacote | F114: =ROUND(D114/C114,2) -> 1.17
A115: Doces | B115: Moranguete 13g | C115: 160 | D115: 61.65 | E115: Pacote | F115: =ROUND(D115/C115,2) -> 0.39
A116: Envelopes | B116: Envelope Canguru 15x13 | C116: 10 | D116: 13.9 | E116: Pacote | F116: =ROUND(D116/C116,2) -> 1.39
A117: Envelopes | B117: Envelope Canguru 15x21 | C117: 10 | D117: 19.7 | E117: Pacote | F117: =ROUND(D117/C117,2) -> 1.97
A118: Offset 90g | B118: Sulfite 90gr | C118: 500 | D118: 50 | E118: Folha A4 | F118: =ROUND(D118/C118,2) -> 0.1
...

Sheet Mulher25
A1: Mini caderno | D1: 8
A2: =Referencias!B230 -> Papelão 5,5x7,5 | B2: 2 | C2: =Referencias!F230 -> 0.19 | D2: =B2*C2 -> 0.38
A3: =Referencias!B231 -> Papel fotografico 8,5x10,5 | B3: 2 | C3: =Referencias!F231 -> 0.2 | D3: =B3*C3 -> 0.4
A4: =Referencias!B31 -> bopp | B4: 0.08 | C4: =Referencias!F31 -> 0.45 | D4: =B4*C4 -> 0.036
A5: =Referencias!B232 -> Papel guarda 5x7 offset adesivo | B5: 2 | C5: =Referencias!F232 -> 0.19 | D5: =B5*C5 -> 0.38
A6: =Referencias!B233 -> miolo 75gr 5x7 | B6: 70 | C6: =Referencias!F233 -> 0.01 | D6: =B6*C6 -> 0.7
A7: =Referencias!B69 -> Espiral 20mm | B7: 0.17 | C7: =Referencias!F69 -> 0.64 | D7: =B7*C7 -> 0.1088
A8: =Referencias!B22 -> Impressao Capa A4 | B8: 1 | C8: =Referencias!F22 -> 0.5 | D8: =B8*C8 -> 0.5
A9: =Referencias!B62 -> Frete | C9: =Referencias!F62 -> 0 | D9: =B9*C9 -> 0
A10: =Referencias!B14 -> Desgaste Bloquinho/Outros | B10: 1 | C10: =Referencias!F14 -> 0.5 | D10: =B10*C10 -> 0.5
A11: =Referencias!B17 -> Embalagem Padrão | B11: 1 | C11: =Referencias!F17 -> 1.5 | D11: =B11*C11 -> 1.5
A12: Custo | D12: =SUM(D2:D11) -> 4.5048
A13: Margem | B13: 0.55 | C13: =D12*B13 -> 2.47764 | D13: =D12+C13 -> 6.98244
A14: Pesquisa
A15: Valor | D15: 10
A17: Pirulito Personalizado | D17: 2
A18: =Referencias!B236 -> Pirulito Florestal Coração Vermelho | B18: 1 | C18: =Referencias!F236 -> 0.18 | D18: =B18*C18 -> 0.18
A19: =Referencias!B111 -> Card OffSet 180gr | B19: 1 | C19: =Referencias!F111 -> 0.05 | D19: =B19*C19 -> 0.05
A20: =Referencias!B112 -> Impressao Card | B20: 1 | C20: =Referencias!F112 -> 0.08 | D20: =B20*C20 -> 0.08
A21: =Referencias!B62 -> Frete | C21: =Referencias!F62 -> 0 | D21: =B21*C21 -> 0
A22: =Referencias!B14 -> Desgaste Bloquinho/Outros | B22: 1 | C22: =Referencias!F14 -> 0.5 | D22: =B22*C22 -> 0.5
A23: =Referencias!B107 -> Embalagem Atacado | B23: 1 | C23: =Referencias!F107 -> 0.5 | D23: =B23*C23 -> 0.5
A24: Custo | D24: =SUM(D18:D23) -> 1.31
A25: Margem | B25: 0.55 | C25: =D24*B25 -> 0.7205 | D25: =D24+C25 -> 2.0305
A26: Pesquisa
A27: Valor | D27: 2.5

Sheet VoltaAulas25
A1: Planner Viagem
A2: =Referencias!B58 -> Papelão 16x22 | B2: 2 | C2: =Referencias!F58 -> 1.5 | D2: =B2*C2 -> 3
A3: =Referencias!B53 -> Papel fotografico A4 | B3: 2 | C3: =Referencias!F53 -> 0.8 | D3: =B3*C3 -> 1.6
A4: =Referencias!B31 -> bopp | B4: 0.6 | C4: =Referencias!F31 -> 0.45 | D4: =B4*C4 -> 0.27
A5: =Referencias!B48 -> Papel guarda 15,5x21,5 offset adesivo | B5: 2 | C5: =Referencias!F48 -> 0.75 | D5: =B5*C5 -> 1.5
A6: =Referencias!B45 -> miolo 90gr A5 | B6: 32 | C6: =Referencias!F45 -> 0.05 | D6: =B6*C6 -> 1.6
A7: =Referencias!B215 -> Color plus metalico Aspen 120g A4 | B7: 1 | C7: =Referencias!F215 -> 0.7 | D7: =B7*C7 -> 0.7
A8: =Referencias!B35 -> divisórias offset 180gr | B8: 4 | C8: =Referencias!F35 -> 0.32 | D8: =B8*C8 -> 1.28
A9: =Referencias!B32 -> Polaseal A4 Divisórias | B9: 4 | C9: =Referencias!F32 -> 0.09 | D9: =B9*C9 -> 0.36
A10: =Referencias!B19 -> Espiral 29mm | B10: 1 | C10: =Referencias!F19 -> 1.83 | D10: =B10*C10 -> 1.83
A11: =Referencias!B22 -> Impressao Capa A4 | B11: 2 | C11: =Referencias!F22 -> 0.5 | D11: =B11*C11 -> 1
A12: =Referencias!B64 -> Impressao Divisória A4 | B12: 4 | C12: =Referencias!F64 -> 1 | D12: =B12*C12 -> 4
A13: =Referencias!B29 -> Impressao Miolo Frente Verso A5 | B13: 32 | C13: =Referencias!F29 -> 0.06 | D13: =B13*C13 -> 1.92
A14: =Referencias!B62 -> Frete | C14: =Referencias!F62 -> 0 | D14: =B14*C14 -> 0
A15: =Referencias!B16 -> Desgaste Planner/Album/Caderno Universitario | B15: 1 | C15: =Referencias!F16 -> 3 | D15: =B15*C15 -> 3
A16: =Referencias!B17 -> Embalagem Padrão | B16: 1 | C16: =Referencias!F17 -> 1.5 | D16: =B16*C16 -> 1.5
A17: Custo | D17: =SUM(D2:D16) -> 23.56
A18: Margem | B18: 0.55 | C18: =D17*B18 -> 12.958 | D18: =D17+C18 -> 36.518
A19: Pesquisa | D19: =B19*C19 -> 0
A20: Valor | D20: =B20*C20 -> 0
A23: Diário de Leitura | D23: 50
A24: =Referencias!B58 -> Papelão 16x22 | B24: 2 | C24: =Referencias!F58 -> 1.5 | D24: =B24*C24 -> 3
A25: =Referencias!B53 -> Papel fotografico A4 | B25: 2 | C25: =Referencias!F53 -> 0.8 | D25: =B25*C25 -> 1.6
A26: =Referencias!B31 -> bopp | B26: =0.3*2 -> 0.6 | C26: =Referencias!F31 -> 0.45 | D26: =B26*C26 -> 0.27
A27: =Referencias!B48 -> Papel guarda 15,5x21,5 offset adesivo | B27: 2 | C27: =Referencias!F48 -> 0.75 | D27: =B27*C27 -> 1.5
A28: =Referencias!B45 -> miolo 90gr A5 | B28: 100 | C28: =Referencias!F45 -> 0.05 | D28: =B28*C28 -> 5
A29: =Referencias!B215 -> Color plus metalico Aspen 120g A4 | B29: 1 | C29: =Referencias!F215 -> 0.7 | D29: =B29*C29 -> 0.7
A30: =Referencias!B19 -> Espiral 29mm | B30: 1 | C30: =Referencias!F19 -> 1.83 | D30: =B30*C30 -> 1.83
A31: =Referencias!B22 -> Impressao Capa A4 | B31: 2 | C31: =Referencias!F22 -> 0.5 | D31: =B31*C31 -> 1
A32: =Referencias!B29 -> Impressao Miolo Frente Verso A5 | B32: 100 | C32: =Referencias!F29 -> 0.06 | D32: =B32*C32 -> 6
A33: =Referencias!B62 -> Frete | C33: =Referencias!F62 -> 0 | D33: =B33*C33 -> 0
A34: =Referencias!B15 -> Desgaste Caderno A5 | B34: 1 | C34: =Referencias!F15 -> 2 | D34: =B34*C34 -> 2
A35: =Referencias!B17 -> Embalagem Padrão | B35: 1 | C35: =Referencias!F17 -> 1.5 | D35: =B35*C35 -> 1.5
A36: Custo | D36: =SUM(D24:D35) -> 24.4
A37: Margem | B37: 0.55 | C37: =D36*B37 -> 13.42 | D37: =D36+C37 -> 37.82
A38: Pesquisa | B38: Elo 7 | C38: Elo 7 - 111p
A39: Valor | B39: 68 | C39: 85 | D39: 50
A41: Agenda Escolar 1 dia | D41: 45
A42: =Referencias!B58 -> Papelão 16x22 | B42: 2 | C42: =Referencias!F58 -> 1.5 | D42: =B42*C42 -> 3
A43: =Referencias!B53 -> Papel fotografico A4 | B43: 2 | C43: =Referencias!F53 -> 0.8 | D43: =B43*C43 -> 1.6
A44: =Referencias!B31 -> bopp | B44: =0.3*2 -> 0.6 | C44: =Referencias!F31 -> 0.45 | D44: =B44*C44 -> 0.27
A45: =Referencias!B48 -> Papel guarda 15,5x21,5 offset adesivo | B45: 2 | C45: =Referencias!F48 -> 0.75 | D45: =B45*C45 -> 1.5
A46: =Referencias!B40 -> miolo 75gr A5 | B46: 109 | C46: =Referencias!F40 -> 0.03 | D46: =B46*C46 -> 3.27
A47: =Referencias!B117 -> Envelope Canguru 15x21 | B47: 1 | C47: =Referencias!F117 -> 1.97 | D47: =B47*C47 -> 1.97
A48: =Referencias!B19 -> Espiral 29mm | B48: 1 | C48: =Referencias!F19 -> 1.83 | D48: =B48*C48 -> 1.83
A49: =Referencias!B22 -> Impressao Capa A4 | B49: 2 | C49: =Referencias!F22 -> 0.5 | D49: =B49*C49 -> 1
A50: =Referencias!B29 -> Impressao Miolo Frente Verso A5 | B50: 109 | C50: =Referencias!F29 -> 0.06 | D50: =B50*C50 -> 6.54
A51: =Referencias!B62 -> Frete | C51: =Referencias!F62 -> 0 | D51: =B51*C51 -> 0
A52: =Referencias!B13 -> Desgaste Agenda | B52: 1 | C52: =Referencias!F13 -> 1 | D52: =B52*C52 -> 1
A53: =Referencias!B17 -> Embalagem Padrão | B53: 1 | C53: =Referencias!F17 -> 1.5 | D53: =B53*C53 -> 1.5
A54: Custo | D54: =SUM(D42:D53) -> 23.48
A55: Margem | B55: 0.55 | C55: =D54*B55 -> 12.914 | D55: =D54+C55 -> 36.394
A56: Pesquisa | B56: MP mimos | C56: Praper
A57: Valor | B57: 55 | C57: 49 | D57: 45
A59: Agenda Escolar 2 dias | D59: 35
A60: =Referencias!B58 -> Papelão 16x22 | B60: 2 | C60: =Referencias!F58 -> 1.5 | D60: =B60*C60 -> 3
A61: =Referencias!B53 -> Papel fotografico A4 | B61: 2 | C61: =Referencias!F53 -> 0.8 | D61: =B61*C61 -> 1.6
A62: =Referencias!B31 -> bopp | B62: =0.3*2 -> 0.6 | C62: =Referencias!F31 -> 0.45 | D62: =B62*C62 -> 0.27
A63: =Referencias!B48 -> Papel guarda 15,5x21,5 offset adesivo | B63: 2 | C63: =Referencias!F48 -> 0.75 | D63: =B63*C63 -> 1.5
A64: =Referencias!B45 -> miolo 90gr A5 | B64: 57 | C64: =Referencias!F45 -> 0.05 | D64: =B64*C64 -> 2.85
A65: =Referencias!B117 -> Envelope Canguru 15x21 | B65: 1 | C65: =Referencias!F117 -> 1.97 | D65: =B65*C65 -> 1.97
A66: =Referencias!B69 -> Espiral 20mm | B66: 1 | C66: =Referencias!F69 -> 0.64 | D66: =B66*C66 -> 0.64
A67: =Referencias!B22 -> Impressao Capa A4 | B67: 2 | C67: =Referencias!F22 -> 0.5 | D67: =B67*C67 -> 1
A68: =Referencias!B29 -> Impressao Miolo Frente Verso A5 | B68: 57 | C68: =Referencias!F29 -> 0.06 | D68: =B68*C68 -> 3.42
A69: =Referencias!B62 -> Frete | C69: =Referencias!F62 -> 0 | D69: =B69*C69 -> 0
A70: =Referencias!B13 -> Desgaste Agenda | B70: 1 | C70: =Referencias!F13 -> 1 | D70: =B70*C70 -> 1
A71: =Referencias!B17 -> Embalagem Padrão | B71: 1 | C71: =Referencias!F17 -> 1.5 | D71: =B71*C71 -> 1.5
A72: Custo | D72: =SUM(D60:D71) -> 18.75
A73: Margem | B73: 0.55 | C73: =D72*B73 -> 10.3125 | D73: =D72+C73 -> 29.0625
A74: Pesquisa | B74: MP mimos | C74: Prapper
A75: Valor | B75: 39 | C75: 39 | D75: 35
A77: Desk Planner | D77: 40
A78: =Referencias!B58 -> Papelão 16x22 | B78: 2 | C78: =Referencias!F58 -> 1.5 | D78: =B78*C78 -> 3
A79: =Referencias!B53 -> Papel fotografico A4 | B79: 2 | C79: =Referencias!F53 -> 0.8 | D79: =B79*C79 -> 1.6
A80: =Referencias!B31 -> bopp | B80: =0.3*2 -> 0.6 | C80: =Referencias!F31 -> 0.45 | D80: =B80*C80 -> 0.27
A81: =Referencias!B48 -> Papel guarda 15,5x21,5 offset adesivo | B81: 2 | C81: =Referencias!F48 -> 0.75 | D81: =B81*C81 -> 1.5
A82: =Referencias!B45 -> miolo 90gr A5 | B82: 61 | C82: =Referencias!F45 -> 0.05 | D82: =B82*C82 -> 3.05
A83: =Referencias!B117 -> Envelope Canguru 15x21 | B83: 1 | C83: =Referencias!F117 -> 1.97 | D83: =B83*C83 -> 1.97
A84: =Referencias!B69 -> Espiral 20mm | B84: 1 | C84: =Referencias!F69 -> 0.64 | D84: =B84*C84 -> 0.64
A85: =Referencias!B22 -> Impressao Capa A4 | B85: 2 | C85: =Referencias!F22 -> 0.5 | D85: =B85*C85 -> 1
A86: =Referencias!B29 -> Impressao Miolo Frente Verso A5 | B86: 61 | C86: =Referencias!F29 -> 0.06 | D86: =B86*C86 -> 3.66
A87: =Referencias!B62 -> Frete | C87: =Referencias!F62 -> 0 | D87: =B87*C87 -> 0
A88: =Referencias!B16 -> Desgaste Planner/Album/Caderno Universitario | B88: 1 | C88: =Referencias!F16 -> 3 | D88: =B88*C88 -> 3
A89: =Referencias!B17 -> Embalagem Padrão | B89: 1 | C89: =Referencias!F17 -> 1.5 | D89: =B89*C89 -> 1.5
A90: Custo | D90: =SUM(D78:D89) -> 21.19
A91: Margem | B91: 0.55 | C91: =D90*B91 -> 11.6545 | D91: =D90+C91 -> 32.8445
A92: Pesquisa | B92: MP mimos
A93: Valor | B93: 42.9 | D93: 40
A95: Caderno A5 | D95: 45
A96: =Referencias!B58 -> Papelão 16x22 | B96: 2 | C96: =Referencias!F58 -> 1.5 | D96: =B96*C96 -> 3
A97: =Referencias!B53 -> Papel fotografico A4 | B97: 2 | C97: =Referencias!F53 -> 0.8 | D97: =B97*C97 -> 1.6
A98: =Referencias!B31 -> bopp | B98: =0.3*2 -> 0.6 | C98: =Referencias!F31 -> 0.45 | D98: =B98*C98 -> 0.27
A99: =Referencias!B48 -> Papel guarda 15,5x21,5 offset adesivo | B99: 2 | C99: =Referencias!F48 -> 0.75 | D99: =B99*C99 -> 1.5
A100: =Referencias!B45 -> miolo 90gr A5 | B100: 50 | C100: =Referencias!F45 -> 0.05 | D100: =B100*C100 -> 2.5
A101: =Referencias!B19 -> Espiral 29mm | B101: 1 | C101: =Referencias!F19 -> 1.83 | D101: =B101*C101 -> 1.83
A102: =Referencias!B22 -> Impressao Capa A4 | B102: 2 | C102: =Referencias!F22 -> 0.5 | D102: =B102*C102 -> 1
A103: =Referencias!B29 -> Impressao Miolo Frente Verso A5 | B103: 50 | C103: =Referencias!F29 -> 0.06 | D103: =B103*C103 -> 3
A104: =Referencias!B62 -> Frete | B104: 0 | C104: =Referencias!F62 -> 0 | D104: =B104*C104 -> 0
A105: =Referencias!B15 -> Desgaste Caderno A5 | B105: 1 | C105: =Referencias!F15 -> 2 | D105: =B105*C105 -> 2
A106: =Referencias!B17 -> Embalagem Padrão | B106: 1 | C106: =Referencias!F17 -> 1.5 | D106: =B106*C106 -> 1.5
...

Sheet Coleção25
A1: Agenda 1 dia datada | D1: 79.9
A2: =Referencias!B58 -> Papelão 16x22 | B2: 2 | C2: =Referencias!F58 -> 1.5 | D2: =B2*C2 -> 3
A3: =Referencias!B53 -> Papel fotografico A4 | B3: 2 | C3: =Referencias!F53 -> 0.8 | D3: =B3*C3 -> 1.6
A4: =Referencias!B31 -> bopp | B4: =0.3*2 -> 0.6 | C4: =Referencias!F31 -> 0.45 | D4: =B4*C4 -> 0.27
A5: =Referencias!B48 -> Papel guarda 15,5x21,5 offset adesivo | B5: 2 | C5: =Referencias!F48 -> 0.75 | D5: =B5*C5 -> 1.5
A6: =Referencias!B40 -> miolo 75gr A5 | B6: 204 | C6: =Referencias!F40 -> 0.03 | D6: =B6*C6 -> 6.12
A7: =Referencias!B215 -> Color plus metalico Aspen 120g A4 | B7: 1 | C7: =Referencias!F215 -> 0.7 | D7: =B7*C7 -> 0.7
A8: =Referencias!B120 -> Espiral 33mm plastico | B8: 1 | C8: =Referencias!F120 -> 2.48 | D8: =B8*C8 -> 2.48
A9: =Referencias!B22 -> Impressao Capa A4 | B9: 2 | C9: =Referencias!F22 -> 0.5 | D9: =B9*C9 -> 1
A10: =Referencias!B29 -> Impressao Miolo Frente Verso A5 | B10: 204 | C10: =Referencias!F29 -> 0.06 | D10: =B10*C10 -> 12.24
A11: =Referencias!B62 -> Frete | C11: =Referencias!F62 -> 0 | D11: =B11*C11 -> 0
A12: =Referencias!B13 -> Desgaste Agenda | B12: 1 | C12: =Referencias!F13 -> 1 | D12: =B12*C12 -> 1
A13: =Referencias!B17 -> Embalagem Padrão | B13: 1 | C13: =Referencias!F17 -> 1.5 | D13: =B13*C13 -> 1.5
A14: Custo | D14: =SUM(D2:D13) -> 31.41
A15: Margem | B15: 0.55 | C15: =D14*B15 -> 17.2755 | D15: =D14+C15 -> 48.6855
A16: Pesquisa | B16: praper | C16: mp
A17: Valor | B17: 69 | C17: 75 | D17: 89.9
A19: Agenda 2 dias datada | D19: 55.9
A20: =Referencias!B57 -> Papelão 15x18,5 | B20: 2 | C20: =Referencias!F57 -> 1.5 | D20: =B20*C20 -> 3
A21: =Referencias!B53 -> Papel fotografico A4 | B21: 2 | C21: =Referencias!F53 -> 0.8 | D21: =B21*C21 -> 1.6
A22: =Referencias!B31 -> bopp | B22: =0.3*2 -> 0.6 | C22: =Referencias!F31 -> 0.45 | D22: =B22*C22 -> 0.27
A23: =Referencias!B47 -> Papel guarda 14,5x18 offset adesivo | B23: 2 | C23: =Referencias!F47 -> 0.75 | D23: =B23*C23 -> 1.5
A24: =Referencias!B46 -> miolo 90gr A5 14x18 | B24: 114 | C24: =Referencias!F46 -> 0.05 | D24: =B24*C24 -> 5.7
A25: =Referencias!B215 -> Color plus metalico Aspen 120g A4 | B25: 1 | C25: =Referencias!F215 -> 0.7 | D25: =B25*C25 -> 0.7
A26: =Referencias!B19 -> Espiral 29mm | B26: 1 | C26: =Referencias!F19 -> 1.83 | D26: =B26*C26 -> 1.83
A27: =Referencias!B22 -> Impressao Capa A4 | B27: 2 | C27: =Referencias!F22 -> 0.5 | D27: =B27*C27 -> 1
A28: =Referencias!B29 -> Impressao Miolo Frente Verso A5 | B28: 114 | C28: =Referencias!F29 -> 0.06 | D28: =B28*C28 -> 6.84
A29: =Referencias!B62 -> Frete | C29: =Referencias!F62 -> 0 | D29: =B29*C29 -> 0
A30: =Referencias!B13 -> Desgaste Agenda | B30: 1 | C30: =Referencias!F13 -> 1 | D30: =B30*C30 -> 1
A31: =Referencias!B17 -> Embalagem Padrão | B31: 1 | C31: =Referencias!F17 -> 1.5 | D31: =B31*C31 -> 1.5
A32: Custo | D32: =SUM(D20:D31) -> 24.94
A33: Margem | B33: 0.55 | C33: =D32*B33 -> 13.717 | D33: =D32+C33 -> 38.657
A34: Pesquisa | B34: praper | C34: mp
A35: Valor | B35: 54.9 | C35: 59 | D35: 65.9
A37: Agenda Agendamento | D37: 85.9
A38: =Referencias!B58 -> Papelão 16x22 | B38: 2 | C38: =Referencias!F58 -> 1.5 | D38: =B38*C38 -> 3
A39: =Referencias!B53 -> Papel fotografico A4 | B39: 2 | C39: =Referencias!F53 -> 0.8 | D39: =B39*C39 -> 1.6
A40: =Referencias!B31 -> bopp | B40: =0.3*2 -> 0.6 | C40: =Referencias!F31 -> 0.45 | D40: =B40*C40 -> 0.27
A41: =Referencias!B48 -> Papel guarda 15,5x21,5 offset adesivo | B41: 2 | C41: =Referencias!F48 -> 0.75 | D41: =B41*C41 -> 1.5
A42: =Referencias!B40 -> miolo 75gr A5 | B42: 209 | C42: =Referencias!F40 -> 0.03 | D42: =B42*C42 -> 6.27
A43: =Referencias!B215 -> Color plus metalico Aspen 120g A4 | B43: 1 | C43: =Referencias!F215 -> 0.7 | D43: =B43*C43 -> 0.7
A44: =Referencias!B120 -> Espiral 33mm plastico | B44: 1 | C44: =Referencias!F120 -> 2.48 | D44: =B44*C44 -> 2.48
A45: =Referencias!B22 -> Impressao Capa A4 | B45: 2 | C45: =Referencias!F22 -> 0.5 | D45: =B45*C45 -> 1
A46: =Referencias!B29 -> Impressao Miolo Frente Verso A5 | B46: 209 | C46: =Referencias!F29 -> 0.06 | D46: =B46*C46 -> 12.54
A47: =Referencias!B62 -> Frete | C47: =Referencias!F62 -> 0 | D47: =B47*C47 -> 0
A48: =Referencias!B13 -> Desgaste Agenda | B48: 1 | C48: =Referencias!F13 -> 1 | D48: =B48*C48 -> 1
A49: =Referencias!B17 -> Embalagem Padrão | B49: 1 | C49: =Referencias!F17 -> 1.5 | D49: =B49*C49 -> 1.5
A50: Custo | D50: =SUM(D38:D49) -> 31.86
A51: Margem | B51: 0.55 | C51: =D50*B51 -> 17.523 | D51: =D50+C51 -> 49.383
A52: Pesquisa | B52: praper
A53: Valor | B53: 84.9 | D53: 85.9
A55: Calendario A5 | D55: 25
A56: =Referencias!B56 -> Papelão 15,5x21,5+2,5x21,5 | B56: 2 | C56: =Referencias!F56 -> 1.5 | D56: =B56*C56 -> 3
A57: =Referencias!B53 -> Papel fotografico A4 | B57: 2 | C57: =Referencias!F53 -> 0.8 | D57: =B57*C57 -> 1.6
A58: =Referencias!B31 -> bopp | B58: =0.3*2 -> 0.6 | C58: =Referencias!F31 -> 0.45 | D58: =B58*C58 -> 0.27
A59: =Referencias!B50 -> Papel guarda 20x20 offset adesivo | B59: 2 | C59: =Referencias!F50 -> 0.75 | D59: =B59*C59 -> 1.5
A60: =Referencias!B36 -> miolo 180g A5 | B60: 12 | C60: =Referencias!F36 -> 0.16 | D60: =B60*C60 -> 1.92
A61: =Referencias!B18 -> Espiral 17mm | B61: 1 | C61: =Referencias!F18 -> 0.52 | D61: =B61*C61 -> 0.52
A62: =Referencias!B22 -> Impressao Capa A4 | B62: 2 | C62: =Referencias!F22 -> 0.5 | D62: =B62*C62 -> 1
A63: =Referencias!B29 -> Impressao Miolo Frente Verso A5 | B63: 12 | C63: =Referencias!F29 -> 0.06 | D63: =B63*C63 -> 0.72
A64: =Referencias!B62 -> Frete | C64: =Referencias!F62 -> 0 | D64: =B64*C64 -> 0
A65: =Referencias!B14 -> Desgaste Bloquinho/Outros | B65: 1 | C65: =Referencias!F14 -> 0.5 | D65: =B65*C65 -> 0.5
A66: =Referencias!B17 -> Embalagem Padrão | B66: 1 | C66: =Referencias!F17 -> 1.5 | D66: =B66*C66 -> 1.5
A67: Custo | D67: =SUM(D56:D66) -> 12.53
A68: Margem | B68: 0.55 | C68: =D67*B68 -> 6.8915 | D68: =D67+C68 -> 19.4215
A69: Pesquisa | B69: praper
A70: Valor | B70: 24.9 | D70: 25
A72: Calendário Comercial | D72: 15
A73: =Referencias!B65 -> Papelão A4 | B73: 1 | C73: =Referencias!F65 -> 1.5 | D73: =B73*C73 -> 1.5
A74: =Referencias!B53 -> Papel fotografico A4 | B74: 1 | C74: =Referencias!F53 -> 0.8 | D74: =B74*C74 -> 0.8
A75: =Referencias!B31 -> bopp | B75: =0.3 -> 0.3 | C75: =Referencias!F31 -> 0.45 | D75: =B75*C75 -> 0.135
A76: =Referencias!B50 -> Papel guarda 20x20 offset adesivo | B76: 1 | C76: =Referencias!F50 -> 0.75 | D76: =B76*C76 -> 0.75
A77: =Referencias!B37 -> miolo 180gr A4 | B77: 3 | C77: =Referencias!F37 -> 0.32 | D77: =B77*C77 -> 0.96
A78: =Referencias!B18 -> Espiral 17mm | B78: 1 | C78: =Referencias!F18 -> 0.52 | D78: =B78*C78 -> 0.52
A79: =Referencias!B22 -> Impressao Capa A4 | B79: 1 | C79: =Referencias!F22 -> 0.5 | D79: =B79*C79 -> 0.5
A80: =Referencias!B28 -> Impressao Miolo Frente Verso A4 | B80: 3 | C80: =Referencias!F28 -> 0.12 | D80: =B80*C80 -> 0.36
A81: =Referencias!B62 -> Frete | B81: 0 | C81: =Referencias!F62 -> 0 | D81: =B81*C81 -> 0
A82: =Referencias!B14 -> Desgaste Bloquinho/Outros | B82: 1 | C82: =Referencias!F14 -> 0.5 | D82: =B82*C82 -> 0.5
A83: =Referencias!B17 -> Embalagem Padrão | B83: 1 | C83: =Referencias!F17 -> 1.5 | D83: =B83*C83 -> 1.5
A84: Custo | D84: =SUM(D73:D83) -> 7.525
A85: Margem | B85: 0.55 | C85: =D84*B85 -> 4.13875 | D85: =D84+C85 -> 11.66375
A86: Pesquisa | B86: praper | C86: mp
A87: Valor | B87: 18.9 | C87: 11.9 | D87: 15
A89: Calendario 10x10 | D89: 15
A90: =Referencias!B61 -> Papelão 9,5x10,5+9,5x2 | B90: 2 | C90: =Referencias!F61 -> 1.5 | D90: =B90*C90 -> 3
A91: =Referencias!B53 -> Papel fotografico A4 | B91: 1 | C91: =Referencias!F53 -> 0.8 | D91: =B91*C91 -> 0.8
A92: =Referencias!B51 -> Papel offset adesivo + guarda | B92: 1 | C92: =Referencias!F51 -> 0.75 | D92: =B92*C92 -> 0.75
A93: =Referencias!B31 -> bopp | B93: =0.3 -> 0.3 | C93: =Referencias!F31 -> 0.45 | D93: =B93*C93 -> 0.135
A94: =Referencias!B37 -> miolo 180gr A4 | B94: 3 | C94: =Referencias!F37 -> 0.32 | D94: =B94*C94 -> 0.96
A95: =Referencias!B18 -> Espiral 17mm | B95: 0.34 | C95: =Referencias!F18 -> 0.52 | D95: =B95*C95 -> 0.1768
A96: =Referencias!B22 -> Impressao Capa A4 | B96: 1 | C96: =Referencias!F22 -> 0.5 | D96: =B96*C96 -> 0.5
A97: =Referencias!B63 -> Impressao Miolo Frente A4 | B97: 3 | C97: =Referencias!F63 -> 0.06 | D97: =B97*C97 -> 0.18
A98: =Referencias!B62 -> Frete | B98: 0 | C98: =Referencias!F62 -> 0 | D98: =B98*C98 -> 0
A99: =Referencias!B14 -> Desgaste Bloquinho/Outros | B99: 1 | C99: =Referencias!F14 -> 0.5 | D99: =B99*C99 -> 0.5
A100: =Referencias!B17 -> Embalagem Padrão | B100: 1 | C100: =Referencias!F17 -> 1.5 | D100: =B100*C100 -> 1.5
A101: Custo | D101: =SUM(D90:D100) -> 8.5018
A102: Margem | B102: 0.55 | C102: =D101*B102 -> 4.67599 | D102: =D101+C102 -> 13.17779
A103: Pesquisa | B103: praper | C103: mp
A104: Valor | B104: 18.9 | C104: 11.9 | D104: 15
A106: Planner Kraft A5 Bordado | D106: 30
...

Sheet Dininha
A1: Jogo da Memória | D1: 15
A2: =Referencias!B65 -> Papelão A4 | B2: 1 | C2: =Referencias!F65 -> 1.5 | D2: =B2*C2 -> 1.5
A3: =Referencias!B53 -> Papel fotografico A4 | B3: 1 | C3: =Referencias!F53 -> 0.8 | D3: =B3*C3 -> 0.8
A4: =Referencias!B31 -> bopp | B4: 0.3 | C4: =Referencias!F31 -> 0.45 | D4: =B4*C4 -> 0.135
A5: =Referencias!B52 -> Papel offset adesivo A4 | B5: 1 | C5: =Referencias!F52 -> 0.75 | D5: =B5*C5 -> 0.75
A6: =Referencias!B38 -> Papel 240g A4 | B6: 1 | C6: =Referencias!F38 -> 0.42 | D6: =B6*C6 -> 0.42
A7: =Referencias!B22 -> Impressao Capa A4 | B7: 4 | C7: =Referencias!F22 -> 0.5 | D7: =B7*C7 -> 2
A8: =Referencias!B62 -> Frete | C8: =Referencias!F62 -> 0 | D8: =B8*C8 -> 0
A9: =Referencias!B14 -> Desgaste Bloquinho/Outros | B9: 1 | C9: =Referencias!F14 -> 0.5 | D9: =B9*C9 -> 0.5
A10: =Referencias!B17 -> Embalagem Padrão | B10: 1 | C10: =Referencias!F17 -> 1.5 | D10: =B10*C10 -> 1.5
A11: Custo | D11: =SUM(D2:D10) -> 7.605
A12: Margem | B12: 0.55 | C12: =D11*B12 -> 4.18275 | D12: =D11+C12 -> 11.78775
A13: Pesquisa
A14: Valor | D14: 15

Sheet Kraft
A1: Bloco Kraft 10x10 bordado espiral pautado | D1: 10
A2: =Referencias!B196 -> Papel Kraft 10,5x9,5 | B2: 2 | C2: =Referencias!F196 -> 0.09 | D2: =B2*C2 -> 0.18
A3: =Referencias!B197 -> Sulfite 90gr 9x9 | B3: 50 | C3: =Referencias!F197 -> 0.03 | D3: =B3*C3 -> 1.5
A4: =Referencias!B199 -> Espiral 14mm | B4: 0.3 | C4: =Referencias!F199 -> 0.42 | D4: =B4*C4 -> 0.126
A5: =Referencias!B198 -> Impressao Miolo Frente Verso 9x9 | B5: 50 | C5: =Referencias!F198 -> 0.02 | D5: =B5*C5 -> 1
A6: =Referencias!B88 -> Linha Circulo Maxi Mouline | B6: 2 | C6: =Referencias!F88 -> 0.18 | D6: =B6*C6 -> 0.36
A7: =Referencias!B62 -> Frete | C7: =Referencias!F62 -> 0 | D7: =B7*C7 -> 0
A8: =Referencias!B14 -> Desgaste Bloquinho/Outros | B8: 1 | C8: =Referencias!F14 -> 0.5 | D8: =B8*C8 -> 0.5
A9: =Referencias!B17 -> Embalagem Padrão | B9: 1 | C9: =Referencias!F17 -> 1.5 | D9: =B9*C9 -> 1.5
A10: Custo | D10: =SUM(D2:D9) -> 5.166
A11: Margem | B11: 0.55 | C11: =D10*B11 -> 2.8413 | D11: =D10+C11 -> 8.0073
A12: Pesquisa | B12: Feito Folhas
A13: Valor | B13: 20 | D13: 10
A15: Caderno Kraft A6 bordado | D15: 20
A16: =Referencias!B55 -> Papel Kraft A5 | B16: 1 | C16: =Referencias!F55 -> 0.27 | D16: =B16*C16 -> 0.27
A17: =Referencias!B42 -> Sulfite 75g A5 | B17: 25 | C17: =Referencias!F42 -> 0.03 | D17: =B17*C17 -> 0.75
A18: =Referencias!B5 -> Cordão Encerado Settanyl | B18: 0.6 | C18: =Referencias!F5 -> 0.16 | D18: =B18*C18 -> 0.096
A19: =Referencias!B88 -> Linha Circulo Maxi Mouline | B19: 2 | C19: =Referencias!F88 -> 0.18 | D19: =B19*C19 -> 0.36
A20: =Referencias!B62 -> Frete | C20: =Referencias!F62 -> 0 | D20: =B20*C20 -> 0
A21: =Referencias!B15 -> Desgaste Caderno A5 | B21: 1 | C21: =Referencias!F15 -> 2 | D21: =B21*C21 -> 2
A22: =Referencias!B17 -> Embalagem Padrão | B22: 1 | C22: =Referencias!F17 -> 1.5 | D22: =B22*C22 -> 1.5
A23: Custo | D23: =SUM(D16:D22) -> 4.976
A24: Margem | B24: 0.55 | C24: =D23*B24 -> 2.7368 | D24: =D23+C24 -> 7.7128
A25: Pesquisa | B25: Feito Folhas
A26: Valor | B26: 20 | D26: 20
A28: Caderno Kraft A5 bordado | D28: 25
A29: =Referencias!B54 -> Papel Kraft A4 | B29: 1 | C29: =Referencias!F54 -> 0.54 | D29: =B29*C29 -> 0.54
A30: =Referencias!B41 -> Sulfite 75g A4 | B30: 30 | C30: =Referencias!F41 -> 0.06 | D30: =B30*C30 -> 1.8
A31: =Referencias!B5 -> Cordão Encerado Settanyl | B31: 1.2 | C31: =Referencias!F5 -> 0.16 | D31: =B31*C31 -> 0.192
A32: =Referencias!B88 -> Linha Circulo Maxi Mouline | B32: 4 | C32: =Referencias!F88 -> 0.18 | D32: =B32*C32 -> 0.72
A33: =Referencias!B62 -> Frete | C33: =Referencias!F62 -> 0 | D33: =B33*C33 -> 0
A34: =Referencias!B15 -> Desgaste Caderno A5 | B34: 1 | C34: =Referencias!F15 -> 2 | D34: =B34*C34 -> 2
A35: =Referencias!B17 -> Embalagem Padrão | B35: 1 | C35: =Referencias!F17 -> 1.5 | D35: =B35*C35 -> 1.5
A36: Custo | D36: =SUM(D29:D35) -> 6.752
A37: Margem | B37: 0.55 | C37: =D36*B37 -> 3.7136 | D37: =D36+C37 -> 10.4656
A38: Pesquisa | B38: Feito Folhas
A39: Valor | B39: 35 | D39: 25
A41: Planner Kraft A5 bordado | D41: 30
A42: =Referencias!B54 -> Papel Kraft A4 | B42: 1 | C42: =Referencias!F54 -> 0.54 | D42: =B42*C42 -> 0.54
A43: =Referencias!B41 -> Sulfite 75g A4 | B43: 27 | C43: =Referencias!F41 -> 0.06 | D43: =B43*C43 -> 1.62
A44: =Referencias!B5 -> Cordão Encerado Settanyl | B44: 1.2 | C44: =Referencias!F5 -> 0.16 | D44: =B44*C44 -> 0.192
A45: =Referencias!B88 -> Linha Circulo Maxi Mouline | B45: 4 | C45: =Referencias!F88 -> 0.18 | D45: =B45*C45 -> 0.72
A46: =Referencias!B28 -> Impressao Miolo Frente Verso A4 | B46: 27 | C46: =Referencias!F28 -> 0.12 | D46: =B46*C46 -> 3.24
A47: =Referencias!B62 -> Frete | C47: =Referencias!F62 -> 0 | D47: =B47*C47 -> 0
A48: =Referencias!B14 -> Desgaste Bloquinho/Outros | B48: 1 | C48: =Referencias!F14 -> 0.5 | D48: =B48*C48 -> 0.5
A49: =Referencias!B17 -> Embalagem Padrão | B49: 1 | C49: =Referencias!F17 -> 1.5 | D49: =B49*C49 -> 1.5
A50: Custo | D50: =SUM(D42:D49) -> 8.312
A51: Margem | B51: 0.55 | C51: =D50*B51 -> 4.5716 | D51: =D50+C51 -> 12.8836
A52: Pesquisa
A53: Valor | D53: 30
A55: Cartão Kraft A6 bordado | D55: 15
A56: =Referencias!B55 -> Papel Kraft A5 | B56: 1 | C56: =Referencias!F55 -> 0.27 | D56: =B56*C56 -> 0.27
A57: =Referencias!B142 -> Papel Offset Sulfite 120g A6 | B57: 1 | C57: =Referencias!F142 -> 0.03 | D57: =B57*C57 -> 0.03
A58: =Referencias!B139 -> Envelope 80g visita 115x80 linho branco 5452 Romitec | B58: 1 | C58: =Referencias!F139 -> 0.27 | D58: =B58*C58 -> 0.27
A59: =Referencias!B88 -> Linha Circulo Maxi Mouline | B59: 2 | C59: =Referencias!F88 -> 0.18 | D59: =B59*C59 -> 0.36
A60: =Referencias!B62 -> Frete | C60: =Referencias!F62 -> 0 | D60: =B60*C60 -> 0
A61: =Referencias!B14 -> Desgaste Bloquinho/Outros | B61: 1 | C61: =Referencias!F14 -> 0.5 | D61: =B61*C61 -> 0.5
A62: =Referencias!B17 -> Embalagem Padrão | B62: 1 | C62: =Referencias!F17 -> 1.5 | D62: =B62*C62 -> 1.5
A63: Custo | D63: =SUM(D56:D62) -> 2.93
A64: Margem | B64: 0.55 | C64: =D63*B64 -> 1.6115 | D64: =D63+C64 -> 4.5415
A65: Pesquisa
A66: Valor | D66: 15
A68: Marcador de Páginas Kraft bordado | D68: 10
A69: =Referencias!B146 -> Papel Kraft 20x5 | B69: 1 | C69: =Referencias!F146 -> 0.09 | D69: =B69*C69 -> 0.09
A70: =Referencias!B88 -> Linha Circulo Maxi Mouline | B70: 2 | C70: =Referencias!F88 -> 0.18 | D70: =B70*C70 -> 0.36
A71: =Referencias!B154 -> Color Plus 20x5 | B71: 1 | C71: =Referencias!F154 -> 0.1 | D71: =B71*C71 -> 0.1
A72: =Referencias!B155 -> Tassel | B72: 1 | C72: =Referencias!F155 -> 0.38 | D72: =B72*C72 -> 0.38
A73: =Referencias!B62 -> Frete | C73: =Referencias!F62 -> 0 | D73: =B73*C73 -> 0
A74: =Referencias!B14 -> Desgaste Bloquinho/Outros | B74: 1 | C74: =Referencias!F14 -> 0.5 | D74: =B74*C74 -> 0.5
A75: =Referencias!B17 -> Embalagem Padrão | B75: 1 | C75: =Referencias!F17 -> 1.5 | D75: =B75*C75 -> 1.5
A76: Custo | D76: =SUM(D69:D75) -> 2.93
A77: Margem | B77: 0.55 | C77: =D76*B77 -> 1.6115 | D77: =D76+C77 -> 4.5415
A78: Pesquisa
A79: Valor | D79: 10
A81: Mini Cartão Kraft A6 bordado | D81: 5
A82: =Referencias!B151 -> Papel Kraft A7 | B82: 1 | C82: =Referencias!F151 -> 0.07 | D82: =B82*C82 -> 0.07
A83: =Referencias!B88 -> Linha Circulo Maxi Mouline | B83: 2 | C83: =Referencias!F88 -> 0.18 | D83: =B83*C83 -> 0.36
A84: =Referencias!B152 -> Sulfite 75g A8 | B84: 1 | C84: =Referencias!F152 -> 0.01 | D84: =B84*C84 -> 0.01
A85: =Referencias!B62 -> Frete | C85: =Referencias!F62 -> 0 | D85: =B85*C85 -> 0
A86: =Referencias!B14 -> Desgaste Bloquinho/Outros | B86: 1 | C86: =Referencias!F14 -> 0.5 | D86: =B86*C86 -> 0.5
A87: =Referencias!B17 -> Embalagem Padrão | B87: 1 | C87: =Referencias!F17 -> 1.5 | D87: =B87*C87 -> 1.5
A88: Custo | D88: =SUM(D82:D87) -> 2.44
A89: Margem | B89: 0.55 | C89: =D88*B89 -> 1.342 | D89: =D88+C89 -> 3.782
A90: Pesquisa
A91: Valor | D91: 5

Sheet Couro
A1: Caderno Amor | D1: 50
A2: =Referencias!B206 -> Couro 16 cm x 11 cm | B2: 40 | C2: =Referencias!F206 -> 0.02 | D2: =B2*C2 -> 0.8
A3: =Referencias!B207 -> Couro 9 cm x 2 cm | B3: 3 | C3: =Referencias!F207 -> 0.02 | D3: =B3*C3 -> 0.06
A4: =Referencias!B144 -> Papel Kraft A6 | B4: 2 | C4: =Referencias!F144 -> 0.13 | D4: =B4*C4 -> 0.26
A5: =Referencias!B205 -> Pólen Bold - 90 g/m2 - A5 | B5: 42 | C5: =Referencias!F205 -> 0.07 | D5: =B5*C5 -> 2.94
A6: =Referencias!B5 -> Cordão Encerado Settanyl | B6: 2 | C6: =Referencias!F5 -> 0.16 | D6: =B6*C6 -> 0.32
A7: =Referencias!B94 -> Cola Branca 1kg | B7: 40 | C7: =Referencias!F88 -> 0.18 | D7: =B7*C7 -> 7.2
A8: =Referencias!B62 -> Frete | C8: =Referencias!F62 -> 0 | D8: =B8*C8 -> 0
A9: =Referencias!B14 -> Desgaste Bloquinho/Outros | B9: 1 | C9: =Referencias!F14 -> 0.5 | D9: =B9*C9 -> 0.5
A10: =Referencias!B17 -> Embalagem Padrão | B10: 1 | C10: =Referencias!F17 -> 1.5 | D10: =B10*C10 -> 1.5
A11: Custo | D11: =SUM(D2:D10) -> 13.58
A12: Margem | B12: 0.55 | C12: =D11*B12 -> 7.469 | D12: =D11+C12 -> 21.049
A13: Pesquisa | B13: Te
A14: Valor | B14: 50 | C14: 80 | D14: 50
A16: Caderno Leveza | D16: 45
A17: =Referencias!B208 -> Couro 15 cm x 28 cm | B17: 20 | C17: =Referencias!F208 -> 0.02 | D17: =B17*C17 -> 0.4
A18: =Referencias!B209 -> Couro 1,5 cm x 30 cm | B18: 9 | C18: =Referencias!F209 -> 0.02 | D18: =B18*C18 -> 0.18
A19: =Referencias!B210 -> Puxador De Metal Carrapeta 7mmx5mm | B19: 1 | C19: =Referencias!F210 -> 3.3 | D19: =B19*C19 -> 3.3
A20: =Referencias!B205 -> Pólen Bold - 90 g/m2 - A5 | B20: 30 | C20: =Referencias!F205 -> 0.07 | D20: =B20*C20 -> 2.1
A21: =Referencias!B5 -> Cordão Encerado Settanyl | B21: 0.6 | C21: =Referencias!F5 -> 0.16 | D21: =B21*C21 -> 0.096
A22: =Referencias!B94 -> Cola Branca 1kg | B22: 10 | C22: =Referencias!F94 -> 0.04 | D22: =B22*C22 -> 0.4
A23: =Referencias!B62 -> Frete | C23: =Referencias!F62 -> 0 | D23: =B23*C23 -> 0
A24: =Referencias!B14 -> Desgaste Bloquinho/Outros | B24: 1 | C24: =Referencias!F14 -> 0.5 | D24: =B24*C24 -> 0.5
A25: =Referencias!B17 -> Embalagem Padrão | B25: 1 | C25: =Referencias!F17 -> 1.5 | D25: =B25*C25 -> 1.5
A26: Custo | D26: =SUM(D17:D25) -> 8.476
A27: Margem | B27: 0.55 | C27: =D26*B27 -> 4.6618 | D27: =D26+C27 -> 13.1378
A28: Pesquisa | B28: Te
A29: Valor⁴ | B29: 50 | C29: 80 | D29: 45
A31: Caderno Liberdade | D31: 55
A32: =Referencias!B211 -> Couro 15 cm x 32 cm | B32: 38 | C32: =Referencias!F211 -> 0.02 | D32: =B32*C32 -> 0.76
A33: =Referencias!B212 -> Couro 15 cm x 3,5 cm | B33: 12 | C33: =Referencias!F212 -> 0.02 | D33: =B33*C33 -> 0.24
A34: =Referencias!B213 -> Couro 15 cm x 9 cm | B34: 10 | C34: =Referencias!F213 -> 0.02 | D34: =B34*C34 -> 0.2
A35: =Referencias!B205 -> Pólen Bold - 90 g/m2 - A5 | B35: 42 | C35: =Referencias!F205 -> 0.07 | D35: =B35*C35 -> 2.94
A36: =Referencias!B214 -> Ímã Neodímio Ø 20x1 mm N35 | B36: 2 | C36: =Referencias!F214 -> 2.87 | D36: =B36*C36 -> 5.74
A37: =Referencias!B5 -> Cordão Encerado Settanyl | B37: 2.1 | C37: =Referencias!F5 -> 0.16 | D37: =B37*C37 -> 0.336
A38: =Referencias!B94 -> Cola Branca 1kg | B38: 20 | C38: =Referencias!F94 -> 0.04 | D38: =B38*C38 -> 0.8
A39: =Referencias!B62 -> Frete | C39: =Referencias!F62 -> 0 | D39: =B39*C39 -> 0
A40: =Referencias!B14 -> Desgaste Bloquinho/Outros | B40: 1 | C40: =Referencias!F14 -> 0.5 | D40: =B40*C40 -> 0.5
A41: =Referencias!B17 -> Embalagem Padrão | B41: 1 | C41: =Referencias!F17 -> 1.5 | D41: =B41*C41 -> 1.5
A42: Custo | D42: =SUM(D32:D41) -> 13.016
A43: Margem | B43: 0.55 | C43: =D42*B43 -> 7.1588 | D43: =D42+C43 -> 20.1748
A44: Pesquisa | B44: Te
A45: Valor | B45: 50 | C45: 80 | D45: 55
A47: Colar pingente caderno | D47: 15
A48: =Referencias!B128 -> Couro 7,5 cm x 3 cm | B48: 2 | C48: =Referencias!F128 -> 0.02 | D48: =B48*C48 -> 0.04
A49: =Referencias!B129 -> miolo 75gr 3cm x 5 cm | B49: 10 | C49: =Referencias!F129 -> 0.01 | D49: =B49*C49 -> 0.1
A50: =Referencias!B5 -> Cordão Encerado Settanyl | B50: 0.2 | C50: =Referencias!F5 -> 0.16 | D50: =B50*C50 -> 0.032
A51: =Referencias!B132 -> Argola para Chaveiro | B51: 1 | C51: =Referencias!F132 -> 0.1 | D51: =B51*C51 -> 0.1
A52: =Referencias!B130 -> Cordão cetim | B52: 0.9 | C52: =Referencias!F130 -> 0.21 | D52: =B52*C52 -> 0.189
A53: =Referencias!B131 -> Tira couro fechamento | B53: 0.5 | C53: =Referencias!F131 -> 0.02 | D53: =B53*C53 -> 0.01
A54: =Referencias!B62 -> Frete | C54: =Referencias!F62 -> 0 | D54: =B54*C54 -> 0
A55: =Referencias!B15 -> Desgaste Caderno A5 | B55: 1 | C55: =Referencias!F15 -> 2 | D55: =B55*C55 -> 2
A56: =Referencias!B17 -> Embalagem Padrão | B56: 1 | C56: =Referencias!F17 -> 1.5 | D56: =B56*C56 -> 1.5
A57: Custo | D57: =SUM(D48:D56) -> 3.971
A58: Margem | B58: 0.55 | C58: =D57*B58 -> 2.18405 | D58: =D57+C58 -> 6.15505
A59: Pesquisa
A60: Valor | D60: 15
A62: Agenda de Bolso | D62: 25
A63: =Referencias!B218 -> Couro 22 cm x 8 cm | B63: 20 | C63: =Referencias!F218 -> 0.02 | D63: =B63*C63 -> 0.4
A64: =Referencias!B219 -> Couro 6 cm x 8 cm | B64: 5 | C64: =Referencias!F219 -> 0.02 | D64: =B64*C64 -> 0.1
A65: =Referencias!B219 -> Couro 6 cm x 8 cm | B65: 5 | C65: =Referencias!F219 -> 0.02 | D65: =B65*C65 -> 0.1
A66: =Referencias!B217 -> miolo 90gr A7 | B66: 60 | C66: =Referencias!F217 -> 0.01 | D66: =B66*C66 -> 0.6
A67: =Referencias!B5 -> Cordão Encerado Settanyl | B67: 0.54 | C67: =Referencias!F5 -> 0.16 | D67: =B67*C67 -> 0.0864
A68: =Referencias!B150 -> Impressao Miolo Frente Verso A7 | B68: 60 | C68: =Referencias!F150 -> 0.02 | D68: =B68*C68 -> 1.2
A69: =Referencias!B62 -> Frete | C69: =Referencias!F62 -> 0 | D69: =B69*C69 -> 0
A70: =Referencias!B14 -> Desgaste Bloquinho/Outros | B70: 1 | C70: =Referencias!F14 -> 0.5 | D70: =B70*C70 -> 0.5
A71: =Referencias!B17 -> Embalagem Padrão | B71: 1 | C71: =Referencias!F17 -> 1.5 | D71: =B71*C71 -> 1.5
A72: Custo | D72: =SUM(D63:D71) -> 4.4864
A73: Margem | B73: 0.55 | C73: =D72*B73 -> 2.46752 | D73: =D72+C73 -> 6.95392
A74: Pesquisa
A75: Valor | D75: 25

Sheet Crochê
A1: Descanso de Panela em Croche Malha - Quadrado | D1: 15
A2: =Referencias!B202 -> Fio de Malha Euroroma 140m | B2: 140 | C2: =Referencias!F202 -> 0.02 | D2: =B2*C2 -> 2.8
A3: =Referencias!B62 -> Frete | C3: =Referencias!F62 -> 0 | D3: =B3*C3 -> 0
A4: =Referencias!B14 -> Desgaste Bloquinho/Outros | B4: 1 | C4: =Referencias!F14 -> 0.5 | D4: =B4*C4 -> 0.5
A5: =Referencias!B17 -> Embalagem Padrão | B5: 1 | C5: =Referencias!F17 -> 1.5 | D5: =B5*C5 -> 1.5
A6: Custo | D6: =SUM(D2:D5) -> 4.8
A7: Margem | B7: 0.55 | C7: =D6*B7 -> 2.64 | D7: =D6+C7 -> 7.44
A8: Pesquisa
A9: Valor | D9: 15
A11: Descanso de Panela em Croche Malha - Flor | D11: 15
A12: =Referencias!B202 -> Fio de Malha Euroroma 140m | B12: 140 | C12: =Referencias!F202 -> 0.02 | D12: =B12*C12 -> 2.8
A13: =Referencias!B62 -> Frete | C13: =Referencias!F62 -> 0 | D13: =B13*C13 -> 0
A14: =Referencias!B14 -> Desgaste Bloquinho/Outros | B14: 1 | C14: =Referencias!F14 -> 0.5 | D14: =B14*C14 -> 0.5
A15: =Referencias!B17 -> Embalagem Padrão | B15: 1 | C15: =Referencias!F17 -> 1.5 | D15: =B15*C15 -> 1.5
A16: Custo | D16: =SUM(D12:D15) -> 4.8
A17: Margem | B17: 0.55 | C17: =D16*B17 -> 2.64 | D17: =D16+C17 -> 7.44
A18: Pesquisa
A19: Valor | D19: 15
A21: Descanso de Panela em Croche Malha - Duplo | D21: 20
A22: =Referencias!B202 -> Fio de Malha Euroroma 140m | B22: 250 | C22: =Referencias!F202 -> 0.02 | D22: =B22*C22 -> 5
A23: =Referencias!B62 -> Frete | B23: 0 | C23: =Referencias!F62 -> 0 | D23: =B23*C23 -> 0
A24: =Referencias!B14 -> Desgaste Bloquinho/Outros | B24: 1 | C24: =Referencias!F14 -> 0.5 | D24: =B24*C24 -> 0.5
A25: =Referencias!B17 -> Embalagem Padrão | B25: 1 | C25: =Referencias!F17 -> 1.5 | D25: =B25*C25 -> 1.5
A26: Custo | D26: =SUM(D22:D25) -> 7
A27: Margem | B27: 0.55 | C27: =D26*B27 -> 3.85 | D27: =D26+C27 -> 10.85
A28: Pesquisa
A29: Valor | D29: 20
A31: Fralda com Crochê | D31: 15
A32: =Referencias!B147 -> Fralda Cremer 70x70 | B32: 1 | C32: =Referencias!F147 -> 7.18 | D32: =B32*C32 -> 7.18
A33: =Referencias!B7 -> Fio Clea 1000 160g | B33: 25 | C33: =Referencias!F7 -> 0.11 | D33: =B33*C33 -> 2.75
A34: =Referencias!B80 -> Linha Dinner | B34: 3.5 | C34: =Referencias!F80 -> 0.1 | D34: =B34*C34 -> 0.35
A35: =Referencias!B82 -> Papel Transfer | B35: 0.02 | C35: =Referencias!F82 -> 5.49 | D35: =B35*C35 -> 0.1098
A36: =Referencias!B83 -> Impressão A4 | B36: 0.02 | C36: =Referencias!F83 -> 0.5 | D36: =B36*C36 -> 0.01
A37: =Referencias!B62 -> Frete | C37: =Referencias!F62 -> 0 | D37: =B37*C37 -> 0
A38: =Referencias!B14 -> Desgaste Bloquinho/Outros | B38: 1 | C38: =Referencias!F14 -> 0.5 | D38: =B38*C38 -> 0.5
A39: =Referencias!B17 -> Embalagem Padrão | B39: 1 | C39: =Referencias!F17 -> 1.5 | D39: =B39*C39 -> 1.5
A40: Custo | D40: =SUM(D32:D39) -> 12.3998
A41: Margem | B41: 0.55 | C41: =D40*B41 -> 6.81989 | D41: =D40+C41 -> 19.21969
A42: Pesquisa
A43: Valor | D43: 15
A45: Fralda com Crochê com 12 | D45: 20
A46: =Referencias!B147 -> Fralda Cremer 70x70 | B46: =B32*12 -> 12 | C46: =Referencias!F147 -> 7.18 | D46: =B46*C46 -> 86.16
A47: =Referencias!B7 -> Fio Clea 1000 160g | B47: =B33*12 -> 300 | C47: =Referencias!F7 -> 0.11 | D47: =B47*C47 -> 33
A48: =Referencias!B80 -> Linha Dinner | B48: =B34*12 -> 42 | C48: =Referencias!F80 -> 0.1 | D48: =B48*C48 -> 4.2
A49: =Referencias!B82 -> Papel Transfer | B49: =B35*12 -> 0.24 | C49: =Referencias!F82 -> 5.49 | D49: =B49*C49 -> 1.3176
A50: =Referencias!B83 -> Impressão A4 | B50: =B36*12 -> 0.24 | C50: =Referencias!F83 -> 0.5 | D50: =B50*C50 -> 0.12
A51: =Referencias!B62 -> Frete | C51: =Referencias!F62 -> 0 | D51: =B51*C51 -> 0
A52: =Referencias!B14 -> Desgaste Bloquinho/Outros | B52: 1 | C52: =Referencias!F14 -> 0.5 | D52: =B52*C52 -> 0.5
A53: =Referencias!B17 -> Embalagem Padrão | B53: 1 | C53: =Referencias!F17 -> 1.5 | D53: =B53*C53 -> 1.5
A54: Custo | D54: =SUM(D46:D53) -> 126.7976
A55: Margem | B55: 0.55 | C55: =D54*B55 -> 69.73868 | D55: =D54+C55 -> 196.53628
A56: Pesquisa
A57: Valor | D57: 20
A59: Toalha com Crochê | D59: 30
A60: =Referencias!B148 -> Toalha Cremer 120x70 | B60: 1 | C60: =Referencias!F148 -> 11.63 | D60: =B60*C60 -> 11.63
A61: =Referencias!B7 -> Fio Clea 1000 160g | B61: 40 | C61: =Referencias!F7 -> 0.11 | D61: =B61*C61 -> 4.4
A62: =Referencias!B80 -> Linha Dinner | B62: 5 | C62: =Referencias!F80 -> 0.1 | D62: =B62*C62 -> 0.5
A63: =Referencias!B82 -> Papel Transfer | B63: 0.02 | C63: =Referencias!F82 -> 5.49 | D63: =B63*C63 -> 0.1098
A64: =Referencias!B83 -> Impressão A4 | B64: 0.02 | C64: =Referencias!F83 -> 0.5 | D64: =B64*C64 -> 0.01
A65: =Referencias!B62 -> Frete | C65: =Referencias!F62 -> 0 | D65: =B65*C65 -> 0
A66: =Referencias!B14 -> Desgaste Bloquinho/Outros | B66: 1 | C66: =Referencias!F14 -> 0.5 | D66: =B66*C66 -> 0.5
A67: =Referencias!B17 -> Embalagem Padrão | B67: 1 | C67: =Referencias!F17 -> 1.5 | D67: =B67*C67 -> 1.5
A68: Custo | D68: =SUM(D60:D67) -> 18.6498
A69: Margem | B69: 0.55 | C69: =D68*B69 -> 10.25739 | D69: =D68+C69 -> 28.90719
A70: Pesquisa
A71: Valor | D71: 30
A73: Toalha com Crochê com 12 | D73: 20
A74: =Referencias!B147 -> Fralda Cremer 70x70 | B74: =B60*12 -> 12 | C74: =Referencias!F147 -> 7.18 | D74: =B74*C74 -> 86.16
A75: =Referencias!B7 -> Fio Clea 1000 160g | B75: =B61*12 -> 480 | C75: =Referencias!F7 -> 0.11 | D75: =B75*C75 -> 52.8
A76: =Referencias!B80 -> Linha Dinner | B76: =B62*12 -> 60 | C76: =Referencias!F80 -> 0.1 | D76: =B76*C76 -> 6
A77: =Referencias!B82 -> Papel Transfer | B77: =B63*12 -> 0.24 | C77: =Referencias!F82 -> 5.49 | D77: =B77*C77 -> 1.3176
A78: =Referencias!B83 -> Impressão A4 | B78: =B64*12 -> 0.24 | C78: =Referencias!F83 -> 0.5 | D78: =B78*C78 -> 0.12
A79: =Referencias!B62 -> Frete | C79: =Referencias!F62 -> 0 | D79: =B79*C79 -> 0
A80: =Referencias!B14 -> Desgaste Bloquinho/Outros | B80: 1 | C80: =Referencias!F14 -> 0.5 | D80: =B80*C80 -> 0.5
A81: =Referencias!B17 -> Embalagem Padrão | B81: 1 | C81: =Referencias!F17 -> 1.5 | D81: =B81*C81 -> 1.5
A82: Custo | D82: =SUM(D74:D81) -> 148.3976
A83: Margem | B83: 0.55 | C83: =D82*B83 -> 81.61868 | D83: =D82+C83 -> 230.01628
A84: Pesquisa
A85: Valor | D85: 20
A87: Pano de Boca com Crochê | D87: 10
A88: =Referencias!B147 -> Fralda Cremer 70x70 | B88: 0.25 | C88: =Referencias!F147 -> 7.18 | D88: =B88*C88 -> 1.795
A89: =Referencias!B7 -> Fio Clea 1000 160g | B89: 25 | C89: =Referencias!F7 -> 0.11 | D89: =B89*C89 -> 2.75
A90: =Referencias!B80 -> Linha Dinner | B90: 1 | C90: =Referencias!F80 -> 0.1 | D90: =B90*C90 -> 0.1
A91: =Referencias!B82 -> Papel Transfer | B91: 0.02 | C91: =Referencias!F82 -> 5.49 | D91: =B91*C91 -> 0.1098
A92: =Referencias!B83 -> Impressão A4 | B92: 0.02 | C92: =Referencias!F83 -> 0.5 | D92: =B92*C92 -> 0.01
A93: =Referencias!B62 -> Frete | C93: =Referencias!F62 -> 0 | D93: =B93*C93 -> 0
A94: =Referencias!B14 -> Desgaste Bloquinho/Outros | B94: 1 | C94: =Referencias!F14 -> 0.5 | D94: =B94*C94 -> 0.5
A95: =Referencias!B17 -> Embalagem Padrão | B95: 1 | C95: =Referencias!F17 -> 1.5 | D95: =B95*C95 -> 1.5
A96: Custo | D96: =SUM(D88:D95) -> 6.7648
A97: Margem | B97: 0.55 | C97: =D96*B97 -> 3.72064 | D97: =D96+C97 -> 10.48544
A98: Pesquisa
A99: Valor | D99: 10
A101: Pano de Prato Atoalhado com Crochê Grande | D101: 25
A102: =Referencias!B12 -> Pano de Prato Atoalhado | B102: 1 | C102: =Referencias!F12 -> 7.03 | D102: =B102*C102 -> 7.03
A103: =Referencias!B105 -> Fio Anne 500 147g | B103: 40 | C103: =Referencias!F105 -> 0.12 | D103: =B103*C103 -> 4.8
A104: =Referencias!B62 -> Frete | C104: =Referencias!F62 -> 0 | D104: =B104*C104 -> 0
A105: =Referencias!B14 -> Desgaste Bloquinho/Outros | B105: 1 | C105: =Referencias!F14 -> 0.5 | D105: =B105*C105 -> 0.5
A106: =Referencias!B17 -> Embalagem Padrão | B106: 1 | C106: =Referencias!F17 -> 1.5 | D106: =B106*C106 -> 1.5
A107: Custo | D107: =SUM(D102:D106) -> 13.83
A108: Margem | B108: 0.55 | C108: =D107*B108 -> 7.6065 | D108: =D107+C108 -> 21.4365
...

Sheet Bebê
A1: Adesivo Garrafa 500ml - Com 60 | D1: 84
A2: =Referencias!B53 -> Papel fotografico A4 | B2: 9 | C2: =Referencias!F53 -> 0.8 | D2: =B2*C2 -> 7.2
A3: =Referencias!B22 -> Impressao Capa A4 | B3: 9 | C3: =Referencias!F22 -> 0.5 | D3: =B3*C3 -> 4.5
A4: =Referencias!B62 -> Frete | C4: =Referencias!F62 -> 0 | D4: =B4*C4 -> 0
A5: =Referencias!B14 -> Desgaste Bloquinho/Outros | B5: 1 | C5: =Referencias!F14 -> 0.5 | D5: =B5*C5 -> 0.5
A6: =Referencias!B17 -> Embalagem Padrão | B6: 1 | C6: =Referencias!F17 -> 1.5 | D6: =B6*C6 -> 1.5
A7: Custo | D7: =SUM(D2:D6) -> 13.7
A8: Margem | B8: 0.55 | C8: =D7*B8 -> 7.535 | D8: =D7+C8 -> 21.235
A9: Pesquisa | B9: elo7 | C9: elo7
A10: Valor | B10: 1.1 | C10: 1.9 | D10: 84
A12: Tag 4 x 4 com 150 | D12: 97
A13: =Referencias!B84 -> Papel 180gr A4 | B13: 5 | C13: =Referencias!F84 -> 0.32 | D13: =B13*C13 -> 1.6
A14: =Referencias!B22 -> Impressao Capa A4 | B14: 5 | C14: =Referencias!F22 -> 0.5 | D14: =B14*C14 -> 2.5
A15: =Referencias!B62 -> Frete | C15: =Referencias!F62 -> 0 | D15: =B15*C15 -> 0
A16: =Referencias!B14 -> Desgaste Bloquinho/Outros | B16: 1 | C16: =Referencias!F14 -> 0.5 | D16: =B16*C16 -> 0.5
A17: =Referencias!B17 -> Embalagem Padrão | B17: 1 | C17: =Referencias!F17 -> 1.5 | D17: =B17*C17 -> 1.5
A18: Custo | D18: =SUM(D13:D17) -> 6.1
A19: Margem | B19: 0.55 | C19: =D18*B19 -> 3.355 | D19: =D18+C19 -> 9.455
A20: Pesquisa | B20: elo7 | C20: elo7
A21: Valor | B21: 0.85 | C21: 0.63 | D21: 97
A23: Caderno de Assinaturas A4 Costurado | D23: 55
A24: =Referencias!B58 -> Papelão 16x22 | B24: 2 | C24: =Referencias!F58 -> 1.5 | D24: =B24*C24 -> 3
A25: =Referencias!B53 -> Papel fotografico A4 | B25: 2 | C25: =Referencias!F53 -> 0.8 | D25: =B25*C25 -> 1.6
A26: =Referencias!B31 -> bopp | B26: =0.3*2 -> 0.6 | C26: =Referencias!F31 -> 0.45 | D26: =B26*C26 -> 0.27
A27: =Referencias!B48 -> Papel guarda 15,5x21,5 offset adesivo | B27: 2 | C27: =Referencias!F48 -> 0.75 | D27: =B27*C27 -> 1.5
A28: =Referencias!B84 -> Papel 180gr A4 | B28: 30 | C28: =Referencias!F84 -> 0.32 | D28: =B28*C28 -> 9.6
A29: =Referencias!B121 -> Fita cetim | B29: 1.18 | C29: =Referencias!F121 -> 0.13 | D29: =B29*C29 -> 0.1534
A30: =Referencias!B10 -> Ilhos | B30: 10 | C30: =Referencias!F10 -> 0.05 | D30: =B30*C30 -> 0.5
A31: =Referencias!B22 -> Impressao Capa A4 | B31: 2 | C31: =Referencias!F22 -> 0.5 | D31: =B31*C31 -> 1
A32: =Referencias!B62 -> Frete | C32: =Referencias!F62 -> 0 | D32: =B32*C32 -> 0
A33: =Referencias!B15 -> Desgaste Caderno A5 | B33: 1 | C33: =Referencias!F15 -> 2 | D33: =B33*C33 -> 2
A34: =Referencias!B17 -> Embalagem Padrão | B34: 1 | C34: =Referencias!F17 -> 1.5 | D34: =B34*C34 -> 1.5
A35: Custo | D35: =SUM(D24:D34) -> 21.1234
A36: Margem | B36: 0.55 | C36: =D35*B36 -> 11.61787 | D36: =D35+C36 -> 32.74127
A37: Pesquisa | B37: praper
A38: Valor | B38: 84.9 | D38: 55
A40: Caderno A5 | D40: 45
A41: =Referencias!B58 -> Papelão 16x22 | B41: 2 | C41: =Referencias!F58 -> 1.5 | D41: =B41*C41 -> 3
A42: =Referencias!B53 -> Papel fotografico A4 | B42: 2 | C42: =Referencias!F53 -> 0.8 | D42: =B42*C42 -> 1.6
A43: =Referencias!B31 -> bopp | B43: =0.3*2 -> 0.6 | C43: =Referencias!F31 -> 0.45 | D43: =B43*C43 -> 0.27
A44: =Referencias!B48 -> Papel guarda 15,5x21,5 offset adesivo | B44: 2 | C44: =Referencias!F48 -> 0.75 | D44: =B44*C44 -> 1.5
A45: =Referencias!B36 -> miolo 180g A5 | B45: 30 | C45: =Referencias!F36 -> 0.16 | D45: =B45*C45 -> 4.8
A46: =Referencias!B69 -> Espiral 20mm | B46: 1 | C46: =Referencias!F69 -> 0.64 | D46: =B46*C46 -> 0.64
A47: =Referencias!B22 -> Impressao Capa A4 | B47: 2 | C47: =Referencias!F22 -> 0.5 | D47: =B47*C47 -> 1
A48: =Referencias!B62 -> Frete | C48: =Referencias!F62 -> 0 | D48: =B48*C48 -> 0
A49: =Referencias!B15 -> Desgaste Caderno A5 | B49: 1 | C49: =Referencias!F15 -> 2 | D49: =B49*C49 -> 2
A50: =Referencias!B17 -> Embalagem Padrão | B50: 1 | C50: =Referencias!F17 -> 1.5 | D50: =B50*C50 -> 1.5
A51: Custo | D51: =SUM(D41:D50) -> 16.31
A52: Margem | B52: 0.55 | C52: =D51*B52 -> 8.9705 | D52: =D51+C52 -> 25.2805
A53: Pesquisa | B53: MP mimos
A54: Valor | B54: 39 | D54: 45
A56: Caderneta de Vacina | D56: 60
A57: =Referencias!B58 -> Papelão 16x22 | B57: 2 | C57: =Referencias!F58 -> 1.5 | D57: =B57*C57 -> 3
A58: =Referencias!B53 -> Papel fotografico A4 | B58: 2 | C58: =Referencias!F53 -> 0.8 | D58: =B58*C58 -> 1.6
A59: =Referencias!B31 -> bopp | B59: =0.3*2 -> 0.6 | C59: =Referencias!F31 -> 0.45 | D59: =B59*C59 -> 0.27
A60: =Referencias!B48 -> Papel guarda 15,5x21,5 offset adesivo | B60: 2 | C60: =Referencias!F48 -> 0.75 | D60: =B60*C60 -> 1.5
A61: =Referencias!B46 -> miolo 90gr A5 14x18 | B61: 60 | C61: =Referencias!F46 -> 0.05 | D61: =B61*C61 -> 3
A62: =Referencias!B69 -> Espiral 20mm | B62: 1 | C62: =Referencias!F69 -> 0.64 | D62: =B62*C62 -> 0.64
A63: =Referencias!B215 -> Color plus metalico Aspen 120g A4 | B63: 1 | C63: =Referencias!F215 -> 0.7 | D63: =B63*C63 -> 0.7
A64: =Referencias!B117 -> Envelope Canguru 15x21 | B64: 1 | C64: =Referencias!F117 -> 1.97 | D64: =B64*C64 -> 1.97
A65: =Referencias!B22 -> Impressao Capa A4 | B65: 2 | C65: =Referencias!F22 -> 0.5 | D65: =B65*C65 -> 1
A66: =Referencias!B29 -> Impressao Miolo Frente Verso A5 | B66: 60 | C66: =Referencias!F29 -> 0.06 | D66: =B66*C66 -> 3.6
A67: =Referencias!B62 -> Frete | C67: =Referencias!F62 -> 0 | D67: =B67*C67 -> 0
A68: =Referencias!B13 -> Desgaste Agenda | B68: 1 | C68: =Referencias!F13 -> 1 | D68: =B68*C68 -> 1
A69: =Referencias!B17 -> Embalagem Padrão | B69: 1 | C69: =Referencias!F17 -> 1.5 | D69: =B69*C69 -> 1.5
A70: Custo | D70: =SUM(D57:D69) -> 19.78
A71: Margem | B71: 0.55 | C71: =D70*B71 -> 10.879 | D71: =D70+C71 -> 30.659
A72: Pesquisa | B72: mp
A73: Valor | B73: 51 | D73: 70

Sheet Casamento
A1: Convite Padrinhos/Daminhas | E1: 42.5
A2: =Referencias!B37 -> miolo 180gr A4 | C2: 13 | D2: =Referencias!F37 -> 0.32 | E2: =C2*D2 -> 4.16
A3: =Referencias!B22 -> Impressao Capa A4 | C3: 13 | D3: =Referencias!F22 -> 0.5 | E3: =C3*D3 -> 6.5
A4: =Referencias!B62 -> Frete | D4: =Referencias!F62 -> 0 | E4: =C4*D4 -> 0
A5: =Referencias!B14 -> Desgaste Bloquinho/Outros | C5: 13 | D5: =Referencias!F14 -> 0.5 | E5: =C5*D5 -> 6.5
A6: =Referencias!B17 -> Embalagem Padrão | C6: 1 | D6: =Referencias!F17 -> 1.5 | E6: =C6*D6 -> 1.5
A7: Custo | E7: =SUM(E2:E6) -> 18.66
A8: Margem | C8: 0.55 | D8: =E7*C8 -> 10.263 | E8: =E7+D8 -> 28.923
A9: Pesquisa | D9: mp
A10: Valor | E10: 42.5
A12: Manual Padrinhos/Daminhas | E12: 42.5
A13: =Referencias!B37 -> miolo 180gr A4 | C13: 13 | D13: =Referencias!F37 -> 0.32 | E13: =C13*D13 -> 4.16
A14: =Referencias!B22 -> Impressao Capa A4 | C14: 13 | D14: =Referencias!F22 -> 0.5 | E14: =C14*D14 -> 6.5
A15: =Referencias!B121 -> Fita cetim | C15: =0.13*13 -> 1.69 | D15: =Referencias!F121 -> 0.13 | E15: =C15*D15 -> 0.2197
A16: =Referencias!B62 -> Frete | D16: =Referencias!F62 -> 0 | E16: =C16*D16 -> 0
A17: =Referencias!B14 -> Desgaste Bloquinho/Outros | C17: 13 | D17: =Referencias!F14 -> 0.5 | E17: =C17*D17 -> 6.5
A18: =Referencias!B17 -> Embalagem Padrão | C18: 1 | D18: =Referencias!F17 -> 1.5 | E18: =C18*D18 -> 1.5
A19: Custo | E19: =SUM(E13:E18) -> 18.8797
A20: Margem | C20: 0.55 | D20: =E19*C20 -> 10.383835 | E20: =E19+D20 -> 29.263535
A21: Pesquisa | D21: mp
A22: Valor | E22: 42.5
A24: Lágrimas | E24: 50
A25: =Referencias!B216 -> Sulfite 90gr A4 | C25: 5 | D25: =Referencias!F216 -> 0.1 | E25: =C25*D25 -> 0.5
A26: =Referencias!B22 -> Impressao Capa A4 | C26: 5 | D26: =Referencias!F22 -> 0.5 | E26: =C26*D26 -> 2.5
A27: =Referencias!B235 -> Lenço de Papel | C27: 40 | D27: =Referencias!F235 -> 0.2 | E27: =C27*D27 -> 8
A28: =Referencias!B234 -> Saco Adesivo Transparente 6x12cm | C28: 40 | D28: =Referencias!F234 -> 0.07 | E28: =C28*D28 -> 2.8
A29: =Referencias!B62 -> Frete | D29: =Referencias!F62 -> 0 | E29: =C29*D29 -> 0
A30: =Referencias!B14 -> Desgaste Bloquinho/Outros | C30: 1 | D30: =Referencias!F14 -> 0.5 | E30: =C30*D30 -> 0.5
A31: =Referencias!B17 -> Embalagem Padrão | C31: 1 | D31: =Referencias!F17 -> 1.5 | E31: =C31*D31 -> 1.5
A32: Custo | E32: =SUM(E25:E31) -> 15.8
A33: Margem | C33: 0.55 | D33: =E32*C33 -> 8.69 | E33: =E32+D33 -> 24.49
A34: Pesquisa | C34: 30 | D34: 50
A35: Valor | C35: 50 | D35: 80 | E35: 50
C36: =(D35+C35)/2 -> 65

Sheet Trevo Saúde
A1: Kit Higiene Bucal | D1: 9.5
A2: =Referencias!B75 -> Plástico Cristal 1mx1,4m | B2: 0.02 | C2: =Referencias!F75 -> 14.9 | D2: =B2*C2 -> 0.298
A3: =Referencias!B76 -> Tecido Tricoline 1mx1,4m trevo | B3: 0.06 | C3: =Referencias!F76 -> 33.8 | D3: =B3*C3 -> 2.028
A4: =Referencias!B77 -> Botão de Pressão | B4: 1 | C4: =Referencias!F77 -> 0.07 | D4: =B4*C4 -> 0.07
A5: =Referencias!B78 -> Manta R2 1mx1,4m | B5: 0.02 | C5: =Referencias!F78 -> 27.8 | D5: =B5*C5 -> 0.556
A6: =Referencias!B79 -> Vies 20m | B6: 0.8 | C6: =Referencias!F79 -> 0.32 | D6: =B6*C6 -> 0.256
A7: =Referencias!B80 -> Linha Dinner | B7: 3.16 | C7: =Referencias!F80 -> 0.1 | D7: =B7*C7 -> 0.316
A8: =Referencias!B81 -> Etiqueta Cetim 1,5 10m | B8: 0.1 | C8: =Referencias!F81 -> 0.25 | D8: =B8*C8 -> 0.025
A9: =Referencias!B82 -> Papel Transfer | B9: 0.02 | C9: =Referencias!F82 -> 5.49 | D9: =B9*C9 -> 0.1098
A10: =Referencias!B83 -> Impressão A4 | B10: 0.02 | C10: =Referencias!F83 -> 0.5 | D10: =B10*C10 -> 0.01
A11: =Referencias!B62 -> Frete | C11: =Referencias!F62 -> 0 | D11: =B11*C11 -> 0
A12: =Referencias!B14 -> Desgaste Bloquinho/Outros | B12: 1 | C12: =Referencias!F14 -> 0.5 | D12: =B12*C12 -> 0.5
A13: =Referencias!B17 -> Embalagem Padrão | B13: 1 | C13: =Referencias!F17 -> 1.5 | D13: =B13*C13 -> 1.5
A14: Custo | D14: =SUM(D2:D13) -> 5.6688
A15: Margem | B15: 0.55 | C15: =D14*B15 -> 3.11784 | D15: =D14+C15 -> 8.78664
A16: Pesquisa
A17: Valor | D17: 10
A19: Ecobag InvisaAlign | D19: 15
A20: =Referencias!B76 -> Tecido Tricoline 1mx1,4m trevo | B20: 0.22 | C20: =Referencias!F76 -> 33.8 | D20: =B20*C20 -> 7.436
A21: =Referencias!B80 -> Linha Dinner | B21: 7.6 | C21: =Referencias!F80 -> 0.1 | D21: =B21*C21 -> 0.76
A22: =Referencias!B81 -> Etiqueta Cetim 1,5 10m | B22: 0.1 | C22: =Referencias!F81 -> 0.25 | D22: =B22*C22 -> 0.025
A23: =Referencias!B82 -> Papel Transfer | B23: 0.02 | C23: =Referencias!F82 -> 5.49 | D23: =B23*C23 -> 0.1098
A24: =Referencias!B83 -> Impressão A4 | B24: 0.02 | C24: =Referencias!F83 -> 0.5 | D24: =B24*C24 -> 0.01
A25: =Referencias!B62 -> Frete | C25: =Referencias!F62 -> 0 | D25: =B25*C25 -> 0
A26: =Referencias!B14 -> Desgaste Bloquinho/Outros | B26: 1 | C26: =Referencias!F14 -> 0.5 | D26: =B26*C26 -> 0.5
A27: =Referencias!B17 -> Embalagem Padrão | B27: 1 | C27: =Referencias!F17 -> 1.5 | D27: =B27*C27 -> 1.5
A28: Custo | D28: =SUM(D20:D27) -> 10.3408
A29: Margem | B29: 0.55 | C29: =D28*B29 -> 5.68744 | D29: =D28+C29 -> 16.02824
A30: Pesquisa
A31: Valor | D31: 20
A33: Ecobag 30x40 | D33: 15
A34: =Referencias!B76 -> Tecido Tricoline 1mx1,4m trevo | B34: 0.38 | C34: 40 | D34: =B34*C34 -> 15.2
A35: =Referencias!B80 -> Linha Dinner | B35: 7.6 | C35: =Referencias!F80 -> 0.1 | D35: =B35*C35 -> 0.76
A36: =Referencias!B81 -> Etiqueta Cetim 1,5 10m | B36: 0.25 | C36: =Referencias!F81 -> 0.25 | D36: =B36*C36 -> 0.0625
A37: =Referencias!B82 -> Papel Transfer | B37: 0.02 | C37: =Referencias!F82 -> 5.49 | D37: =B37*C37 -> 0.1098
A38: =Referencias!B83 -> Impressão A4 | B38: 0.02 | C38: =Referencias!F83 -> 0.5 | D38: =B38*C38 -> 0.01
A39: =Referencias!B62 -> Frete | C39: =Referencias!F62 -> 0 | D39: =B39*C39 -> 0
A40: =Referencias!B14 -> Desgaste Bloquinho/Outros | B40: 1 | C40: =Referencias!F14 -> 0.5 | D40: =B40*C40 -> 0.5
A41: =Referencias!B17 -> Embalagem Padrão | B41: 1 | C41: =Referencias!F17 -> 1.5 | D41: =B41*C41 -> 1.5
A42: Custo | D42: =SUM(D34:D41) -> 18.1423
A43: Margem | B43: 0.55 | C43: =D42*B43 -> 9.978265 | D43: =D42+C43 -> 28.120565
A44: Pesquisa
A45: Valor | D45: 30

Sheet Fofurinhas
A1: Caderno A5 - Preguiça | D1: 50
A2: =Referencias!B58 -> Papelão 16x22 | B2: 2 | C2: =Referencias!F58 -> 1.5 | D2: =B2*C2 -> 3
A3: =Referencias!B53 -> Papel fotografico A4 | B3: 2 | C3: =Referencias!F53 -> 0.8 | D3: =B3*C3 -> 1.6
A4: =Referencias!B31 -> bopp | B4: =2*0.3 -> 0.6 | C4: =Referencias!F31 -> 0.45 | D4: =B4*C4 -> 0.27
A5: =Referencias!B48 -> Papel guarda 15,5x21,5 offset adesivo | B5: 2 | C5: =Referencias!F48 -> 0.75 | D5: =B5*C5 -> 1.5
A6: =Referencias!B45 -> miolo 90gr A5 | B6: 80 | C6: =Referencias!F45 -> 0.05 | D6: =B6*C6 -> 4
A7: =Referencias!B69 -> Espiral 20mm | B7: 1 | C7: =Referencias!F69 -> 0.64 | D7: =B7*C7 -> 0.64
A8: =Referencias!B22 -> Impressao Capa A4 | B8: 2 | C8: =Referencias!F22 -> 0.5 | D8: =B8*C8 -> 1
A9: =Referencias!B29 -> Impressao Miolo Frente Verso A5 | B9: 80 | C9: =Referencias!F29 -> 0.06 | D9: =B9*C9 -> 4.8
A10: =Referencias!B62 -> Frete | C10: =Referencias!F62 -> 0 | D10: =B10*C10 -> 0
A11: =Referencias!B15 -> Desgaste Caderno A5 | B11: 1 | C11: =Referencias!F15 -> 2 | D11: =B11*C11 -> 2
A12: =Referencias!B17 -> Embalagem Padrão | B12: 1 | C12: =Referencias!F17 -> 1.5 | D12: =B12*C12 -> 1.5
A13: Custo | D13: =SUM(D2:D12) -> 20.31
A14: Margem | B14: 0.55 | C14: =D13*B14 -> 11.1705 | D14: =D13+C14 -> 31.4805
A15: Pesquisa | B15: praper | C15: mp
A16: Valor | D16: 60
A18: Caderno A5 - Preguiça+ | D18: 75
A19: =Referencias!B58 -> Papelão 16x22 | B19: 2 | C19: =Referencias!F58 -> 1.5 | D19: =B19*C19 -> 3
A20: =Referencias!B53 -> Papel fotografico A4 | B20: 2 | C20: =Referencias!F53 -> 0.8 | D20: =B20*C20 -> 1.6
A21: =Referencias!B31 -> bopp | B21: =2*0.3 -> 0.6 | C21: =Referencias!F31 -> 0.45 | D21: =B21*C21 -> 0.27
A22: =Referencias!B48 -> Papel guarda 15,5x21,5 offset adesivo | B22: 2 | C22: =Referencias!F48 -> 0.75 | D22: =B22*C22 -> 1.5
A23: =Referencias!B45 -> miolo 90gr A5 | B23: 150 | C23: =Referencias!F45 -> 0.05 | D23: =B23*C23 -> 7.5
A24: =Referencias!B20 -> Espiral 33mm | B24: 1 | C24: =Referencias!F20 -> 4 | D24: =B24*C24 -> 4
A25: =Referencias!B22 -> Impressao Capa A4 | B25: 2 | C25: =Referencias!F22 -> 0.5 | D25: =B25*C25 -> 1
A26: =Referencias!B29 -> Impressao Miolo Frente Verso A5 | B26: 150 | C26: =Referencias!F29 -> 0.06 | D26: =B26*C26 -> 9
A27: =Referencias!B62 -> Frete | C27: =Referencias!F62 -> 0 | D27: =B27*C27 -> 0
A28: =Referencias!B15 -> Desgaste Caderno A5 | B28: 1 | C28: =Referencias!F15 -> 2 | D28: =B28*C28 -> 2
A29: =Referencias!B17 -> Embalagem Padrão | B29: 1 | C29: =Referencias!F17 -> 1.5 | D29: =B29*C29 -> 1.5
A30: Custo | D30: =SUM(D19:D29) -> 31.37
A31: Margem | B31: 0.55 | C31: =D30*B31 -> 17.2535 | D31: =D30+C31 -> 48.6235
A32: Pesquisa | B32: praper | C32: mp
A33: Valor | D33: 95
A35: Bloquinho de Anotações 12x12 cm - Preguiça | D35: 15
A36: =Referencias!B92 -> Papelão 12x12+12x12+12x1 | B36: 1 | C36: =Referencias!F92 -> 1.5 | D36: =B36*C36 -> 1.5
A37: =Referencias!B53 -> Papel fotografico A4 | B37: 1 | C37: =Referencias!F53 -> 0.8 | D37: =B37*C37 -> 0.8
A38: =Referencias!B31 -> bopp | B38: 0.3 | C38: =Referencias!F31 -> 0.45 | D38: =B38*C38 -> 0.135
A39: =Referencias!B66 -> Papel guarda offset adesivo A4 | B39: 1 | C39: =Referencias!F66 -> 0.75 | D39: =B39*C39 -> 0.75
A40: =Referencias!B68 -> miolo 75gr A7 | B40: 80 | C40: =Referencias!F68 -> 0.01 | D40: =B40*C40 -> 0.8
A41: =Referencias!B22 -> Impressao Capa A4 | B41: 1 | C41: =Referencias!F22 -> 0.5 | D41: =B41*C41 -> 0.5
A42: =Referencias!B62 -> Frete | C42: =Referencias!F62 -> 0 | D42: =B42*C42 -> 0
A43: =Referencias!B14 -> Desgaste Bloquinho/Outros | B43: 1 | C43: =Referencias!F14 -> 0.5 | D43: =B43*C43 -> 0.5
A44: =Referencias!B17 -> Embalagem Padrão | B44: 1 | C44: =Referencias!F17 -> 1.5 | D44: =B44*C44 -> 1.5
A45: Custo | D45: =SUM(D36:D44) -> 6.485
A46: Margem | B46: 0.55 | C46: =D45*B46 -> 3.56675 | D46: =D45+C46 -> 10.05175
A47: Pesquisa | B47: praper
A48: Valor | D48: 20
A50: Caderno Brochura A5 - Fofurinhas | D50: 20
A51: =Referencias!B89 -> Caderno Brochura Foroni A5 | B51: 1 | C51: =Referencias!F89 -> 4.1 | D51: =B51*C51 -> 4.1
A52: =Referencias!B90 -> Contact 200x45 | B52: =0.25*0.34 -> 0.085 | C52: =Referencias!F90 -> 15 | D52: =B52*C52 -> 1.275
A53: =Referencias!B91 -> EVA 40x47 | B53: =2*0.14*0.18 -> 0.0504 | C53: =Referencias!F91 -> 1.19 | D53: =B53*C53 -> 0.059976
A54: =Referencias!B48 -> Papel guarda 15,5x21,5 offset adesivo | B54: 2 | C54: =Referencias!F48 -> 0.75 | D54: =B54*C54 -> 1.5
A55: =Referencias!B75 -> Plástico Cristal 1mx1,4m | B55: =(26*35)/(100*140) -> 0.065 | C55: =Referencias!F75 -> 14.9 | D55: =B55*C55 -> 0.9685
A56: =Referencias!B62 -> Frete | C56: =Referencias!F62 -> 0 | D56: =B56*C56 -> 0
A57: =Referencias!B15 -> Desgaste Caderno A5 | B57: 1 | C57: =Referencias!F15 -> 2 | D57: =B57*C57 -> 2
A58: =Referencias!B17 -> Embalagem Padrão | B58: 1 | C58: =Referencias!F17 -> 1.5 | D58: =B58*C58 -> 1.5
A59: Custo | D59: =SUM(D51:D58) -> 11.403476
A60: Margem | B60: 0.55 | C60: =D59*B60 -> 6.2719118 | D60: =D59+C60 -> 17.675388
A61: Pesquisa | B61: praper
A62: Valor | B62: 6 | C62: 7 | D62: 25
A64: Bloquinho de Anotações A7 - Fofurinhas | D64: 15
A65: =Referencias!B96 -> Papelão 11,5x15,5 | B65: 2 | C65: =Referencias!F96 -> 0.75 | D65: =B65*C65 -> 1.5
A66: =Referencias!B90 -> Contact 200x45 | B66: =(14*18)/(200*45) -> 0.028 | C66: =Referencias!F90 -> 15 | D66: =B66*C66 -> 0.42
A67: =Referencias!B75 -> Plástico Cristal 1mx1,4m | B67: =(15*19)/(100*140) -> 0.020357143 | C67: =Referencias!F75 -> 14.9 | D67: =B67*C67 -> 0.30332143
A68: =Referencias!B97 -> Papel guarda 11x14,5 offset adesivo | B68: 2 | C68: =Referencias!F48 -> 0.75 | D68: =B68*C68 -> 1.5
A69: =Referencias!B98 -> Sulfite 75g A6 | B69: 80 | C69: =Referencias!F98 -> 0.02 | D69: =B69*C69 -> 1.6
A70: =Referencias!B69 -> Espiral 20mm | B70: 0.5 | C70: =Referencias!F69 -> 0.64 | D70: =B70*C70 -> 0.32
A71: =Referencias!B91 -> EVA 40x47 | B71: =2*(10*12)/(40*47) -> 0.12765957 | C71: =Referencias!F91 -> 1.19 | D71: =B71*C71 -> 0.15191489
A72: =Referencias!B62 -> Frete | C72: =Referencias!F62 -> 0 | D72: =B72*C72 -> 0
A73: =Referencias!B14 -> Desgaste Bloquinho/Outros | B73: 1 | C73: =Referencias!F14 -> 0.5 | D73: =B73*C73 -> 0.5
A74: =Referencias!B17 -> Embalagem Padrão | B74: 1 | C74: =Referencias!F17 -> 1.5 | D74: =B74*C74 -> 1.5
A75: Custo | D75: =SUM(D65:D74) -> 7.7952363
A76: Margem | B76: 0.55 | C76: =D75*B76 -> 4.28738 | D76: =D75+C76 -> 12.082616
A77: Pesquisa
A78: Valor | D78: 15
A80: Caderno Brochurado A5 - Fofurinhas | D80: 30
A81: =Referencias!B58 -> Papelão 16x22 | B81: 2 | C81: =Referencias!F58 -> 1.5 | D81: =B81*C81 -> 3
A82: =Referencias!B90 -> Contact 200x45 | B82: =0.25*0.34 -> 0.085 | C82: =Referencias!F90 -> 15 | D82: =B82*C82 -> 1.275
A83: =Referencias!B75 -> Plástico Cristal 1mx1,4m | B83: =(26*35)/(100*140) -> 0.065 | C83: =Referencias!F75 -> 14.9 | D83: =B83*C83 -> 0.9685
A84: =Referencias!B48 -> Papel guarda 15,5x21,5 offset adesivo | B84: 2 | C84: =Referencias!F48 -> 0.75 | D84: =B84*C84 -> 1.5
A85: =Referencias!B45 -> miolo 90gr A5 | B85: 100 | C85: =Referencias!F45 -> 0.05 | D85: =B85*C85 -> 5
A86: =Referencias!B91 -> EVA 40x47 | B86: =2*0.14*0.18 -> 0.0504 | C86: =Referencias!F91 -> 1.19 | D86: =B86*C86 -> 0.059976
A87: =Referencias!B94 -> Cola Branca 1kg | B87: 10 | C87: =Referencias!F94 -> 0.04 | D87: =B87*C87 -> 0.4
A88: =Referencias!B95 -> Linha Urso | B88: 10 | C88: =Referencias!F95 -> 0.23 | D88: =B88*C88 -> 2.3
A89: =Referencias!B62 -> Frete | C89: =Referencias!F62 -> 0 | D89: =B89*C89 -> 0
A90: =Referencias!B14 -> Desgaste Bloquinho/Outros | B90: 1 | C90: =Referencias!F14 -> 0.5 | D90: =B90*C90 -> 0.5
A91: =Referencias!B17 -> Embalagem Padrão | B91: 1 | C91: =Referencias!F17 -> 1.5 | D91: =B91*C91 -> 1.5
A92: Custo | D92: =SUM(D81:D91) -> 16.503476
A93: Margem | B93: 0.55 | C93: =D92*B93 -> 9.0769118 | D93: =D92+C93 -> 25.580388
A94: Pesquisa | B94: loja sabonete
A95: Valor | B95: 24 | D95: 30

Sheet Costura Criativa
A1: Toalhinha para Lancheira 30x40 | D1: 15
A2: =Referencias!B76 -> Tecido Tricoline 1mx1,4m trevo | B2: 0.17 | C2: =Referencias!F76 -> 33.8 | D2: =B2*C2 -> 5.746
A3: =Referencias!B80 -> Linha Dinner | B3: 0.5 | C3: =Referencias!F80 -> 0.1 | D3: =B3*C3 -> 0.05
A4: =Referencias!B81 -> Etiqueta Cetim 1,5 10m | B4: 0.1 | C4: =Referencias!F81 -> 0.25 | D4: =B4*C4 -> 0.025
A5: =Referencias!B82 -> Papel Transfer | B5: 0.02 | C5: =Referencias!F82 -> 5.49 | D5: =B5*C5 -> 0.1098
A6: =Referencias!B83 -> Impressão A4 | B6: 0.02 | C6: =Referencias!F83 -> 0.5 | D6: =B6*C6 -> 0.01
A7: =Referencias!B62 -> Frete | C7: =Referencias!F62 -> 0 | D7: =B7*C7 -> 0
A8: =Referencias!B14 -> Desgaste Bloquinho/Outros | B8: 1 | C8: =Referencias!F14 -> 0.5 | D8: =B8*C8 -> 0.5
A9: =Referencias!B17 -> Embalagem Padrão | B9: 1 | C9: =Referencias!F17 -> 1.5 | D9: =B9*C9 -> 1.5
A10: Custo | D10: =SUM(D2:D9) -> 7.9408
A11: Margem | B11: 0.55 | C11: =D10*B11 -> 4.36744 | D11: =D10+C11 -> 12.30824
A12: Pesquisa
A13: Valor | D13: 15
A15: Capa Plástica para Caderneta de Vacina do Idoso | D15: 10
A16: =Referencias!B119 -> Plástico Alclear Light Translucido | B16: 0.1 | C16: =Referencias!F119 -> 26.9 | D16: =B16*C16 -> 2.69
A17: =Referencias!B79 -> Vies 20m | B17: 1.5 | C17: =Referencias!F79 -> 0.32 | D17: =B17*C17 -> 0.48
A18: =Referencias!B77 -> Botão de Pressão | B18: 2 | C18: =Referencias!F79 -> 0.32 | D18: =B18*C18 -> 0.64
A19: =Referencias!B80 -> Linha Dinner | B19: 3 | C19: =Referencias!F77 -> 0.07 | D19: =B19*C19 -> 0.21
A20: =Referencias!B62 -> Frete | C20: =Referencias!F62 -> 0 | D20: =B20*C20 -> 0
A21: =Referencias!B14 -> Desgaste Bloquinho/Outros | B21: 1 | C21: =Referencias!F14 -> 0.5 | D21: =B21*C21 -> 0.5
A22: =Referencias!B17 -> Embalagem Padrão | B22: 1 | C22: =Referencias!F17 -> 1.5 | D22: =B22*C22 -> 1.5
A23: Custo | D23: =SUM(D16:D22) -> 6.02
A24: Margem | B24: 0.55 | C24: =D23*B24 -> 3.311 | D24: =D23+C24 -> 9.331
A25: Pesquisa
A26: Valor | D26: 10
A28: Jogo 5 Marias | D28: 20
A29: =Referencias!B238 -> Tecido Tricoline 32cmx20cm | B29: 1 | C29: =Referencias!F238 -> 1.48 | D29: =B29*C29 -> 1.48
A30: =Referencias!B239 -> Tecido Tricoline 11cmx6cm | B30: 5 | C30: =Referencias!F239 -> 0.15 | D30: =B30*C30 -> 0.75
A31: =Referencias!B240 -> Barbante Bandeirantes nº 4 | B31: 1.5 | C31: =Referencias!F240 -> 0.02 | D31: =B31*C31 -> 0.03
A32: =Referencias!B241 -> Painço 500g | B32: 75 | C32: =Referencias!F241 -> 0.01 | D32: =B32*C32 -> 0.75
A33: =Referencias!B80 -> Linha Dinner | B33: 1.5 | C33: =Referencias!F80 -> 0.1 | D33: =B33*C33 -> 0.15
A34: =Referencias!B81 -> Etiqueta Cetim 1,5 10m | B34: 0.1 | C34: =Referencias!F81 -> 0.25 | D34: =B34*C34 -> 0.025
A35: =Referencias!B82 -> Papel Transfer | B35: 0.02 | C35: =Referencias!F82 -> 5.49 | D35: =B35*C35 -> 0.1098
A36: =Referencias!B83 -> Impressão A4 | B36: 0.02 | C36: =Referencias!F83 -> 0.5 | D36: =B36*C36 -> 0.01
A37: =Referencias!B37 -> miolo 180gr A4 | B37: 0.16 | C37: =Referencias!F37 -> 0.32 | D37: =B37*C37 -> 0.0512
A38: =Referencias!B28 -> Impressao Miolo Frente Verso A4 | B38: 0.16 | C38: =Referencias!F28 -> 0.12 | D38: =B38*C38 -> 0.0192
A39: =Referencias!B62 -> Frete | C39: =Referencias!F62 -> 0 | D39: =B39*C39 -> 0
A40: =Referencias!B14 -> Desgaste Bloquinho/Outros | B40: 1 | C40: =Referencias!F14 -> 0.5 | D40: =B40*C40 -> 0.5
A41: =Referencias!B17 -> Embalagem Padrão | B41: 1 | C41: =Referencias!F17 -> 1.5 | D41: =B41*C41 -> 1.5
A42: Custo | D42: =SUM(D29:D41) -> 5.3752
A43: Margem | B43: 0.55 | C43: =D42*B43 -> 2.95636 | D43: =D42+C43 -> 8.33156
A44: Pesquisa | B44: 24 | C44: 15
A45: Valor | D45: 20

Sheet Sacolas em Papel
A1: Sacolinha P | D1: 6
A2: =Referencias!B84 -> Papel 180gr A4 | B2: 2 | C2: =Referencias!F84 -> 0.32 | D2: =B2*C2 -> 0.64
A3: =Referencias!B85 -> Alça - Fio Nautico circulo branco | B3: =0.26*2 -> 0.52 | C3: =Referencias!F85 -> 0.14 | D3: =B3*C3 -> 0.0728
A4: =Referencias!B83 -> Impressão A4 | B4: 2 | C4: =Referencias!F83 -> 0.5 | D4: =B4*C4 -> 1
A5: =Referencias!B62 -> Frete | C5: =Referencias!F62 -> 0 | D5: =B5*C5 -> 0
A6: =Referencias!B14 -> Desgaste Bloquinho/Outros | B6: 1 | C6: =Referencias!F14 -> 0.5 | D6: =B6*C6 -> 0.5
A7: =Referencias!B17 -> Embalagem Padrão | B7: 1 | C7: =Referencias!F17 -> 1.5 | D7: =B7*C7 -> 1.5
A8: Custo | D8: =SUM(D2:D7) -> 3.7128
A9: Margem | B9: 0.55 | C9: =D8*B9 -> 2.04204 | D9: =D8+C9 -> 5.75484
A10: Pesquisa
A11: Valor | D11: 6
A13: Sacolinha M | D13: 7
A14: =Referencias!B84 -> Papel 180gr A4 | B14: 3 | C14: =Referencias!F84 -> 0.32 | D14: =B14*C14 -> 0.96
A15: =Referencias!B85 -> Alça - Fio Nautico circulo branco | B15: =0.32*2 -> 0.64 | C15: =Referencias!F85 -> 0.14 | D15: =B15*C15 -> 0.0896
A16: =Referencias!B83 -> Impressão A4 | B16: 3 | C16: =Referencias!F83 -> 0.5 | D16: =B16*C16 -> 1.5
A17: =Referencias!B62 -> Frete | C17: =Referencias!F62 -> 0 | D17: =B17*C17 -> 0
A18: =Referencias!B14 -> Desgaste Bloquinho/Outros | B18: 1 | C18: =Referencias!F14 -> 0.5 | D18: =B18*C18 -> 0.5
A19: =Referencias!B17 -> Embalagem Padrão | B19: 1 | C19: =Referencias!F17 -> 1.5 | D19: =B19*C19 -> 1.5
A20: Custo | D20: =SUM(D14:D19) -> 4.5496
A21: Margem | B21: 0.55 | C21: =D20*B21 -> 2.50228 | D21: =D20+C21 -> 7.05188
A22: Pesquisa
A23: Valor | D23: 7
A25: Sacolinha 8,5 x 8,5 | D25: 5.5
A26: =Referencias!B84 -> Papel 180gr A4 | B26: 1 | C26: =Referencias!F84 -> 0.32 | D26: =B26*C26 -> 0.32
A27: =Referencias!B85 -> Alça - Fio Nautico circulo branco | B27: 0.51 | C27: =Referencias!F85 -> 0.14 | D27: =B27*C27 -> 0.0714
A28: =Referencias!B83 -> Impressão A4 | B28: 1 | C28: =Referencias!F83 -> 0.5 | D28: =B28*C28 -> 0.5
A29: =Referencias!B62 -> Frete | C29: =Referencias!F62 -> 0 | D29: =B29*C29 -> 0
A30: =Referencias!B13 -> Desgaste Agenda | B30: 1 | C30: =Referencias!F13 -> 1 | D30: =B30*C30 -> 1
A31: =Referencias!B17 -> Embalagem Padrão | B31: 1 | C31: =Referencias!F17 -> 1.5 | D31: =B31*C31 -> 1.5
A32: Custo | D32: =SUM(D26:D31) -> 3.3914
A33: Margem | B33: 0.55 | C33: =D32*B33 -> 1.86527 | D33: =D32+C33 -> 5.25667
A34: Pesquisa
A35: Valor | D35: 5.5
A37: Sacolinha M reciclado | D37: 8
A38: =Referencias!B86 -> Papel 180gr A4 Reciclado | B38: 3 | C38: =Referencias!F86 -> 0.25 | D38: =B38*C38 -> 0.75
A39: =Referencias!B87 -> Alça - Cordão de Algodão | B39: 0.51 | C39: =Referencias!F87 -> 0.52 | D39: =B39*C39 -> 0.2652
A40: =Referencias!B83 -> Impressão A4 | B40: 3 | C40: =Referencias!F83 -> 0.5 | D40: =B40*C40 -> 1.5
A41: =Referencias!B62 -> Frete | C41: =Referencias!F62 -> 0 | D41: =B41*C41 -> 0
A42: =Referencias!B13 -> Desgaste Agenda | B42: 1 | C42: =Referencias!F13 -> 1 | D42: =B42*C42 -> 1
A43: =Referencias!B17 -> Embalagem Padrão | B43: 1 | C43: =Referencias!F17 -> 1.5 | D43: =B43*C43 -> 1.5
A44: Custo | D44: =SUM(D38:D43) -> 5.0152
A45: Margem | B45: 0.55 | C45: =D44*B45 -> 2.75836 | D45: =D44+C45 -> 7.77356
A46: Pesquisa
A47: Valor | D47: 8

Sheet Sacolas 60
A1: Sacolinha P | D1: 6
A2: =Referencias!B84 -> Papel 180gr A4 | B2: 120 | C2: =Referencias!F84 -> 0.32 | D2: =B2*C2 -> 38.4
A3: =Referencias!B85 -> Alça - Fio Nautico circulo branco | B3: =0.26*2*60 -> 31.2 | C3: =Referencias!F85 -> 0.14 | D3: =B3*C3 -> 4.368
A4: =Referencias!B83 -> Impressão A4 | B4: 120 | C4: =Referencias!F83 -> 0.5 | D4: =B4*C4 -> 60
A5: =Referencias!B62 -> Frete | C5: =Referencias!F62 -> 0 | D5: =B5*C5 -> 0
A6: =Referencias!B14 -> Desgaste Bloquinho/Outros | B6: 1 | C6: =Referencias!F14 -> 0.5 | D6: =B6*C6 -> 0.5
A7: =Referencias!B17 -> Embalagem Padrão | B7: 1 | C7: =Referencias!F17 -> 1.5 | D7: =B7*C7 -> 1.5
A8: Custo | D8: =SUM(D2:D7) -> 104.768
A9: Margem | B9: 0.55 | C9: =D8*B9 -> 57.6224 | D9: =D8+C9 -> 162.3904
A10: Pesquisa
A11: Valor | D11: 6
A13: Sacolinha M | D13: 7
A14: =Referencias!B84 -> Papel 180gr A4 | B14: 3 | C14: =Referencias!F84 -> 0.32 | D14: =B14*C14 -> 0.96
A15: =Referencias!B85 -> Alça - Fio Nautico circulo branco | B15: =0.32*2 -> 0.64 | C15: =Referencias!F85 -> 0.14 | D15: =B15*C15 -> 0.0896
A16: =Referencias!B83 -> Impressão A4 | B16: 3 | C16: =Referencias!F83 -> 0.5 | D16: =B16*C16 -> 1.5
A17: =Referencias!B62 -> Frete | C17: =Referencias!F62 -> 0 | D17: =B17*C17 -> 0
A18: =Referencias!B14 -> Desgaste Bloquinho/Outros | B18: 1 | C18: =Referencias!F14 -> 0.5 | D18: =B18*C18 -> 0.5
A19: =Referencias!B17 -> Embalagem Padrão | B19: 1 | C19: =Referencias!F17 -> 1.5 | D19: =B19*C19 -> 1.5
A20: Custo | D20: =SUM(D14:D19) -> 4.5496
A21: Margem | B21: 0.55 | C21: =D20*B21 -> 2.50228 | D21: =D20+C21 -> 7.05188
A22: Pesquisa
A23: Valor | D23: 7
A25: Sacolinha 8,5 x 8,5 | D25: 5.5
A26: =Referencias!B84 -> Papel 180gr A4 | B26: 1 | C26: =Referencias!F84 -> 0.32 | D26: =B26*C26 -> 0.32
A27: =Referencias!B85 -> Alça - Fio Nautico circulo branco | B27: 0.51 | C27: =Referencias!F85 -> 0.14 | D27: =B27*C27 -> 0.0714
A28: =Referencias!B83 -> Impressão A4 | B28: 1 | C28: =Referencias!F83 -> 0.5 | D28: =B28*C28 -> 0.5
A29: =Referencias!B62 -> Frete | C29: =Referencias!F62 -> 0 | D29: =B29*C29 -> 0
A30: =Referencias!B13 -> Desgaste Agenda | B30: 1 | C30: =Referencias!F13 -> 1 | D30: =B30*C30 -> 1
A31: =Referencias!B17 -> Embalagem Padrão | B31: 1 | C31: =Referencias!F17 -> 1.5 | D31: =B31*C31 -> 1.5
A32: Custo | D32: =SUM(D26:D31) -> 3.3914
A33: Margem | B33: 0.55 | C33: =D32*B33 -> 1.86527 | D33: =D32+C33 -> 5.25667
A34: Pesquisa
A35: Valor | D35: 5.5
A37: Sacolinha M reciclado | D37: 8
A38: =Referencias!B86 -> Papel 180gr A4 Reciclado | B38: 3 | C38: =Referencias!F86 -> 0.25 | D38: =B38*C38 -> 0.75
A39: =Referencias!B87 -> Alça - Cordão de Algodão | B39: 0.51 | C39: =Referencias!F87 -> 0.52 | D39: =B39*C39 -> 0.2652
A40: =Referencias!B83 -> Impressão A4 | B40: 3 | C40: =Referencias!F83 -> 0.5 | D40: =B40*C40 -> 1.5
A41: =Referencias!B62 -> Frete | C41: =Referencias!F62 -> 0 | D41: =B41*C41 -> 0
A42: =Referencias!B13 -> Desgaste Agenda | B42: 1 | C42: =Referencias!F13 -> 1 | D42: =B42*C42 -> 1
A43: =Referencias!B17 -> Embalagem Padrão | B43: 1 | C43: =Referencias!F17 -> 1.5 | D43: =B43*C43 -> 1.5
A44: Custo | D44: =SUM(D38:D43) -> 5.0152
A45: Margem | B45: 0.55 | C45: =D44*B45 -> 2.75836 | D45: =D44+C45 -> 7.77356
A46: Pesquisa
A47: Valor | D47: 8

Sheet Sacolas 40
A1: Sacolinha P | D1: 6
A2: =Referencias!B84 -> Papel 180gr A4 | B2: 80 | C2: =Referencias!F84 -> 0.32 | D2: =B2*C2 -> 25.6
A3: =Referencias!B85 -> Alça - Fio Nautico circulo branco | B3: =0.26*2*40 -> 20.8 | C3: =Referencias!F85 -> 0.14 | D3: =B3*C3 -> 2.912
A4: =Referencias!B83 -> Impressão A4 | B4: 80 | C4: =Referencias!F83 -> 0.5 | D4: =B4*C4 -> 40
A5: =Referencias!B62 -> Frete | C5: =Referencias!F62 -> 0 | D5: =B5*C5 -> 0
A6: =Referencias!B14 -> Desgaste Bloquinho/Outros | B6: 40 | C6: =Referencias!F14 -> 0.5 | D6: =B6*C6 -> 20
A7: =Referencias!B17 -> Embalagem Padrão | B7: 1 | C7: =Referencias!F17 -> 1.5 | D7: =B7*C7 -> 1.5
A8: Custo | D8: =SUM(D2:D7) -> 90.012
A9: Margem | B9: 0.55 | C9: =D8*B9 -> 49.5066 | D9: =D8+C9 -> 139.5186
A10: Pesquisa
A11: Valor | D11: 125
A13: Sacolinha M | D13: 7
A14: =Referencias!B84 -> Papel 180gr A4 | B14: 120 | C14: =Referencias!F84 -> 0.32 | D14: =B14*C14 -> 38.4
A15: =Referencias!B85 -> Alça - Fio Nautico circulo branco | B15: =0.32*2*40 -> 25.6 | C15: =Referencias!F85 -> 0.14 | D15: =B15*C15 -> 3.584
A16: =Referencias!B83 -> Impressão A4 | B16: 120 | C16: =Referencias!F83 -> 0.5 | D16: =B16*C16 -> 60
A17: =Referencias!B62 -> Frete | C17: =Referencias!F62 -> 0 | D17: =B17*C17 -> 0
A18: =Referencias!B14 -> Desgaste Bloquinho/Outros | B18: 40 | C18: =Referencias!F14 -> 0.5 | D18: =B18*C18 -> 20
A19: =Referencias!B17 -> Embalagem Padrão | B19: 1 | C19: =Referencias!F17 -> 1.5 | D19: =B19*C19 -> 1.5
A20: Custo | D20: =SUM(D14:D19) -> 123.484
A21: Margem | B21: 0.55 | C21: =D20*B21 -> 67.9162 | D21: =D20+C21 -> 191.4002
A22: Pesquisa
A23: Valor | D23: 170
A25: Sacolinha 8,5 x 8,5 | D25: 5.5
A26: =Referencias!B84 -> Papel 180gr A4 | B26: 1 | C26: =Referencias!F84 -> 0.32 | D26: =B26*C26 -> 0.32
A27: =Referencias!B85 -> Alça - Fio Nautico circulo branco | B27: 0.51 | C27: =Referencias!F85 -> 0.14 | D27: =B27*C27 -> 0.0714
A28: =Referencias!B83 -> Impressão A4 | B28: 1 | C28: =Referencias!F83 -> 0.5 | D28: =B28*C28 -> 0.5
A29: =Referencias!B62 -> Frete | C29: =Referencias!F62 -> 0 | D29: =B29*C29 -> 0
A30: =Referencias!B13 -> Desgaste Agenda | B30: 1 | C30: =Referencias!F13 -> 1 | D30: =B30*C30 -> 1
A31: =Referencias!B17 -> Embalagem Padrão | B31: 1 | C31: =Referencias!F17 -> 1.5 | D31: =B31*C31 -> 1.5
A32: Custo | D32: =SUM(D26:D31) -> 3.3914
A33: Margem | B33: 0.55 | C33: =D32*B33 -> 1.86527 | D33: =D32+C33 -> 5.25667
A34: Pesquisa
A35: Valor | D35: 5.5
A37: Sacolinha M reciclado | D37: 8
A38: =Referencias!B86 -> Papel 180gr A4 Reciclado | B38: 3 | C38: =Referencias!F86 -> 0.25 | D38: =B38*C38 -> 0.75
A39: =Referencias!B87 -> Alça - Cordão de Algodão | B39: 0.51 | C39: =Referencias!F87 -> 0.52 | D39: =B39*C39 -> 0.2652
A40: =Referencias!B83 -> Impressão A4 | B40: 3 | C40: =Referencias!F83 -> 0.5 | D40: =B40*C40 -> 1.5
A41: =Referencias!B62 -> Frete | C41: =Referencias!F62 -> 0 | D41: =B41*C41 -> 0
A42: =Referencias!B13 -> Desgaste Agenda | B42: 1 | C42: =Referencias!F13 -> 1 | D42: =B42*C42 -> 1
A43: =Referencias!B17 -> Embalagem Padrão | B43: 1 | C43: =Referencias!F17 -> 1.5 | D43: =B43*C43 -> 1.5
A44: Custo | D44: =SUM(D38:D43) -> 5.0152
A45: Margem | B45: 0.55 | C45: =D44*B45 -> 2.75836 | D45: =D44+C45 -> 7.77356
A46: Pesquisa
A47: Valor | D47: 8

Sheet Arraiá24
A1: Mini Chapéu em Crochê | D1: 15
A2: =Referencias!B200 -> Lã Balloon 100g | B2: 20 | C2: =Referencias!F200 -> 0.17 | D2: =B2*C2 -> 3.4
A3: =Referencias!B201 -> Bico de Pato Jacaré com Garra | B3: 1 | C3: =Referencias!F201 -> 0.78 | D3: =B3*C3 -> 0.78
A4: =Referencias!B62 -> Frete | C4: =Referencias!F62 -> 0 | D4: =B4*C4 -> 0
A5: =Referencias!B14 -> Desgaste Bloquinho/Outros | B5: 1 | C5: =Referencias!F14 -> 0.5 | D5: =B5*C5 -> 0.5
A6: =Referencias!B17 -> Embalagem Padrão | B6: 1 | C6: =Referencias!F17 -> 1.5 | D6: =B6*C6 -> 1.5
A7: Custo | D7: =SUM(D2:D6) -> 6.18
A8: Margem | B8: 0.55 | C8: =D7*B8 -> 3.399 | D8: =D7+C8 -> 9.579
A9: Pesquisa | B9: praper | C9: mp
A10: Valor | B10: 10 | C10: 15 | D10: 15
A12: Descanso de Panela em Croche Malha - Quadrado | D12: 15
A13: =Referencias!B202 -> Fio de Malha Euroroma 140m | B13: 140 | C13: =Referencias!F202 -> 0.02 | D13: =B13*C13 -> 2.8
A14: =Referencias!B62 -> Frete | C14: =Referencias!F62 -> 0 | D14: =B14*C14 -> 0
A15: =Referencias!B14 -> Desgaste Bloquinho/Outros | B15: 1 | C15: =Referencias!F14 -> 0.5 | D15: =B15*C15 -> 0.5
A16: =Referencias!B17 -> Embalagem Padrão | B16: 1 | C16: =Referencias!F17 -> 1.5 | D16: =B16*C16 -> 1.5
A17: Custo | D17: =SUM(D13:D16) -> 4.8
A18: Margem | B18: 0.55 | C18: =D17*B18 -> 2.64 | D18: =D17+C18 -> 7.44
A19: Pesquisa
A20: Valor | D20: 15
A22: Descanso de Panela em Croche Malha - Flor | D22: 15
A23: =Referencias!B202 -> Fio de Malha Euroroma 140m | B23: 140 | C23: =Referencias!F202 -> 0.02 | D23: =B23*C23 -> 2.8
A24: =Referencias!B62 -> Frete | C24: =Referencias!F62 -> 0 | D24: =B24*C24 -> 0
A25: =Referencias!B14 -> Desgaste Bloquinho/Outros | B25: 1 | C25: =Referencias!F14 -> 0.5 | D25: =B25*C25 -> 0.5
A26: =Referencias!B17 -> Embalagem Padrão | B26: 1 | C26: =Referencias!F17 -> 1.5 | D26: =B26*C26 -> 1.5
A27: Custo | D27: =SUM(D23:D26) -> 4.8
A28: Margem | B28: 0.55 | C28: =D27*B28 -> 2.64 | D28: =D27+C28 -> 7.44
A29: Pesquisa
A30: Valor | D30: 15
A32: Descanso de Panela em Croche Malha - Duplo | D32: 20
A33: =Referencias!B202 -> Fio de Malha Euroroma 140m | B33: 250 | C33: =Referencias!F202 -> 0.02 | D33: =B33*C33 -> 5
A34: =Referencias!B62 -> Frete | B34: 0 | C34: =Referencias!F62 -> 0 | D34: =B34*C34 -> 0
A35: =Referencias!B14 -> Desgaste Bloquinho/Outros | B35: 1 | C35: =Referencias!F14 -> 0.5 | D35: =B35*C35 -> 0.5
A36: =Referencias!B17 -> Embalagem Padrão | B36: 1 | C36: =Referencias!F17 -> 1.5 | D36: =B36*C36 -> 1.5
A37: Custo | D37: =SUM(D33:D36) -> 7
A38: Margem | B38: 0.55 | C38: =D37*B38 -> 3.85 | D38: =D37+C38 -> 10.85
A39: Pesquisa
A40: Valor | D40: 20

Sheet Mães24
A1: Caderno de Receitas | D1: 45
A2: =Referencias!B58 -> Papelão 16x22 | B2: 2 | C2: =Referencias!F58 -> 1.5 | D2: =B2*C2 -> 3
A3: =Referencias!B53 -> Papel fotografico A4 | B3: 2 | C3: =Referencias!F53 -> 0.8 | D3: =B3*C3 -> 1.6
A4: =Referencias!B31 -> bopp | B4: =2*0.3 -> 0.6 | C4: =Referencias!F31 -> 0.45 | D4: =B4*C4 -> 0.27
A5: =Referencias!B48 -> Papel guarda 15,5x21,5 offset adesivo | B5: 2 | C5: =Referencias!F48 -> 0.75 | D5: =B5*C5 -> 1.5
A6: =Referencias!B45 -> miolo 90gr A5 | B6: 102 | C6: =Referencias!F45 -> 0.05 | D6: =B6*C6 -> 5.1
A7: =Referencias!B19 -> Espiral 29mm | B7: 1 | C7: =Referencias!F19 -> 1.83 | D7: =B7*C7 -> 1.83
A8: =Referencias!B22 -> Impressao Capa A4 | B8: 2 | C8: =Referencias!F22 -> 0.5 | D8: =B8*C8 -> 1
A9: =Referencias!B29 -> Impressao Miolo Frente Verso A5 | B9: 102 | C9: =Referencias!F29 -> 0.06 | D9: =B9*C9 -> 6.12
A10: =Referencias!B62 -> Frete | C10: =Referencias!F62 -> 0 | D10: =B10*C10 -> 0
A11: =Referencias!B15 -> Desgaste Caderno A5 | B11: 1 | C11: =Referencias!F15 -> 2 | D11: =B11*C11 -> 2
A12: =Referencias!B17 -> Embalagem Padrão | B12: 1 | C12: =Referencias!F17 -> 1.5 | D12: =B12*C12 -> 1.5
A13: Custo | D13: =SUM(D2:D12) -> 23.92
A14: Margem | B14: 0.55 | C14: =D13*B14 -> 13.156 | D14: =D13+C14 -> 37.076
A15: Pesquisa | B15: praper | C15: mp
A16: Valor | D16: 50
A18: Terço Aparecida P | D18: 20
A19: =Referencias!B165 -> Entermeio Nossa Senhora Aparecida 1,5x1,1 | B19: 1 | C19: =Referencias!F165 -> 0.97 | D19: =B19*C19 -> 0.97
A20: =Referencias!B168 -> Cruxifixo Metal Niquel | B20: 1 | C20: =Referencias!F168 -> 0.85 | D20: =B20*C20 -> 0.85
A21: =Referencias!B161 -> Miçanga Jablonex | B21: 3 | C21: =Referencias!F161 -> 0.47 | D21: =B21*C21 -> 1.41
A22: =Referencias!B172 -> Argola | B22: 1 | C22: =Referencias!F172 -> 0.14 | D22: =B22*C22 -> 0.14
A23: =Referencias!B170 -> Contrapino | B23: 59 | C23: =Referencias!F170 -> 0.02 | D23: =B23*C23 -> 1.18
A24: =Referencias!B173 -> Caixa Acrilica 5x5 | B24: 1 | C24: =Referencias!F173 -> 1 | D24: =B24*C24 -> 1
A25: =Referencias!B174 -> Feltro 10x5 | B25: 1 | C25: =Referencias!F174 -> 0.13 | D25: =B25*C25 -> 0.13
A26: =Referencias!B9 -> Fita cetim | B26: 0.15 | C26: =Referencias!F9 -> 0.13 | D26: =B26*C26 -> 0.0195
A27: =Referencias!B62 -> Frete | C27: =Referencias!F62 -> 0 | D27: =B27*C27 -> 0
A28: =Referencias!B14 -> Desgaste Bloquinho/Outros | B28: 1 | C28: =Referencias!F14 -> 0.5 | D28: =B28*C28 -> 0.5
A29: =Referencias!B17 -> Embalagem Padrão | B29: 1 | C29: =Referencias!F17 -> 1.5 | D29: =B29*C29 -> 1.5
A30: Custo | D30: =SUM(D19:D29) -> 7.6995
A31: Margem | B31: 0.55 | C31: =D30*B31 -> 4.234725 | D31: =D30+C31 -> 11.934225
A32: Pesquisa
A33: Valor | D33: 20
A35: Terço Aparecida M | D35: 30
A36: =Referencias!B164 -> Entermeio Nossa Senhora Aparecida 1,9x1,5 | B36: 1 | C36: =Referencias!F164 -> 1.74 | D36: =B36*C36 -> 1.74
A37: =Referencias!B169 -> Cruz Face de Cristo 3,3x2 | B37: 1 | C37: =Referencias!F169 -> 1.2 | D37: =B37*C37 -> 1.2
A38: =Referencias!B160 -> Balão de acrilico | B38: 6 | C38: =Referencias!F160 -> 0.16 | D38: =B38*C38 -> 0.96
A39: =Referencias!B163 -> Conta Plastica Florzinha | B39: 1 | C39: =Referencias!F163 -> 0.19 | D39: =B39*C39 -> 0.19
A40: =Referencias!B172 -> Argola | B40: 1 | C40: =Referencias!F172 -> 0.14 | D40: =B40*C40 -> 0.14
A41: =Referencias!B170 -> Contrapino | B41: 59 | C41: =Referencias!F170 -> 0.02 | D41: =B41*C41 -> 1.18
A42: =Referencias!B173 -> Caixa Acrilica 5x5 | B42: 1 | C42: =Referencias!F173 -> 1 | D42: =B42*C42 -> 1
A43: =Referencias!B174 -> Feltro 10x5 | B43: 1 | C43: =Referencias!F174 -> 0.13 | D43: =B43*C43 -> 0.13
A44: =Referencias!B9 -> Fita cetim | B44: 0.15 | C44: =Referencias!F9 -> 0.13 | D44: =B44*C44 -> 0.0195
A45: =Referencias!B62 -> Frete | C45: =Referencias!F62 -> 0 | D45: =B45*C45 -> 0
A46: =Referencias!B14 -> Desgaste Bloquinho/Outros | B46: 1 | C46: =Referencias!F14 -> 0.5 | D46: =B46*C46 -> 0.5
A47: =Referencias!B17 -> Embalagem Padrão | B47: 1 | C47: =Referencias!F17 -> 1.5 | D47: =B47*C47 -> 1.5
A48: Custo | D48: =SUM(D36:D47) -> 8.5595
A49: Margem | B49: 0.55 | C49: =D48*B49 -> 4.707725 | D49: =D48+C49 -> 13.267225
A50: Pesquisa
A51: Valor | D51: 30
A53: Terço Aparecida Infantil | D53: 25
A54: =Referencias!B167 -> Cruz e Entremeio emborrachado | B54: 1 | C54: =Referencias!F167 -> 5.9 | D54: =B54*C54 -> 5.9
A55: =Referencias!B162 -> Cristal Plastico | B55: 6 | C55: =Referencias!F160 -> 0.16 | D55: =B55*C55 -> 0.96
A56: =Referencias!B171 -> Triangulo | B56: 1 | C56: =Referencias!F171 -> 0.23 | D56: =B56*C56 -> 0.23
A57: =Referencias!B172 -> Argola | B57: 1 | C57: =Referencias!F172 -> 0.14 | D57: =B57*C57 -> 0.14
A58: =Referencias!B170 -> Contrapino | B58: 59 | C58: =Referencias!F170 -> 0.02 | D58: =B58*C58 -> 1.18
A59: =Referencias!B173 -> Caixa Acrilica 5x5 | B59: 1 | C59: =Referencias!F173 -> 1 | D59: =B59*C59 -> 1
A60: =Referencias!B174 -> Feltro 10x5 | B60: 1 | C60: =Referencias!F174 -> 0.13 | D60: =B60*C60 -> 0.13
A61: =Referencias!B9 -> Fita cetim | B61: 0.15 | C61: =Referencias!F9 -> 0.13 | D61: =B61*C61 -> 0.0195
A62: =Referencias!B62 -> Frete | B62: 0 | C62: =Referencias!F62 -> 0 | D62: =B62*C62 -> 0
A63: =Referencias!B14 -> Desgaste Bloquinho/Outros | B63: 1 | C63: =Referencias!F14 -> 0.5 | D63: =B63*C63 -> 0.5
A64: =Referencias!B17 -> Embalagem Padrão | B64: 1 | C64: =Referencias!F17 -> 1.5 | D64: =B64*C64 -> 1.5
A65: Custo | D65: =SUM(D54:D64) -> 11.5595
A66: Margem | B66: 0.55 | C66: =D65*B66 -> 6.357725 | D66: =D65+C66 -> 17.917225
A67: Pesquisa
A68: Valor | D68: 25
A70: Terço São Bento | D70: 20
A71: =Referencias!B166 -> Entermeio Medalha de São Bento 1,5x1,5 | B71: 1 | C71: =Referencias!F166 -> 0.95 | D71: =B71*C71 -> 0.95
A72: =Referencias!B168 -> Cruxifixo Metal Niquel | B72: 1 | C72: =Referencias!F168 -> 0.85 | D72: =B72*C72 -> 0.85
A73: =Referencias!B160 -> Balão de acrilico | B73: 6 | C73: =Referencias!F160 -> 0.16 | D73: =B73*C73 -> 0.96
A74: =Referencias!B172 -> Argola | B74: 1 | C74: =Referencias!F172 -> 0.14 | D74: =B74*C74 -> 0.14
A75: =Referencias!B170 -> Contrapino | B75: 59 | C75: =Referencias!F170 -> 0.02 | D75: =B75*C75 -> 1.18
A76: =Referencias!B173 -> Caixa Acrilica 5x5 | B76: 0.5 | C76: =Referencias!F173 -> 1 | D76: =B76*C76 -> 0.5
A77: =Referencias!B174 -> Feltro 10x5 | B77: 1 | C77: =Referencias!F174 -> 0.13 | D77: =B77*C77 -> 0.13
A78: =Referencias!B9 -> Fita cetim | B78: 0.15 | C78: =Referencias!F9 -> 0.13 | D78: =B78*C78 -> 0.0195
A79: =Referencias!B62 -> Frete | C79: =Referencias!F62 -> 0 | D79: =B79*C79 -> 0
A80: =Referencias!B14 -> Desgaste Bloquinho/Outros | B80: 1 | C80: =Referencias!F14 -> 0.5 | D80: =B80*C80 -> 0.5
A81: =Referencias!B17 -> Embalagem Padrão | B81: 1 | C81: =Referencias!F17 -> 1.5 | D81: =B81*C81 -> 1.5
A82: Custo | D82: =SUM(D71:D81) -> 6.7295
A83: Margem | B83: 0.55 | C83: =D82*B83 -> 3.701225 | D83: =D82+C83 -> 10.430725
A84: Pesquisa
A85: Valor | D85: 20
A87: Caderno A5 | D87: 40
A88: =Referencias!B58 -> Papelão 16x22 | B88: 2 | C88: =Referencias!F58 -> 1.5 | D88: =B88*C88 -> 3
A89: =Referencias!B53 -> Papel fotografico A4 | B89: 2 | C89: =Referencias!F53 -> 0.8 | D89: =B89*C89 -> 1.6
A90: =Referencias!B31 -> bopp | B90: =0.3*2 -> 0.6 | C90: =Referencias!F31 -> 0.45 | D90: =B90*C90 -> 0.27
A91: =Referencias!B48 -> Papel guarda 15,5x21,5 offset adesivo | B91: 2 | C91: =Referencias!F48 -> 0.75 | D91: =B91*C91 -> 1.5
A92: =Referencias!B45 -> miolo 90gr A5 | B92: 81 | C92: =Referencias!F45 -> 0.05 | D92: =B92*C92 -> 4.05
A93: =Referencias!B19 -> Espiral 29mm | B93: 1 | C93: =Referencias!F19 -> 1.83 | D93: =B93*C93 -> 1.83
A94: =Referencias!B22 -> Impressao Capa A4 | B94: 2 | C94: =Referencias!F22 -> 0.5 | D94: =B94*C94 -> 1
A95: =Referencias!B29 -> Impressao Miolo Frente Verso A5 | B95: 81 | C95: =Referencias!F29 -> 0.06 | D95: =B95*C95 -> 4.86
A96: =Referencias!B62 -> Frete | C96: =Referencias!F62 -> 0 | D96: =B96*C96 -> 0
A97: =Referencias!B15 -> Desgaste Caderno A5 | B97: 1 | C97: =Referencias!F15 -> 2 | D97: =B97*C97 -> 2
A98: =Referencias!B17 -> Embalagem Padrão | B98: 1 | C98: =Referencias!F17 -> 1.5 | D98: =B98*C98 -> 1.5
A99: Custo | D99: =SUM(D88:D98) -> 21.61
A100: Margem | B100: 0.55 | C100: =D99*B100 -> 11.8855 | D100: =D99+C100 -> 33.4955
A101: Pesquisa | B101: MP mimos
A102: Valor | B102: 39 | D102: 40
A104: Caderneta Vacina Pet | D104: 30
A105: =Referencias!B58 -> Papelão 16x22 | B105: 2 | C105: =Referencias!F58 -> 1.5 | D105: =B105*C105 -> 3
A106: =Referencias!B53 -> Papel fotografico A4 | B106: 2 | C106: =Referencias!F53 -> 0.8 | D106: =B106*C106 -> 1.6
...

Sheet Pascoa24
A1: Caça aos ovos | D1: 15
A2: =Referencias!B37 -> miolo 180gr A4 | B2: 5 | C2: =Referencias!F37 -> 0.32 | D2: =B2*C2 -> 1.6
A3: =Referencias!B22 -> Impressao Capa A4 | B3: 5 | C3: =Referencias!F22 -> 0.5 | D3: =B3*C3 -> 2.5
A4: =Referencias!B62 -> Frete | C4: =Referencias!F62 -> 0 | D4: =B4*C4 -> 0
A5: =Referencias!B14 -> Desgaste Bloquinho/Outros | B5: 1 | C5: =Referencias!F14 -> 0.5 | D5: =B5*C5 -> 0.5
A6: =Referencias!B17 -> Embalagem Padrão | B6: 1 | C6: =Referencias!F17 -> 1.5 | D6: =B6*C6 -> 1.5
A7: Custo | D7: =SUM(D2:D6) -> 6.1
A8: Margem | B8: 0.55 | C8: =D7*B8 -> 3.355 | D8: =D7+C8 -> 9.455
A9: Pesquisa
A10: Valor | D10: 20
A12: Sacolinha P | D12: 5.5
A13: =Referencias!B84 -> Papel 180gr A4 | B13: 2 | C13: =Referencias!F84 -> 0.32 | D13: =B13*C13 -> 0.64
A14: =Referencias!B85 -> Alça - Fio Nautico circulo branco | B14: 0.52 | C14: =Referencias!F85 -> 0.14 | D14: =B14*C14 -> 0.0728
A15: =Referencias!B83 -> Impressão A4 | B15: 2 | C15: =Referencias!F83 -> 0.5 | D15: =B15*C15 -> 1
A16: =Referencias!B62 -> Frete | C16: =Referencias!F62 -> 0 | D16: =B16*C16 -> 0
A17: =Referencias!B14 -> Desgaste Bloquinho/Outros | B17: 1 | C17: =Referencias!F14 -> 0.5 | D17: =B17*C17 -> 0.5
A18: =Referencias!B17 -> Embalagem Padrão | B18: 1 | C18: =Referencias!F17 -> 1.5 | D18: =B18*C18 -> 1.5
A19: Custo | D19: =SUM(D13:D18) -> 3.7128
A20: Margem | B20: 0.55 | C20: =D19*B20 -> 2.04204 | D20: =D19+C20 -> 5.75484
A21: Pesquisa
A22: Valor | D22: 6
A24: Sacolinha G | D24: 6.5
A25: =Referencias!B84 -> Papel 180gr A4 | B25: 3 | C25: =Referencias!F84 -> 0.32 | D25: =B25*C25 -> 0.96
A26: =Referencias!B85 -> Alça - Fio Nautico circulo branco | B26: 0.64 | C26: =Referencias!F85 -> 0.14 | D26: =B26*C26 -> 0.0896
A27: =Referencias!B83 -> Impressão A4 | B27: 3 | C27: =Referencias!F83 -> 0.5 | D27: =B27*C27 -> 1.5
A28: =Referencias!B62 -> Frete | B28: 0 | C28: =Referencias!F62 -> 0 | D28: =B28*C28 -> 0
A29: =Referencias!B14 -> Desgaste Bloquinho/Outros | B29: 1 | C29: =Referencias!F14 -> 0.5 | D29: =B29*C29 -> 0.5
A30: =Referencias!B17 -> Embalagem Padrão | B30: 1 | C30: =Referencias!F17 -> 1.5 | D30: =B30*C30 -> 1.5
A31: Custo | D31: =SUM(D25:D30) -> 4.5496
A32: Margem | B32: 0.55 | C32: =D31*B32 -> 2.50228 | D32: =D31+C32 -> 7.05188
A33: Pesquisa
A34: Valor | D34: 7.5
A36: Saquinho bom bom | D36: 4
A37: =Referencias!B100 -> Papel 180gr A6 | B37: 1 | C37: =Referencias!F100 -> 0.08 | D37: =B37*C37 -> 0.08
A38: =Referencias!B114 -> Sonho de Valsa 15g | B38: 1 | C38: =Referencias!F114 -> 1.17 | D38: =B38*C38 -> 1.17
A39: =Referencias!B24 -> Impressao Capa A6 | B39: 1 | C39: =Referencias!F24 -> 0.13 | D39: =B39*C39 -> 0.13
A40: =Referencias!B9 -> Fita cetim | B40: 0.15 | C40: =Referencias!F9 -> 0.13 | D40: =B40*C40 -> 0.0195
A41: =Referencias!B62 -> Frete | C41: =Referencias!F62 -> 0 | D41: =B41*C41 -> 0
A42: =Referencias!B14 -> Desgaste Bloquinho/Outros | B42: 1 | C42: =Referencias!F14 -> 0.5 | D42: =B42*C42 -> 0.5
A43: =Referencias!B107 -> Embalagem Atacado | B43: 1 | C43: =Referencias!F107 -> 0.5 | D43: =B43*C43 -> 0.5
A44: Custo | D44: =SUM(D37:D43) -> 2.3995
A45: Margem | B45: 0.55 | C45: =D44*B45 -> 1.319725 | D45: =D44+C45 -> 3.719225
A46: Pesquisa
A47: Valor | D47: 4
A49: Saquinho Bom bom c/ 10 | D49: 27
A50: =Referencias!B100 -> Papel 180gr A6 | B50: 10 | C50: =Referencias!F100 -> 0.08 | D50: =B50*C50 -> 0.8
A51: =Referencias!B114 -> Sonho de Valsa 15g | B51: 10 | C51: =Referencias!F114 -> 1.17 | D51: =B51*C51 -> 11.7
A52: =Referencias!B24 -> Impressao Capa A6 | B52: 10 | C52: =Referencias!F24 -> 0.13 | D52: =B52*C52 -> 1.3
A53: =Referencias!B9 -> Fita cetim | B53: =0.15*10 -> 1.5 | C53: =Referencias!F9 -> 0.13 | D53: =B53*C53 -> 0.195
A54: =Referencias!B62 -> Frete | C54: =Referencias!F62 -> 0 | D54: =B54*C54 -> 0
A55: =Referencias!B14 -> Desgaste Bloquinho/Outros | B55: 1 | C55: =Referencias!F14 -> 0.5 | D55: =B55*C55 -> 0.5
A56: =Referencias!B17 -> Embalagem Padrão | B56: 1 | C56: =Referencias!F17 -> 1.5 | D56: =B56*C56 -> 1.5
A57: Custo | D57: =SUM(D50:D56) -> 15.995
A58: Margem | B58: 0.55 | C58: =D57*B58 -> 8.79725 | D58: =D57+C58 -> 24.79225
A59: Pesquisa
A60: Valor | D60: 27
A62: Pasta com desenho colorir
A63: =Referencias!B38 -> Papel 240g A4 | B63: 3 | C63: =Referencias!F38 -> 0.42 | D63: =B63*C63 -> 1.26
A64: =Referencias!B45 -> miolo 90gr A5 | B64: 10 | C64: =Referencias!F45 -> 0.05 | D64: =B64*C64 -> 0.5
A65: =Referencias!B156 -> Lápis de Cor 12 cores meio lápis redondo HT 11.1702 Happy-time | B65: 1 | C65: =Referencias!F156 -> 3.3 | D65: =B65*C65 -> 3.3
A66: =Referencias!B157 -> Elastico roliço | B66: 0.3 | C66: =Referencias!F25 -> 0.25 | D66: =B66*C66 -> 0.075
A67: =Referencias!B10 -> Ilhos | B67: 4 | C67: =Referencias!F10 -> 0.05 | D67: =B67*C67 -> 0.2
A68: =Referencias!B26 -> Impressao Miolo Frente A5 | B68: 10 | C68: =Referencias!F26 -> 0.03 | D68: =B68*C68 -> 0.3
A69: =Referencias!B22 -> Impressao Capa A4 | B69: 3 | C69: =Referencias!F22 -> 0.5 | D69: =B69*C69 -> 1.5
A70: =Referencias!B14 -> Desgaste Bloquinho/Outros | B70: 1 | C70: =Referencias!F14 -> 0.5 | D70: =B70*C70 -> 0.5
A71: =Referencias!B17 -> Embalagem Padrão | B71: 1 | C71: =Referencias!F17 -> 1.5 | D71: =B71*C71 -> 1.5
A72: Custo | D72: =SUM(D63:D71) -> 9.135
A73: Margem | B73: 0.55 | C73: =D72*B73 -> 5.02425 | D73: =D72+C73 -> 14.15925
A74: Pesquisa
A75: Valor | D75: 15
A77: Caixa Presente de Páscoa | D77: 30
A78: =Referencias!B38 -> Papel 240g A4 | B78: 6 | C78: =Referencias!F38 -> 0.42 | D78: =B78*C78 -> 2.52
A79: =Referencias!B9 -> Fita cetim | B79: 0.6 | C79: =Referencias!F9 -> 0.13 | D79: =B79*C79 -> 0.078
A80: =Referencias!B22 -> Impressao Capa A4 | B80: 8 | C80: =Referencias!F22 -> 0.5 | D80: =B80*C80 -> 4
A81: =Referencias!B114 -> Sonho de Valsa 15g | C81: =Referencias!F114 -> 1.17 | D81: =B81*C81 -> 0
A82: =Referencias!B62 -> Frete | C82: =Referencias!F62 -> 0 | D82: =B82*C82 -> 0
A83: =Referencias!B14 -> Desgaste Bloquinho/Outros | B83: 1 | C83: =Referencias!F14 -> 0.5 | D83: =B83*C83 -> 0.5
A84: =Referencias!B17 -> Embalagem Padrão | B84: 1 | C84: =Referencias!F17 -> 1.5 | D84: =B84*C84 -> 1.5
A85: Custo | D85: =SUM(D78:D84) -> 8.598
A86: Margem | B86: 0.55 | C86: =D85*B86 -> 4.7289 | D86: =D85+C86 -> 13.3269
A87: Pesquisa
A88: Valor | D88: 35
A90: Caneta Decorada | D90: 7
A91: =Referencias!B158 -> Caneta decorada | B91: 1 | C91: =Referencias!F158 -> 1.75 | D91: =B91*C91 -> 1.75
A92: =Referencias!B62 -> Frete | C92: =Referencias!F62 -> 0 | D92: =B92*C92 -> 0
A93: =Referencias!B17 -> Embalagem Padrão | B93: 1 | C93: =Referencias!F17 -> 1.5 | D93: =B93*C93 -> 1.5
A94: Custo | D94: =SUM(D91:D93) -> 3.25
A95: Margem | B95: 0.55 | C95: =D94*B95 -> 1.7875 | D95: =D94+C95 -> 5.0375
A96: Pesquisa
A97: Valor | D97: 7
A99: Lapis infinito | D99: 15
A100: =Referencias!B159 -> Lapis infinito | B100: 1 | C100: =Referencias!F159 -> 2.95 | D100: =B100*C100 -> 2.95
A101: =Referencias!B62 -> Frete | C101: =Referencias!F62 -> 0 | D101: =B101*C101 -> 0
A102: =Referencias!B17 -> Embalagem Padrão | B102: 1 | C102: =Referencias!F17 -> 1.5 | D102: =B102*C102 -> 1.5
A103: Custo | D103: =SUM(D100:D102) -> 4.45
A104: Margem | B104: 0.55 | C104: =D103*B104 -> 2.4475 | D104: =D103+C104 -> 6.8975
A105: Pesquisa
A106: Valor | D106: 15
A109: Marca texto | D109: 7
A110: =Referencias!B220 -> Marca texto | B110: 1 | C110: =Referencias!F220 -> 3.17 | D110: =B110*C110 -> 3.17
...

Sheet Mulher24
A1: Chá Personalizado | D1: 4.6
A2: =Referencias!B153 -> Chá Twinings Frutas Silvestres | B2: 1 | C2: =Referencias!F153 -> 1.69 | D2: =B2*C2 -> 1.69
A3: =Referencias!B111 -> Card OffSet 180gr | B3: 1 | C3: =Referencias!F111 -> 0.05 | D3: =B3*C3 -> 0.05
A4: =Referencias!B23 -> Impressao Capa A5 | B4: 1 | C4: =Referencias!F23 -> 0.25 | D4: =B4*C4 -> 0.25
A5: =Referencias!B62 -> Frete | C5: =Referencias!F62 -> 0 | D5: =B5*C5 -> 0
A6: =Referencias!B14 -> Desgaste Bloquinho/Outros | B6: 1 | C6: =Referencias!F14 -> 0.5 | D6: =B6*C6 -> 0.5
A7: =Referencias!B107 -> Embalagem Atacado | B7: 1 | C7: =Referencias!F107 -> 0.5 | D7: =B7*C7 -> 0.5
A8: Custo | D8: =SUM(D2:D7) -> 2.99
A9: Margem | B9: 0.55 | C9: =D8*B9 -> 1.6445 | D9: =D8+C9 -> 4.6345
A10: Pesquisa
A11: Valor | D11: 5
A13: Chá Personalizado c/ 10 | D13: 35
A14: =Referencias!B153 -> Chá Twinings Frutas Silvestres | B14: 10 | C14: =Referencias!F153 -> 1.69 | D14: =B14*C14 -> 16.9
A15: =Referencias!B111 -> Card OffSet 180gr | B15: 10 | C15: =Referencias!F111 -> 0.05 | D15: =B15*C15 -> 0.5
A16: =Referencias!B23 -> Impressao Capa A5 | B16: 10 | C16: =Referencias!F23 -> 0.25 | D16: =B16*C16 -> 2.5
A17: =Referencias!B62 -> Frete | C17: =Referencias!F62 -> 0 | D17: =B17*C17 -> 0
A18: =Referencias!B14 -> Desgaste Bloquinho/Outros | B18: 1 | C18: =Referencias!F14 -> 0.5 | D18: =B18*C18 -> 0.5
A19: =Referencias!B17 -> Embalagem Padrão | B19: 1 | C19: =Referencias!F17 -> 1.5 | D19: =B19*C19 -> 1.5
A20: Custo | D20: =SUM(D14:D19) -> 21.9
A21: Margem | B21: 0.55 | C21: =D20*B21 -> 12.045 | D21: =D20+C21 -> 33.945
A22: Pesquisa
A23: Valor | D23: 40
A25: Chocolate Baton Personalizado | D25: 3.5
A26: =Referencias!B110 -> Chocolate Baton 16g | B26: 1 | C26: =Referencias!F110 -> 0.93 | D26: =B26*C26 -> 0.93
A27: =Referencias!B36 -> miolo 180g A5 | B27: 1 | C27: =Referencias!F36 -> 0.16 | D27: =B27*C27 -> 0.16
A28: =Referencias!B23 -> Impressao Capa A5 | B28: 1 | C28: =Referencias!F23 -> 0.25 | D28: =B28*C28 -> 0.25
A29: =Referencias!B62 -> Frete | C29: =Referencias!F62 -> 0 | D29: =B29*C29 -> 0
A30: =Referencias!B14 -> Desgaste Bloquinho/Outros | B30: 1 | C30: =Referencias!F14 -> 0.5 | D30: =B30*C30 -> 0.5
A31: =Referencias!B107 -> Embalagem Atacado | B31: 1 | C31: =Referencias!F107 -> 0.5 | D31: =B31*C31 -> 0.5
A32: Custo | D32: =SUM(D26:D31) -> 2.34
A33: Margem | B33: 0.55 | C33: =D32*B33 -> 1.287 | D33: =D32+C33 -> 3.627
A34: Pesquisa
A35: Valor | D35: 3.6
A37: Chocolate Baton Personalizado c/ 10 | D37: 30
A38: =Referencias!B110 -> Chocolate Baton 16g | B38: 10 | C38: =Referencias!F110 -> 0.93 | D38: =B38*C38 -> 9.3
A39: =Referencias!B36 -> miolo 180g A5 | B39: 10 | C39: =Referencias!F36 -> 0.16 | D39: =B39*C39 -> 1.6
A40: =Referencias!B23 -> Impressao Capa A5 | B40: 10 | C40: =Referencias!F23 -> 0.25 | D40: =B40*C40 -> 2.5
A41: =Referencias!B62 -> Frete | C41: =Referencias!F62 -> 0 | D41: =B41*C41 -> 0
A42: =Referencias!B14 -> Desgaste Bloquinho/Outros | B42: 1 | C42: =Referencias!F14 -> 0.5 | D42: =B42*C42 -> 0.5
A43: =Referencias!B17 -> Embalagem Padrão | B43: 1 | C43: =Referencias!F17 -> 1.5 | D43: =B43*C43 -> 1.5
A44: Custo | D44: =SUM(D38:D43) -> 15.4
A45: Margem | B45: 0.55 | C45: =D44*B45 -> 8.47 | D45: =D44+C45 -> 23.87
A46: Pesquisa
A47: Valor | D47: 30
A49: Sonho de Valsa Personalizado | D49: 3.5
A50: =Referencias!B114 -> Sonho de Valsa 15g | B50: 1 | C50: =Referencias!F114 -> 1.17 | D50: =B50*C50 -> 1.17
A51: =Referencias!B111 -> Card OffSet 180gr | B51: 1 | C51: =Referencias!F111 -> 0.05 | D51: =B51*C51 -> 0.05
A52: =Referencias!B112 -> Impressao Card | B52: 1 | C52: =Referencias!F112 -> 0.08 | D52: =B52*C52 -> 0.08
A53: =Referencias!B62 -> Frete | C53: =Referencias!F62 -> 0 | D53: =B53*C53 -> 0
A54: =Referencias!B14 -> Desgaste Bloquinho/Outros | B54: 1 | C54: =Referencias!F14 -> 0.5 | D54: =B54*C54 -> 0.5
A55: =Referencias!B107 -> Embalagem Atacado | B55: 1 | C55: =Referencias!F107 -> 0.5 | D55: =B55*C55 -> 0.5
A56: Custo | D56: =SUM(D50:D55) -> 2.3
A57: Margem | B57: 0.55 | C57: =D56*B57 -> 1.265 | D57: =D56+C57 -> 3.565
A58: Pesquisa
A59: Valor | D59: 3.5
A61: Moranguete Personalizado | D61: 2.35
A62: =Referencias!B115 -> Moranguete 13g | B62: 1 | C62: =Referencias!F115 -> 0.39 | D62: =B62*C62 -> 0.39
A63: =Referencias!B111 -> Card OffSet 180gr | B63: 1 | C63: =Referencias!F111 -> 0.05 | D63: =B63*C63 -> 0.05
A64: =Referencias!B112 -> Impressao Card | B64: 1 | C64: =Referencias!F112 -> 0.08 | D64: =B64*C64 -> 0.08
A65: =Referencias!B62 -> Frete | C65: =Referencias!F62 -> 0 | D65: =B65*C65 -> 0
A66: =Referencias!B14 -> Desgaste Bloquinho/Outros | B66: 1 | C66: =Referencias!F14 -> 0.5 | D66: =B66*C66 -> 0.5
A67: =Referencias!B107 -> Embalagem Atacado | B67: 1 | C67: =Referencias!F107 -> 0.5 | D67: =B67*C67 -> 0.5
A68: Custo | D68: =SUM(D62:D67) -> 1.52
A69: Margem | B69: 0.55 | C69: =D68*B69 -> 0.836 | D69: =D68+C69 -> 2.356
A70: Pesquisa
A71: Valor | D71: 2.4

Sheet VoltaAulas24
A1: Agenda Escolar 1 dia | D1: 37.9
A2: =Referencias!B58 -> Papelão 16x22 | B2: 2 | C2: =Referencias!F58 -> 1.5 | D2: =B2*C2 -> 3
A3: =Referencias!B53 -> Papel fotografico A4 | B3: 2 | C3: =Referencias!F53 -> 0.8 | D3: =B3*C3 -> 1.6
A4: =Referencias!B31 -> bopp | B4: =0.3*2 -> 0.6 | C4: =Referencias!F31 -> 0.45 | D4: =B4*C4 -> 0.27
A5: =Referencias!B48 -> Papel guarda 15,5x21,5 offset adesivo | B5: 2 | C5: =Referencias!F48 -> 0.75 | D5: =B5*C5 -> 1.5
A6: =Referencias!B40 -> miolo 75gr A5 | B6: 109 | C6: =Referencias!F40 -> 0.03 | D6: =B6*C6 -> 3.27
A7: =Referencias!B34 -> Bolso offset 180gr | B7: 1 | C7: =Referencias!F34 -> 0.32 | D7: =B7*C7 -> 0.32
A8: =Referencias!B19 -> Espiral 29mm | B8: 1 | C8: =Referencias!F19 -> 1.83 | D8: =B8*C8 -> 1.83
A9: =Referencias!B22 -> Impressao Capa A4 | B9: 2 | C9: =Referencias!F22 -> 0.5 | D9: =B9*C9 -> 1
A10: =Referencias!B29 -> Impressao Miolo Frente Verso A5 | B10: 109 | C10: =Referencias!F29 -> 0.06 | D10: =B10*C10 -> 6.54
A11: =Referencias!B21 -> Impressao Bolso A4 | B11: 1 | C11: =Referencias!F21 -> 1 | D11: =B11*C11 -> 1
A12: =Referencias!B62 -> Frete | C12: =Referencias!F62 -> 0 | D12: =B12*C12 -> 0
A13: =Referencias!B13 -> Desgaste Agenda | B13: 1 | C13: =Referencias!F13 -> 1 | D13: =B13*C13 -> 1
A14: =Referencias!B17 -> Embalagem Padrão | B14: 1 | C14: =Referencias!F17 -> 1.5 | D14: =B14*C14 -> 1.5
A15: Custo | D15: =SUM(D2:D14) -> 22.83
A16: Margem | B16: 0.55 | C16: =D15*B16 -> 12.5565 | D16: =D15+C16 -> 35.3865
A17: Pesquisa | B17: MP mimos
A18: Valor | B18: 55 | D18: 40
A20: Agenda Escolar 2 dias | D20: 30
A21: =Referencias!B58 -> Papelão 16x22 | B21: 2 | C21: =Referencias!F58 -> 1.5 | D21: =B21*C21 -> 3
A22: =Referencias!B53 -> Papel fotografico A4 | B22: 2 | C22: =Referencias!F53 -> 0.8 | D22: =B22*C22 -> 1.6
A23: =Referencias!B31 -> bopp | B23: =0.3*2 -> 0.6 | C23: =Referencias!F31 -> 0.45 | D23: =B23*C23 -> 0.27
A24: =Referencias!B48 -> Papel guarda 15,5x21,5 offset adesivo | B24: 2 | C24: =Referencias!F48 -> 0.75 | D24: =B24*C24 -> 1.5
A25: =Referencias!B45 -> miolo 90gr A5 | B25: 57 | C25: =Referencias!F45 -> 0.05 | D25: =B25*C25 -> 2.85
A26: =Referencias!B34 -> Bolso offset 180gr | B26: 1 | C26: =Referencias!F34 -> 0.32 | D26: =B26*C26 -> 0.32
A27: =Referencias!B69 -> Espiral 20mm | B27: 1 | C27: =Referencias!F69 -> 0.64 | D27: =B27*C27 -> 0.64
A28: =Referencias!B22 -> Impressao Capa A4 | B28: 2 | C28: =Referencias!F22 -> 0.5 | D28: =B28*C28 -> 1
A29: =Referencias!B29 -> Impressao Miolo Frente Verso A5 | B29: 57 | C29: =Referencias!F29 -> 0.06 | D29: =B29*C29 -> 3.42
A30: =Referencias!B21 -> Impressao Bolso A4 | B30: 1 | C30: =Referencias!F21 -> 1 | D30: =B30*C30 -> 1
A31: =Referencias!B62 -> Frete | C31: =Referencias!F62 -> 0 | D31: =B31*C31 -> 0
A32: =Referencias!B13 -> Desgaste Agenda | B32: 1 | C32: =Referencias!F13 -> 1 | D32: =B32*C32 -> 1
A33: =Referencias!B17 -> Embalagem Padrão | B33: 1 | C33: =Referencias!F17 -> 1.5 | D33: =B33*C33 -> 1.5
A34: Custo | D34: =SUM(D21:D33) -> 18.1
A35: Margem | B35: 0.55 | C35: =D34*B35 -> 9.955 | D35: =D34+C35 -> 28.055
A36: Pesquisa | B36: MP mimos
A37: Valor | B37: 39 | D37: 30
A39: Agenda creche | D39: 40
A40: =Referencias!B58 -> Papelão 16x22 | B40: 2 | C40: =Referencias!F58 -> 1.5 | D40: =B40*C40 -> 3
A41: =Referencias!B53 -> Papel fotografico A4 | B41: 2 | C41: =Referencias!F53 -> 0.8 | D41: =B41*C41 -> 1.6
A42: =Referencias!B31 -> bopp | B42: =0.3*2 -> 0.6 | C42: =Referencias!F31 -> 0.45 | D42: =B42*C42 -> 0.27
A43: =Referencias!B48 -> Papel guarda 15,5x21,5 offset adesivo | B43: 2 | C43: =Referencias!F48 -> 0.75 | D43: =B43*C43 -> 1.5
A44: =Referencias!B40 -> miolo 75gr A5 | B44: 130 | C44: =Referencias!F40 -> 0.03 | D44: =B44*C44 -> 3.9
A45: =Referencias!B34 -> Bolso offset 180gr | B45: 1 | C45: =Referencias!F34 -> 0.32 | D45: =B45*C45 -> 0.32
A46: =Referencias!B19 -> Espiral 29mm | B46: 1 | C46: =Referencias!F19 -> 1.83 | D46: =B46*C46 -> 1.83
A47: =Referencias!B22 -> Impressao Capa A4 | B47: 2 | C47: =Referencias!F22 -> 0.5 | D47: =B47*C47 -> 1
A48: =Referencias!B29 -> Impressao Miolo Frente Verso A5 | B48: 130 | C48: =Referencias!F29 -> 0.06 | D48: =B48*C48 -> 7.8
A49: =Referencias!B21 -> Impressao Bolso A4 | B49: 1 | C49: =Referencias!F21 -> 1 | D49: =B49*C49 -> 1
A50: =Referencias!B62 -> Frete | C50: =Referencias!F62 -> 0 | D50: =B50*C50 -> 0
A51: =Referencias!B13 -> Desgaste Agenda | B51: 1 | C51: =Referencias!F13 -> 1 | D51: =B51*C51 -> 1
A52: =Referencias!B17 -> Embalagem Padrão | B52: 1 | C52: =Referencias!F17 -> 1.5 | D52: =B52*C52 -> 1.5
A53: Custo | D53: =SUM(D40:D52) -> 24.72
A54: Margem | B54: 0.55 | C54: =D53*B54 -> 13.596 | D54: =D53+C54 -> 38.316
A55: Pesquisa
A56: Valor | D56: 40
A58: Desk Planner | D58: 35
A59: =Referencias!B58 -> Papelão 16x22 | B59: 2 | C59: =Referencias!F58 -> 1.5 | D59: =B59*C59 -> 3
A60: =Referencias!B53 -> Papel fotografico A4 | B60: 2 | C60: =Referencias!F53 -> 0.8 | D60: =B60*C60 -> 1.6
A61: =Referencias!B31 -> bopp | B61: =0.3*2 -> 0.6 | C61: =Referencias!F31 -> 0.45 | D61: =B61*C61 -> 0.27
A62: =Referencias!B48 -> Papel guarda 15,5x21,5 offset adesivo | B62: 2 | C62: =Referencias!F48 -> 0.75 | D62: =B62*C62 -> 1.5
A63: =Referencias!B45 -> miolo 90gr A5 | B63: 61 | C63: =Referencias!F45 -> 0.05 | D63: =B63*C63 -> 3.05
A64: =Referencias!B34 -> Bolso offset 180gr | B64: 1 | C64: =Referencias!F34 -> 0.32 | D64: =B64*C64 -> 0.32
A65: =Referencias!B69 -> Espiral 20mm | B65: 1 | C65: =Referencias!F69 -> 0.64 | D65: =B65*C65 -> 0.64
A66: =Referencias!B22 -> Impressao Capa A4 | B66: 2 | C66: =Referencias!F22 -> 0.5 | D66: =B66*C66 -> 1
A67: =Referencias!B29 -> Impressao Miolo Frente Verso A5 | B67: 61 | C67: =Referencias!F29 -> 0.06 | D67: =B67*C67 -> 3.66
A68: =Referencias!B21 -> Impressao Bolso A4 | B68: 1 | C68: =Referencias!F21 -> 1 | D68: =B68*C68 -> 1
A69: =Referencias!B62 -> Frete | C69: =Referencias!F62 -> 0 | D69: =B69*C69 -> 0
A70: =Referencias!B16 -> Desgaste Planner/Album/Caderno Universitario | B70: 1 | C70: =Referencias!F16 -> 3 | D70: =B70*C70 -> 3
A71: =Referencias!B17 -> Embalagem Padrão | B71: 1 | C71: =Referencias!F17 -> 1.5 | D71: =B71*C71 -> 1.5
A72: Custo | D72: =SUM(D59:D71) -> 20.54
A73: Margem | B73: 0.55 | C73: =D72*B73 -> 11.297 | D73: =D72+C73 -> 31.837
A74: Pesquisa | B74: MP mimos
A75: Valor | B75: 42.9 | D75: 35
A77: Caderno A5 | D77: 35
A78: =Referencias!B58 -> Papelão 16x22 | B78: 2 | C78: =Referencias!F58 -> 1.5 | D78: =B78*C78 -> 3
A79: =Referencias!B53 -> Papel fotografico A4 | B79: 2 | C79: =Referencias!F53 -> 0.8 | D79: =B79*C79 -> 1.6
A80: =Referencias!B31 -> bopp | B80: =0.3*2 -> 0.6 | C80: =Referencias!F31 -> 0.45 | D80: =B80*C80 -> 0.27
A81: =Referencias!B48 -> Papel guarda 15,5x21,5 offset adesivo | B81: 2 | C81: =Referencias!F48 -> 0.75 | D81: =B81*C81 -> 1.5
A82: =Referencias!B45 -> miolo 90gr A5 | B82: 80 | C82: =Referencias!F45 -> 0.05 | D82: =B82*C82 -> 4
A83: =Referencias!B19 -> Espiral 29mm | B83: 1 | C83: =Referencias!F19 -> 1.83 | D83: =B83*C83 -> 1.83
A84: =Referencias!B22 -> Impressao Capa A4 | B84: 2 | C84: =Referencias!F22 -> 0.5 | D84: =B84*C84 -> 1
A85: =Referencias!B29 -> Impressao Miolo Frente Verso A5 | B85: 80 | C85: =Referencias!F29 -> 0.06 | D85: =B85*C85 -> 4.8
A86: =Referencias!B62 -> Frete | C86: =Referencias!F62 -> 0 | D86: =B86*C86 -> 0
A87: =Referencias!B15 -> Desgaste Caderno A5 | B87: 1 | C87: =Referencias!F15 -> 2 | D87: =B87*C87 -> 2
A88: =Referencias!B17 -> Embalagem Padrão | B88: 1 | C88: =Referencias!F17 -> 1.5 | D88: =B88*C88 -> 1.5
A89: Custo | D89: =SUM(D78:D88) -> 21.5
A90: Margem | B90: 0.55 | C90: =D89*B90 -> 11.825 | D90: =D89+C90 -> 33.325
A91: Pesquisa | B91: MP mimos
A92: Valor | B92: 39 | D92: 40
A94: Caderno A5 | D94: 35
A95: Manteiga | B95: 10 | C95: =68.37/50 -> 1.3674 | D95: =B95*C95 -> 13.674
A96: Papel 180g | B96: 10 | C96: 0.2 | D96: =B96*C96 -> 2
A97: Impressao A4 | B97: 10 | C97: 0.5 | D97: =B97*C97 -> 5
A98: Frete | B98: 0 | C98: 0 | D98: =B98*C98 -> 0
A99: Desgaste | B99: 1 | C99: 0.5 | D99: =B99*C99 -> 0.5
A100: Embalagem | B100: 1 | C100: 1.5 | D100: =B100*C100 -> 1.5
D101: =B101*C101 -> 0
D102: =B102*C102 -> 0
D103: =B103*C103 -> 0
D104: =B104*C104 -> 0
D105: =B105*C105 -> 0
...

Sheet Coleção24
A1: Agenda 1 dia datada | D1: 79.9
A2: =Referencias!B58 -> Papelão 16x22 | B2: 2 | C2: =Referencias!F58 -> 1.5 | D2: =B2*C2 -> 3
A3: =Referencias!B53 -> Papel fotografico A4 | B3: 2 | C3: =Referencias!F53 -> 0.8 | D3: =B3*C3 -> 1.6
A4: =Referencias!B31 -> bopp | B4: =0.3*2 -> 0.6 | C4: =Referencias!F31 -> 0.45 | D4: =B4*C4 -> 0.27
A5: =Referencias!B48 -> Papel guarda 15,5x21,5 offset adesivo | B5: 2 | C5: =Referencias!F48 -> 0.75 | D5: =B5*C5 -> 1.5
A6: =Referencias!B40 -> miolo 75gr A5 | B6: 204 | C6: =Referencias!F40 -> 0.03 | D6: =B6*C6 -> 6.12
A7: =Referencias!B34 -> Bolso offset 180gr | B7: 1 | C7: =Referencias!F34 -> 0.32 | D7: =B7*C7 -> 0.32
A8: =Referencias!B120 -> Espiral 33mm plastico | B8: 1 | C8: =Referencias!F120 -> 2.48 | D8: =B8*C8 -> 2.48
A9: =Referencias!B22 -> Impressao Capa A4 | B9: 2 | C9: =Referencias!F22 -> 0.5 | D9: =B9*C9 -> 1
A10: =Referencias!B29 -> Impressao Miolo Frente Verso A5 | B10: 204 | C10: =Referencias!F29 -> 0.06 | D10: =B10*C10 -> 12.24
A11: =Referencias!B21 -> Impressao Bolso A4 | B11: 1 | C11: =Referencias!F21 -> 1 | D11: =B11*C11 -> 1
A12: =Referencias!B62 -> Frete | C12: =Referencias!F62 -> 0 | D12: =B12*C12 -> 0
A13: =Referencias!B13 -> Desgaste Agenda | B13: 1 | C13: =Referencias!F13 -> 1 | D13: =B13*C13 -> 1
A14: =Referencias!B17 -> Embalagem Padrão | B14: 1 | C14: =Referencias!F17 -> 1.5 | D14: =B14*C14 -> 1.5
A15: Custo | D15: =SUM(D2:D14) -> 32.03
A16: Margem | B16: 0.55 | C16: =D15*B16 -> 17.6165 | D16: =D15+C16 -> 49.6465
A17: Pesquisa | B17: praper | C17: mp
A18: Valor | B18: 69 | C18: 75 | D18: 89.9
A20: Agenda 2 dias datada | D20: 55.9
A21: =Referencias!B57 -> Papelão 15x18,5 | B21: 2 | C21: =Referencias!F57 -> 1.5 | D21: =B21*C21 -> 3
A22: =Referencias!B53 -> Papel fotografico A4 | B22: 2 | C22: =Referencias!F53 -> 0.8 | D22: =B22*C22 -> 1.6
A23: =Referencias!B31 -> bopp | B23: =0.3*2 -> 0.6 | C23: =Referencias!F31 -> 0.45 | D23: =B23*C23 -> 0.27
A24: =Referencias!B47 -> Papel guarda 14,5x18 offset adesivo | B24: 2 | C24: =Referencias!F47 -> 0.75 | D24: =B24*C24 -> 1.5
A25: =Referencias!B46 -> miolo 90gr A5 14x18 | B25: 114 | C25: =Referencias!F46 -> 0.05 | D25: =B25*C25 -> 5.7
A26: =Referencias!B34 -> Bolso offset 180gr | B26: 1 | C26: =Referencias!F34 -> 0.32 | D26: =B26*C26 -> 0.32
A27: =Referencias!B19 -> Espiral 29mm | B27: 1 | C27: =Referencias!F19 -> 1.83 | D27: =B27*C27 -> 1.83
A28: =Referencias!B22 -> Impressao Capa A4 | B28: 2 | C28: =Referencias!F22 -> 0.5 | D28: =B28*C28 -> 1
A29: =Referencias!B29 -> Impressao Miolo Frente Verso A5 | B29: 114 | C29: =Referencias!F29 -> 0.06 | D29: =B29*C29 -> 6.84
A30: =Referencias!B21 -> Impressao Bolso A4 | B30: 1 | C30: =Referencias!F21 -> 1 | D30: =B30*C30 -> 1
A31: =Referencias!B62 -> Frete | C31: =Referencias!F62 -> 0 | D31: =B31*C31 -> 0
A32: =Referencias!B13 -> Desgaste Agenda | B32: 1 | C32: =Referencias!F13 -> 1 | D32: =B32*C32 -> 1
A33: =Referencias!B17 -> Embalagem Padrão | B33: 1 | C33: =Referencias!F17 -> 1.5 | D33: =B33*C33 -> 1.5
A34: Custo | D34: =SUM(D21:D33) -> 25.56
A35: Margem | B35: 0.55 | C35: =D34*B35 -> 14.058 | D35: =D34+C35 -> 39.618
A36: Pesquisa | B36: praper | C36: mp
A37: Valor | B37: 54.9 | C37: 59 | D37: 65.9
A39: Agenda Agendamento | D39: 85.9
A40: =Referencias!B58 -> Papelão 16x22 | B40: 2 | C40: =Referencias!F58 -> 1.5 | D40: =B40*C40 -> 3
A41: =Referencias!B53 -> Papel fotografico A4 | B41: 2 | C41: =Referencias!F53 -> 0.8 | D41: =B41*C41 -> 1.6
A42: =Referencias!B31 -> bopp | B42: =0.3*2 -> 0.6 | C42: =Referencias!F31 -> 0.45 | D42: =B42*C42 -> 0.27
A43: =Referencias!B48 -> Papel guarda 15,5x21,5 offset adesivo | B43: 2 | C43: =Referencias!F48 -> 0.75 | D43: =B43*C43 -> 1.5
A44: =Referencias!B40 -> miolo 75gr A5 | B44: 209 | C44: =Referencias!F40 -> 0.03 | D44: =B44*C44 -> 6.27
A45: =Referencias!B34 -> Bolso offset 180gr | B45: 1 | C45: =Referencias!F34 -> 0.32 | D45: =B45*C45 -> 0.32
A46: =Referencias!B120 -> Espiral 33mm plastico | B46: 1 | C46: =Referencias!F120 -> 2.48 | D46: =B46*C46 -> 2.48
A47: =Referencias!B22 -> Impressao Capa A4 | B47: 2 | C47: =Referencias!F22 -> 0.5 | D47: =B47*C47 -> 1
A48: =Referencias!B29 -> Impressao Miolo Frente Verso A5 | B48: 209 | C48: =Referencias!F29 -> 0.06 | D48: =B48*C48 -> 12.54
A49: =Referencias!B21 -> Impressao Bolso A4 | B49: 1 | C49: =Referencias!F21 -> 1 | D49: =B49*C49 -> 1
A50: =Referencias!B62 -> Frete | C50: =Referencias!F62 -> 0 | D50: =B50*C50 -> 0
A51: =Referencias!B13 -> Desgaste Agenda | B51: 1 | C51: =Referencias!F13 -> 1 | D51: =B51*C51 -> 1
A52: =Referencias!B17 -> Embalagem Padrão | B52: 1 | C52: =Referencias!F17 -> 1.5 | D52: =B52*C52 -> 1.5
A53: Custo | D53: =SUM(D40:D52) -> 32.48
A54: Margem | B54: 0.55 | C54: =D53*B54 -> 17.864 | D54: =D53+C54 -> 50.344
A55: Pesquisa | B55: praper
A56: Valor | B56: 84.9 | D56: 85.9
A58: Calendario A5 | D58: 25
A59: =Referencias!B56 -> Papelão 15,5x21,5+2,5x21,5 | B59: 2 | C59: =Referencias!F56 -> 1.5 | D59: =B59*C59 -> 3
A60: =Referencias!B52 -> Papel offset adesivo A4 | B60: 2 | C60: =Referencias!F52 -> 0.75 | D60: =B60*C60 -> 1.5
A61: =Referencias!B31 -> bopp | B61: =0.3*2 -> 0.6 | C61: =Referencias!F31 -> 0.45 | D61: =B61*C61 -> 0.27
A62: =Referencias!B50 -> Papel guarda 20x20 offset adesivo | B62: 2 | C62: =Referencias!F50 -> 0.75 | D62: =B62*C62 -> 1.5
A63: =Referencias!B36 -> miolo 180g A5 | B63: 12 | C63: =Referencias!F36 -> 0.16 | D63: =B63*C63 -> 1.92
A64: =Referencias!B18 -> Espiral 17mm | B64: 1 | C64: =Referencias!F18 -> 0.52 | D64: =B64*C64 -> 0.52
A65: =Referencias!B22 -> Impressao Capa A4 | B65: 2 | C65: =Referencias!F22 -> 0.5 | D65: =B65*C65 -> 1
A66: =Referencias!B29 -> Impressao Miolo Frente Verso A5 | B66: 12 | C66: =Referencias!F29 -> 0.06 | D66: =B66*C66 -> 0.72
A67: =Referencias!B62 -> Frete | C67: =Referencias!F62 -> 0 | D67: =B67*C67 -> 0
A68: =Referencias!B14 -> Desgaste Bloquinho/Outros | B68: 1 | C68: =Referencias!F14 -> 0.5 | D68: =B68*C68 -> 0.5
A69: =Referencias!B17 -> Embalagem Padrão | B69: 1 | C69: =Referencias!F17 -> 1.5 | D69: =B69*C69 -> 1.5
A70: Custo | D70: =SUM(D59:D69) -> 12.43
A71: Margem | B71: 0.55 | C71: =D70*B71 -> 6.8365 | D71: =D70+C71 -> 19.2665
A72: Pesquisa | B72: praper
A73: Valor | B73: 24.9 | D73: 25
A75: Calendario 10x10 | D75: 15
A76: =Referencias!B61 -> Papelão 9,5x10,5+9,5x2 | B76: 1 | C76: =Referencias!F61 -> 1.5 | D76: =B76*C76 -> 1.5
A77: =Referencias!B51 -> Papel offset adesivo + guarda | B77: 1 | C77: =Referencias!F51 -> 0.75 | D77: =B77*C77 -> 0.75
A78: =Referencias!B31 -> bopp | B78: =0.3 -> 0.3 | C78: =Referencias!F31 -> 0.45 | D78: =B78*C78 -> 0.135
A79: =Referencias!B37 -> miolo 180gr A4 | B79: 3 | C79: =Referencias!F37 -> 0.32 | D79: =B79*C79 -> 0.96
A80: =Referencias!B18 -> Espiral 17mm | B80: 0.34 | C80: =Referencias!F18 -> 0.52 | D80: =B80*C80 -> 0.1768
A81: =Referencias!B22 -> Impressao Capa A4 | B81: 1 | C81: =Referencias!F22 -> 0.5 | D81: =B81*C81 -> 0.5
A82: =Referencias!B63 -> Impressao Miolo Frente A4 | B82: 3 | C82: =Referencias!F63 -> 0.06 | D82: =B82*C82 -> 0.18
A83: =Referencias!B62 -> Frete | C83: =Referencias!F62 -> 0 | D83: =B83*C83 -> 0
A84: =Referencias!B14 -> Desgaste Bloquinho/Outros | B84: 1 | C84: =Referencias!F14 -> 0.5 | D84: =B84*C84 -> 0.5
A85: =Referencias!B17 -> Embalagem Padrão | B85: 1 | C85: =Referencias!F17 -> 1.5 | D85: =B85*C85 -> 1.5
A86: Custo | D86: =SUM(D76:D85) -> 6.2018
A87: Margem | B87: 0.55 | C87: =D86*B87 -> 3.41099 | D87: =D86+C87 -> 9.61279
A88: Pesquisa | B88: praper | C88: mp
A89: Valor | B89: 18.9 | C89: 11.9 | D89: 15
A91: Planner Kraft A5 Bordado | D91: 30
A92: =Referencias!B54 -> Papel Kraft A4 | B92: 1 | C92: =Referencias!F54 -> 0.54 | D92: =B92*C92 -> 0.54
A93: =Referencias!B41 -> Sulfite 75g A4 | B93: 27 | C93: =Referencias!F41 -> 0.06 | D93: =B93*C93 -> 1.62
A94: =Referencias!B5 -> Cordão Encerado Settanyl | B94: 1.2 | C94: =Referencias!F5 -> 0.16 | D94: =B94*C94 -> 0.192
A95: =Referencias!B88 -> Linha Circulo Maxi Mouline | B95: 4 | C95: =Referencias!F88 -> 0.18 | D95: =B95*C95 -> 0.72
A96: =Referencias!B28 -> Impressao Miolo Frente Verso A4 | B96: 27 | C96: =Referencias!F28 -> 0.12 | D96: =B96*C96 -> 3.24
A97: =Referencias!B62 -> Frete | C97: =Referencias!F62 -> 0 | D97: =B97*C97 -> 0
A98: =Referencias!B14 -> Desgaste Bloquinho/Outros | B98: 1 | C98: =Referencias!F14 -> 0.5 | D98: =B98*C98 -> 0.5
A99: =Referencias!B17 -> Embalagem Padrão | B99: 1 | C99: =Referencias!F17 -> 1.5 | D99: =B99*C99 -> 1.5
A100: Custo | D100: =SUM(D92:D99) -> 8.312
A101: Margem | B101: 0.55 | C101: =D100*B101 -> 4.5716 | D101: =D100+C101 -> 12.8836
A102: Pesquisa
A103: Valor | D103: 30
A105: Planner anual | D105: 119.9
A106: =Referencias!B59 -> Papelão 17x22 | B106: 2 | C106: =Referencias!F59 -> 1.5 | D106: =B106*C106 -> 3
...

Sheet Pais23
A1: Marcador de Páginas Kraft bordado | D1: 5
A2: =Referencias!B146 -> Papel Kraft 20x5 | B2: 1 | C2: =Referencias!F146 -> 0.09 | D2: =B2*C2 -> 0.09
A3: =Referencias!B88 -> Linha Circulo Maxi Mouline | B3: 2 | C3: =Referencias!F88 -> 0.18 | D3: =B3*C3 -> 0.36
A4: =Referencias!B62 -> Frete | C4: =Referencias!F62 -> 0 | D4: =B4*C4 -> 0
A5: =Referencias!B14 -> Desgaste Bloquinho/Outros | B5: 1 | C5: =Referencias!F14 -> 0.5 | D5: =B5*C5 -> 0.5
A6: =Referencias!B17 -> Embalagem Padrão | B6: 1 | C6: =Referencias!F17 -> 1.5 | D6: =B6*C6 -> 1.5
A7: Custo | D7: =SUM(D2:D6) -> 2.45
A8: Margem | B8: 0.55 | C8: =D7*B8 -> 1.3475 | D8: =D7+C8 -> 3.7975
A9: Pesquisa
A10: Valor | D10: 5
A12: Caixa Dia dos Pais | D12: 10
A13: =Referencias!B84 -> Papel 180gr A4 | B13: 3 | C13: =Referencias!F84 -> 0.32 | D13: =B13*C13 -> 0.96
A14: =Referencias!B83 -> Impressão A4 | B14: 3 | C14: =Referencias!F83 -> 0.5 | D14: =B14*C14 -> 1.5
A15: =Referencias!B62 -> Frete | B15: 0 | C15: =Referencias!F62 -> 0 | D15: =B15*C15 -> 0
A16: =Referencias!B14 -> Desgaste Bloquinho/Outros | B16: 1 | C16: =Referencias!F14 -> 0.5 | D16: =B16*C16 -> 0.5
A17: =Referencias!B17 -> Embalagem Padrão | B17: 1 | C17: =Referencias!F17 -> 1.5 | D17: =B17*C17 -> 1.5
A18: Custo | D18: =SUM(D13:D17) -> 4.46
A19: Margem | B19: 0.55 | C19: =D18*B19 -> 2.453 | D19: =D18+C19 -> 6.913
A20: Pesquisa
A21: Valor | D21: 10
A23: Caixa Ferramentas | D23: 5
A24: =Referencias!B84 -> Papel 180gr A4 | B24: 1 | C24: =Referencias!F84 -> 0.32 | D24: =B24*C24 -> 0.32
A25: =Referencias!B83 -> Impressão A4 | B25: 1 | C25: =Referencias!F83 -> 0.5 | D25: =B25*C25 -> 0.5
A26: =Referencias!B62 -> Frete | B26: 0 | C26: =Referencias!F62 -> 0 | D26: =B26*C26 -> 0
A27: =Referencias!B14 -> Desgaste Bloquinho/Outros | B27: 1 | C27: =Referencias!F14 -> 0.5 | D27: =B27*C27 -> 0.5
A28: =Referencias!B17 -> Embalagem Padrão | B28: 1 | C28: =Referencias!F17 -> 1.5 | D28: =B28*C28 -> 1.5
A29: Custo | D29: =SUM(D24:D28) -> 2.82
A30: Margem | B30: 0.55 | C30: =D29*B30 -> 1.551 | D30: =D29+C30 -> 4.371
A31: Pesquisa
A32: Valor | D32: 5
A34: Cesta Café | D34: 40
A35: =#REF! -> #REF! | B35: 1 | C35: =#REF! -> #REF! | D35: =B35*C35 -> #REF!
A36: =A12 -> Caixa Dia dos Pais | B36: 1 | C36: =D18 -> 4.46 | D36: =B36*C36 -> 4.46
A37: =Referencias!B133 -> Kit Bolachas (1 Torrada, 1 Maisena, 1 Creem Cracker, 1 Chocolate, 1 Leite, 1 Gotas, 1 Banana com Canela) | B37: 1 | C37: =Referencias!F133 -> 4.41 | D37: =B37*C37 -> 4.41
A38: =Referencias!B134 -> Suco Caixinha Chefa 200ml | B38: 1 | C38: =Referencias!F134 -> 1.19 | D38: =B38*C38 -> 1.19
A39: =Referencias!B135 -> Açucar União Sache 5g | B39: 2 | C39: =Referencias!F135 -> 0.32 | D39: =B39*C39 -> 0.64
A40: =Referencias!B136 -> Café Pelé Sache | B40: 1 | C40: =Referencias!F136 -> 0.43 | D40: =B40*C40 -> 0.43
A41: =Referencias!B137 -> Capuccino 3 Corações Sache | B41: 1 | C41: =Referencias!F137 -> 1.99 | D41: =B41*C41 -> 1.99
A42: =Referencias!B138 -> Geleia Blister 15g | B42: 2 | C42: =Referencias!F138 -> 0.66 | D42: =B42*C42 -> 1.32
A43: =Referencias!B62 -> Frete | B43: 0 | C43: =Referencias!F62 -> 0 | D43: =B43*C43 -> 0
A44: =Referencias!B14 -> Desgaste Bloquinho/Outros | B44: 1 | C44: =Referencias!F14 -> 0.5 | D44: =B44*C44 -> 0.5
A45: =Referencias!B17 -> Embalagem Padrão | B45: 1 | C45: =Referencias!F17 -> 1.5 | D45: =B45*C45 -> 1.5
A46: Custo | D46: =SUM(D35:D45) -> #REF!
A47: Margem | B47: 0.55 | C47: =D46*B47 -> #REF! | D47: =D46+C47 -> #REF!
A48: Pesquisa
A49: Valor | D49: 40
A51: Caixa Geleia | D51: 40
A52: =A23 -> Caixa Ferramentas | B52: 1 | C52: =D29 -> 2.82 | D52: =B52*C52 -> 2.82
A53: Pote de Geleia Caseira | B53: 1 | C53: 11 | D53: =B53*C53 -> 11
A54: =Referencias!B62 -> Frete | B54: 0 | C54: =Referencias!F62 -> 0 | D54: =B54*C54 -> 0
A55: =Referencias!B14 -> Desgaste Bloquinho/Outros | B55: 1 | C55: =Referencias!F14 -> 0.5 | D55: =B55*C55 -> 0.5
A56: =Referencias!B17 -> Embalagem Padrão | B56: 1 | C56: =Referencias!F17 -> 1.5 | D56: =B56*C56 -> 1.5
A57: Custo | D57: =SUM(D52:D56) -> 15.82
A58: Margem | B58: 0.55 | C58: =D57*B58 -> 8.701 | D58: =D57+C58 -> 24.521
A59: Pesquisa
A60: Valor | D60: 40

Sheet Namorados23
A1: Cartão Kraft A6 bordado | D1: 5
A2: =Referencias!B55 -> Papel Kraft A5 | B2: 1 | C2: =Referencias!F55 -> 0.27 | D2: =B2*C2 -> 0.27
A3: =Referencias!B142 -> Papel Offset Sulfite 120g A6 | B3: 1 | C3: =Referencias!F142 -> 0.03 | D3: =B3*C3 -> 0.03
A4: =Referencias!B139 -> Envelope 80g visita 115x80 linho branco 5452 Romitec | B4: 1 | C4: =Referencias!F139 -> 0.27 | D4: =B4*C4 -> 0.27
A5: =Referencias!B88 -> Linha Circulo Maxi Mouline | B5: 2 | C5: =Referencias!F88 -> 0.18 | D5: =B5*C5 -> 0.36
A6: =Referencias!B62 -> Frete | C6: =Referencias!F62 -> 0 | D6: =B6*C6 -> 0
A7: =Referencias!B14 -> Desgaste Bloquinho/Outros | B7: 1 | C7: =Referencias!F14 -> 0.5 | D7: =B7*C7 -> 0.5
A8: =Referencias!B17 -> Embalagem Padrão | B8: 1 | C8: =Referencias!F17 -> 1.5 | D8: =B8*C8 -> 1.5
A9: Custo | D9: =SUM(D2:D8) -> 2.93
A10: Margem | B10: 0.55 | C10: =D9*B10 -> 1.6115 | D10: =D9+C10 -> 4.5415
A11: Pesquisa
A12: Valor | D12: 5
A14: Livro do Casal | D14: 30
A15: =Referencias!B58 -> Papelão 16x22 | B15: 2 | C15: =Referencias!F58 -> 1.5 | D15: =B15*C15 -> 3
A16: =Referencias!B53 -> Papel fotografico A4 | B16: 2 | C16: =Referencias!F53 -> 0.8 | D16: =B16*C16 -> 1.6
A17: =Referencias!B31 -> bopp | B17: =2*0.3 -> 0.6 | C17: =Referencias!F31 -> 0.45 | D17: =B17*C17 -> 0.27
A18: =Referencias!B48 -> Papel guarda 15,5x21,5 offset adesivo | B18: 2 | C18: =Referencias!F48 -> 0.75 | D18: =B18*C18 -> 1.5
A19: =Referencias!B36 -> miolo 180g A5 | B19: 13 | C19: =Referencias!F36 -> 0.16 | D19: =B19*C19 -> 2.08
A20: =Referencias!B18 -> Espiral 17mm | B20: 1 | C20: =Referencias!F18 -> 0.52 | D20: =B20*C20 -> 0.52
A21: =Referencias!B22 -> Impressao Capa A4 | B21: 2 | C21: =Referencias!F22 -> 0.5 | D21: =B21*C21 -> 1
A22: =Referencias!B29 -> Impressao Miolo Frente Verso A5 | B22: 13 | C22: =Referencias!F29 -> 0.06 | D22: =B22*C22 -> 0.78
A23: =Referencias!B62 -> Frete | C23: =Referencias!F62 -> 0 | D23: =B23*C23 -> 0
A24: =Referencias!B15 -> Desgaste Caderno A5 | B24: 1 | C24: =Referencias!F15 -> 2 | D24: =B24*C24 -> 2
A25: =Referencias!B17 -> Embalagem Padrão | B25: 1 | C25: =Referencias!F17 -> 1.5 | D25: =B25*C25 -> 1.5
A26: Custo | D26: =SUM(D15:D25) -> 14.25
A27: Margem | B27: 0.55 | C27: =D26*B27 -> 7.8375 | D27: =D26+C27 -> 22.0875
A28: Pesquisa | B28: praper | C28: mp
A29: Valor | D29: 30

Sheet Mães23
A1: Caderno gratidão | D1: 20
A2: =Referencias!B123 -> Papelão 15,5x11,5 | B2: 2 | C2: =Referencias!F123 -> 0.75 | D2: =B2*C2 -> 1.5
A3: =Referencias!B53 -> Papel fotografico A4 | B3: 1 | C3: =Referencias!F53 -> 0.8 | D3: =B3*C3 -> 0.8
A4: =Referencias!B31 -> bopp | B4: =0.3*2 -> 0.6 | C4: =Referencias!F31 -> 0.45 | D4: =B4*C4 -> 0.27
A5: =Referencias!B124 -> Papel guarda 11x15 offset adesivo | B5: 2 | C5: =Referencias!F124 -> 0.35 | D5: =B5*C5 -> 0.7
A6: =Referencias!B122 -> miolo 75gr A6 | B6: 81 | C6: =Referencias!F122 -> 0.016 | D6: =B6*C6 -> 1.296
A7: =Referencias!B69 -> Espiral 20mm | B7: 0.5 | C7: =Referencias!F69 -> 0.64 | D7: =B7*C7 -> 0.32
A8: =Referencias!B24 -> Impressao Capa A6 | B8: 2 | C8: =Referencias!F24 -> 0.13 | D8: =B8*C8 -> 0.26
A9: =Referencias!B27 -> Impressao Miolo Frente A6 | B9: 81 | C9: =Referencias!F27 -> 0.02 | D9: =B9*C9 -> 1.62
A10: =Referencias!B62 -> Frete | C10: =Referencias!F62 -> 0 | D10: =B10*C10 -> 0
A11: =Referencias!B15 -> Desgaste Caderno A5 | B11: 1 | C11: =Referencias!F15 -> 2 | D11: =B11*C11 -> 2
A12: =Referencias!B17 -> Embalagem Padrão | B12: 1 | C12: =Referencias!F17 -> 1.5 | D12: =B12*C12 -> 1.5
A13: Custo | D13: =SUM(D2:D12) -> 10.266
A14: Margem | B14: 0.55 | C14: =D13*B14 -> 5.6463 | D14: =D13+C14 -> 15.9123
A15: Pesquisa | B15: praper | C15: mp
A16: Valor | D16: 20
A18: Diário | D18: 35
A19: =Referencias!B58 -> Papelão 16x22 | B19: 2 | C19: =Referencias!F58 -> 1.5 | D19: =B19*C19 -> 3
A20: =Referencias!B53 -> Papel fotografico A4 | B20: 2 | C20: =Referencias!F53 -> 0.8 | D20: =B20*C20 -> 1.6
A21: =Referencias!B31 -> bopp | B21: =2*0.3 -> 0.6 | C21: =Referencias!F31 -> 0.45 | D21: =B21*C21 -> 0.27
A22: =Referencias!B48 -> Papel guarda 15,5x21,5 offset adesivo | B22: 2 | C22: =Referencias!F48 -> 0.75 | D22: =B22*C22 -> 1.5
A23: =Referencias!B45 -> miolo 90gr A5 | B23: 80 | C23: =Referencias!F45 -> 0.05 | D23: =B23*C23 -> 4
A24: =Referencias!B69 -> Espiral 20mm | B24: 1 | C24: =Referencias!F69 -> 0.64 | D24: =B24*C24 -> 0.64
A25: =Referencias!B22 -> Impressao Capa A4 | B25: 2 | C25: =Referencias!F22 -> 0.5 | D25: =B25*C25 -> 1
A26: =Referencias!B29 -> Impressao Miolo Frente Verso A5 | B26: 80 | C26: =Referencias!F29 -> 0.06 | D26: =B26*C26 -> 4.8
A27: =Referencias!B62 -> Frete | C27: =Referencias!F62 -> 0 | D27: =B27*C27 -> 0
A28: =Referencias!B15 -> Desgaste Caderno A5 | B28: 1 | C28: =Referencias!F15 -> 2 | D28: =B28*C28 -> 2
A29: =Referencias!B17 -> Embalagem Padrão | B29: 1 | C29: =Referencias!F17 -> 1.5 | D29: =B29*C29 -> 1.5
A30: Custo | D30: =SUM(D19:D29) -> 20.31
A31: Margem | B31: 0.55 | C31: =D30*B31 -> 11.1705 | D31: =D30+C31 -> 31.4805
A32: Pesquisa | B32: praper | C32: mp
A33: Valor | D33: 35
A35: Kit beleza | D35: 40
A36: =Mulher23!A21 -> Ecopad c/3 M | B36: 1 | C36: =Mulher23!D22 -> 0.9 | D36: =B36*C36 -> 0.9
A37: =Mulher23!A51 -> Esponja Massageadora em Crochê | B37: 1 | C37: =Mulher23!D52 -> 2.88 | D37: =B37*C37 -> 2.88
A38: =A117 -> Cesta em Tecido | B38: 1 | C38: =D127 -> 9.7608 | D38: =B38*C38 -> 9.7608
A39: =Referencias!B127 -> Sabonete Natura com 5 | B39: 1 | C39: =Referencias!F127 -> 5.58 | D39: =B39*C39 -> 5.58
A40: =Referencias!B101 -> Máscara Facial de Limpeza | B40: 2 | C40: =Referencias!F101 -> 1.02 | D40: =B40*C40 -> 2.04
A41: =Referencias!B62 -> Frete | C41: =Referencias!F62 -> 0 | D41: =B41*C41 -> 0
A42: =Referencias!B14 -> Desgaste Bloquinho/Outros | B42: 1 | C42: =Referencias!F14 -> 0.5 | D42: =B42*C42 -> 0.5
A43: =Referencias!B17 -> Embalagem Padrão | B43: 1 | C43: =Referencias!F17 -> 1.5 | D43: =B43*C43 -> 1.5
A44: Custo | D44: =SUM(D36:D43) -> 23.1608
A45: Margem | B45: 0.55 | C45: =D44*B45 -> 12.73844 | D45: =D44+C45 -> 35.89924
A46: Pesquisa
A47: Valor | D47: 40
A49: Kit com 5 Ecopads e mascara facial | D49: 15
A50: =Mulher23!A1 -> Ecopad c/5 P | B50: 1 | C50: =Mulher23!D2 -> 0.9 | D50: =B50*C50 -> 0.9
A51: =Referencias!B101 -> Máscara Facial de Limpeza | B51: 2 | C51: =Referencias!F101 -> 1.02 | D51: =B51*C51 -> 2.04
A52: =Mulher23!A41 -> Bolsa para Ecopad em Croche | B52: 1 | C52: =Mulher23!D42 -> 1.2 | D52: =B52*C52 -> 1.2
A53: =Referencias!B62 -> Frete | C53: =Referencias!F62 -> 0 | D53: =B53*C53 -> 0
A54: =Referencias!B14 -> Desgaste Bloquinho/Outros | B54: 1 | C54: =Referencias!F14 -> 0.5 | D54: =B54*C54 -> 0.5
A55: =Referencias!B17 -> Embalagem Padrão | B55: 1 | C55: =Referencias!F17 -> 1.5 | D55: =B55*C55 -> 1.5
A56: Custo | D56: =SUM(D50:D55) -> 6.14
A57: Margem | B57: 0.55 | C57: =D56*B57 -> 3.377 | D57: =D56+C57 -> 9.517
A58: Pesquisa | B58: praper
A59: Valor | B59: 84.9 | D59: 15
A61: Caderno receitas | D61: 30
A62: =Referencias!B58 -> Papelão 16x22 | B62: 2 | C62: =Referencias!F58 -> 1.5 | D62: =B62*C62 -> 3
A63: =Referencias!B53 -> Papel fotografico A4 | B63: 2 | C63: =Referencias!F53 -> 0.8 | D63: =B63*C63 -> 1.6
A64: =Referencias!B31 -> bopp | B64: =0.3*2 -> 0.6 | C64: =Referencias!F31 -> 0.45 | D64: =B64*C64 -> 0.27
A65: =Referencias!B48 -> Papel guarda 15,5x21,5 offset adesivo | B65: 2 | C65: =Referencias!F48 -> 0.75 | D65: =B65*C65 -> 1.5
A66: =Referencias!B45 -> miolo 90gr A5 | B66: 51 | C66: =Referencias!F45 -> 0.05 | D66: =B66*C66 -> 2.55
A67: =Referencias!B69 -> Espiral 20mm | B67: 1 | C67: =Referencias!F69 -> 0.64 | D67: =B67*C67 -> 0.64
A68: =Referencias!B22 -> Impressao Capa A4 | B68: 2 | C68: =Referencias!F22 -> 0.5 | D68: =B68*C68 -> 1
A69: =Referencias!B29 -> Impressao Miolo Frente Verso A5 | B69: 51 | C69: =Referencias!F29 -> 0.06 | D69: =B69*C69 -> 3.06
A70: =Referencias!B62 -> Frete | B70: 0 | C70: =Referencias!F62 -> 0 | D70: =B70*C70 -> 0
A71: =Referencias!B15 -> Desgaste Caderno A5 | B71: 1 | C71: =Referencias!F15 -> 2 | D71: =B71*C71 -> 2
A72: =Referencias!B17 -> Embalagem Padrão | B72: 1 | C72: =Referencias!F17 -> 1.5 | D72: =B72*C72 -> 1.5
A73: Custo | D73: =SUM(D62:D72) -> 17.12
A74: Margem | B74: 0.55 | C74: =D73*B74 -> 9.416 | D74: =D73+C74 -> 26.536
A75: Pesquisa | B75: praper | C75: mp
A76: Valor | D76: 30
A78: Colar pingente caderno | D78: 15
A79: =Referencias!B128 -> Couro 7,5 cm x 3 cm | B79: 2 | C79: =Referencias!F128 -> 0.02 | D79: =B79*C79 -> 0.04
A80: =Referencias!B129 -> miolo 75gr 3cm x 5 cm | B80: 10 | C80: =Referencias!F129 -> 0.01 | D80: =B80*C80 -> 0.1
A81: =Referencias!B5 -> Cordão Encerado Settanyl | B81: 0.2 | C81: =Referencias!F5 -> 0.16 | D81: =B81*C81 -> 0.032
A82: =Referencias!B132 -> Argola para Chaveiro | B82: 1 | C82: =Referencias!F132 -> 0.1 | D82: =B82*C82 -> 0.1
A83: =Referencias!B130 -> Cordão cetim | B83: 0.9 | C83: =Referencias!F130 -> 0.21 | D83: =B83*C83 -> 0.189
A84: =Referencias!B131 -> Tira couro fechamento | B84: 0.5 | C84: =Referencias!F131 -> 0.02 | D84: =B84*C84 -> 0.01
A85: =Referencias!B62 -> Frete | C85: =Referencias!F62 -> 0 | D85: =B85*C85 -> 0
A86: =Referencias!B15 -> Desgaste Caderno A5 | B86: 1 | C86: =Referencias!F15 -> 2 | D86: =B86*C86 -> 2
A87: =Referencias!B17 -> Embalagem Padrão | B87: 1 | C87: =Referencias!F17 -> 1.5 | D87: =B87*C87 -> 1.5
A88: Custo | D88: =SUM(D79:D87) -> 3.971
A89: Margem | B89: 0.55 | C89: =D88*B89 -> 2.18405 | D89: =D88+C89 -> 6.15505
A90: Pesquisa
A91: Valor | D91: 15
A93: Sacolinha P | D93: 6
A94: =Referencias!B84 -> Papel 180gr A4 | B94: 2 | C94: =Referencias!F84 -> 0.32 | D94: =B94*C94 -> 0.64
A95: =Referencias!B85 -> Alça - Fio Nautico circulo branco | B95: 0.52 | C95: =Referencias!F85 -> 0.14 | D95: =B95*C95 -> 0.0728
A96: =Referencias!B83 -> Impressão A4 | B96: 2 | C96: =Referencias!F83 -> 0.5 | D96: =B96*C96 -> 1
A97: =Referencias!B62 -> Frete | C97: =Referencias!F62 -> 0 | D97: =B97*C97 -> 0
A98: =Referencias!B14 -> Desgaste Bloquinho/Outros | B98: 1 | C98: =Referencias!F14 -> 0.5 | D98: =B98*C98 -> 0.5
A99: =Referencias!B17 -> Embalagem Padrão | B99: 1 | C99: =Referencias!F17 -> 1.5 | D99: =B99*C99 -> 1.5
A100: Custo | D100: =SUM(D94:D99) -> 3.7128
A101: Margem | B101: 0.55 | C101: =D100*B101 -> 2.04204 | D101: =D100+C101 -> 5.75484
A102: Pesquisa
A103: Valor | D103: 6
A105: Sacolinha G | D105: 7.5
A106: =Referencias!B84 -> Papel 180gr A4 | B106: 3 | C106: =Referencias!F84 -> 0.32 | D106: =B106*C106 -> 0.96
A107: =Referencias!B85 -> Alça - Fio Nautico circulo branco | B107: 0.64 | C107: =Referencias!F85 -> 0.14 | D107: =B107*C107 -> 0.0896
...

Sheet Pascoa23
A1: Agenda 1 dia Alice | D1: 69
A2: =Referencias!B58 -> Papelão 16x22 | B2: 2 | C2: =Referencias!F58 -> 1.5 | D2: =B2*C2 -> 3
A3: =Referencias!B53 -> Papel fotografico A4 | B3: 2 | C3: =Referencias!F53 -> 0.8 | D3: =B3*C3 -> 1.6
A4: =Referencias!B31 -> bopp | B4: =0.3*2 -> 0.6 | C4: =Referencias!F31 -> 0.45 | D4: =B4*C4 -> 0.27
A5: =Referencias!B48 -> Papel guarda 15,5x21,5 offset adesivo | B5: 2 | C5: =Referencias!F48 -> 0.75 | D5: =B5*C5 -> 1.5
A6: =Referencias!B40 -> miolo 75gr A5 | B6: 198 | C6: =Referencias!F40 -> 0.03 | D6: =B6*C6 -> 5.94
A7: =Referencias!B34 -> Bolso offset 180gr | B7: 1 | C7: =Referencias!F34 -> 0.32 | D7: =B7*C7 -> 0.32
A8: =Referencias!B120 -> Espiral 33mm plastico | B8: 1 | C8: =Referencias!F120 -> 2.48 | D8: =B8*C8 -> 2.48
A9: =Referencias!B22 -> Impressao Capa A4 | B9: 2 | C9: =Referencias!F22 -> 0.5 | D9: =B9*C9 -> 1
A10: =Referencias!B29 -> Impressao Miolo Frente Verso A5 | B10: 205 | C10: =Referencias!F29 -> 0.06 | D10: =B10*C10 -> 12.3
A11: =Referencias!B21 -> Impressao Bolso A4 | B11: 1 | C11: =Referencias!F21 -> 1 | D11: =B11*C11 -> 1
A12: =Referencias!B62 -> Frete | C12: =Referencias!F62 -> 0 | D12: =B12*C12 -> 0
A13: =Referencias!B13 -> Desgaste Agenda | B13: 1 | C13: =Referencias!F13 -> 1 | D13: =B13*C13 -> 1
A14: =Referencias!B17 -> Embalagem Padrão | B14: 1 | C14: =Referencias!F17 -> 1.5 | D14: =B14*C14 -> 1.5
A15: Custo | D15: =SUM(D2:D14) -> 31.91
A16: Margem | B16: 0.55 | C16: =D15*B16 -> 17.5505 | D16: =D15+C16 -> 49.4605
A17: Pesquisa | B17: praper | C17: mp
A18: Valor | B18: 69 | C18: 69 | D18: 69
A20: Agenda 2 dias Alice | D20: 49
A21: =Referencias!B58 -> Papelão 16x22 | B21: 2 | C21: =Referencias!F58 -> 1.5 | D21: =B21*C21 -> 3
A22: =Referencias!B53 -> Papel fotografico A4 | B22: 2 | C22: =Referencias!F53 -> 0.8 | D22: =B22*C22 -> 1.6
A23: =Referencias!B31 -> bopp | B23: =0.3*2 -> 0.6 | C23: =Referencias!F31 -> 0.45 | D23: =B23*C23 -> 0.27
A24: =Referencias!B48 -> Papel guarda 15,5x21,5 offset adesivo | B24: 2 | C24: =Referencias!F47 -> 0.75 | D24: =B24*C24 -> 1.5
A25: =Referencias!B45 -> miolo 90gr A5 | B25: 109 | C25: =Referencias!F45 -> 0.05 | D25: =B25*C25 -> 5.45
A26: =Referencias!B34 -> Bolso offset 180gr | B26: 1 | C26: =Referencias!F34 -> 0.32 | D26: =B26*C26 -> 0.32
A27: =Referencias!B19 -> Espiral 29mm | B27: 1 | C27: =Referencias!F19 -> 1.83 | D27: =B27*C27 -> 1.83
A28: =Referencias!B22 -> Impressao Capa A4 | B28: 2 | C28: =Referencias!F22 -> 0.5 | D28: =B28*C28 -> 1
A29: =Referencias!B29 -> Impressao Miolo Frente Verso A5 | B29: 115 | C29: =Referencias!F29 -> 0.06 | D29: =B29*C29 -> 6.9
A30: =Referencias!B21 -> Impressao Bolso A4 | B30: 1 | C30: =Referencias!F21 -> 1 | D30: =B30*C30 -> 1
A31: =Referencias!B62 -> Frete | C31: =Referencias!F62 -> 0 | D31: =B31*C31 -> 0
A32: =Referencias!B13 -> Desgaste Agenda | B32: 1 | C32: =Referencias!F13 -> 1 | D32: =B32*C32 -> 1
A33: =Referencias!B17 -> Embalagem Padrão | B33: 1 | C33: =Referencias!F17 -> 1.5 | D33: =B33*C33 -> 1.5
A34: Custo | D34: =SUM(D21:D33) -> 25.37
A35: Margem | B35: 0.55 | C35: =D34*B35 -> 13.9535 | D35: =D34+C35 -> 39.3235
A36: Pesquisa | B36: praper | C36: mp
A37: Valor | B37: 54.9 | C37: 54 | D37: 49
A39: Agenda Masculina 1 dia | D39: 69
A40: =Referencias!B58 -> Papelão 16x22 | B40: 2 | C40: =Referencias!F58 -> 1.5 | D40: =B40*C40 -> 3
A41: =Referencias!B53 -> Papel fotografico A4 | B41: 2 | C41: =Referencias!F53 -> 0.8 | D41: =B41*C41 -> 1.6
A42: =Referencias!B31 -> bopp | B42: =0.3*2 -> 0.6 | C42: =Referencias!F31 -> 0.45 | D42: =B42*C42 -> 0.27
A43: =Referencias!B48 -> Papel guarda 15,5x21,5 offset adesivo | B43: 2 | C43: =Referencias!F48 -> 0.75 | D43: =B43*C43 -> 1.5
A44: =Referencias!B40 -> miolo 75gr A5 | B44: 204 | C44: =Referencias!F40 -> 0.03 | D44: =B44*C44 -> 6.12
A45: =Referencias!B34 -> Bolso offset 180gr | B45: 1 | C45: =Referencias!F34 -> 0.32 | D45: =B45*C45 -> 0.32
A46: =Referencias!B120 -> Espiral 33mm plastico | B46: 1 | C46: =Referencias!F120 -> 2.48 | D46: =B46*C46 -> 2.48
A47: =Referencias!B22 -> Impressao Capa A4 | B47: 2 | C47: =Referencias!F22 -> 0.5 | D47: =B47*C47 -> 1
A48: =Referencias!B29 -> Impressao Miolo Frente Verso A5 | B48: 209 | C48: =Referencias!F29 -> 0.06 | D48: =B48*C48 -> 12.54
A49: =Referencias!B21 -> Impressao Bolso A4 | B49: 1 | C49: =Referencias!F21 -> 1 | D49: =B49*C49 -> 1
A50: =Referencias!B62 -> Frete | C50: =Referencias!F62 -> 0 | D50: =B50*C50 -> 0
A51: =Referencias!B13 -> Desgaste Agenda | B51: 1 | C51: =Referencias!F13 -> 1 | D51: =B51*C51 -> 1
A52: =Referencias!B17 -> Embalagem Padrão | B52: 1 | C52: =Referencias!F17 -> 1.5 | D52: =B52*C52 -> 1.5
A53: Custo | D53: =SUM(D40:D52) -> 32.33
A54: Margem | B54: 0.55 | C54: =D53*B54 -> 17.7815 | D54: =D53+C54 -> 50.1115
A55: Pesquisa | B55: praper
A56: Valor | B56: 84.9 | D56: 69
A58: Agenda Masculina 2 dias | D58: 49
A59: =Referencias!B58 -> Papelão 16x22 | B59: 2 | C59: =Referencias!F58 -> 1.5 | D59: =B59*C59 -> 3
A60: =Referencias!B53 -> Papel fotografico A4 | B60: 2 | C60: =Referencias!F53 -> 0.8 | D60: =B60*C60 -> 1.6
A61: =Referencias!B31 -> bopp | B61: =0.3*2 -> 0.6 | C61: =Referencias!F31 -> 0.45 | D61: =B61*C61 -> 0.27
A62: =Referencias!B48 -> Papel guarda 15,5x21,5 offset adesivo | B62: 2 | C62: =Referencias!F48 -> 0.75 | D62: =B62*C62 -> 1.5
A63: =Referencias!B45 -> miolo 90gr A5 | B63: 115 | C63: =Referencias!F45 -> 0.05 | D63: =B63*C63 -> 5.75
A64: =Referencias!B34 -> Bolso offset 180gr | B64: 1 | C64: =Referencias!F34 -> 0.32 | D64: =B64*C64 -> 0.32
A65: =Referencias!B19 -> Espiral 29mm | B65: 1 | C65: =Referencias!F19 -> 1.83 | D65: =B65*C65 -> 1.83
A66: =Referencias!B22 -> Impressao Capa A4 | B66: 2 | C66: =Referencias!F22 -> 0.5 | D66: =B66*C66 -> 1
A67: =Referencias!B29 -> Impressao Miolo Frente Verso A5 | B67: 115 | C67: =Referencias!F29 -> 0.06 | D67: =B67*C67 -> 6.9
A68: =Referencias!B21 -> Impressao Bolso A4 | B68: 1 | C68: =Referencias!F21 -> 1 | D68: =B68*C68 -> 1
A69: =Referencias!B62 -> Frete | B69: 0 | C69: =Referencias!F62 -> 0 | D69: =B69*C69 -> 0
A70: =Referencias!B13 -> Desgaste Agenda | B70: 1 | C70: =Referencias!F13 -> 1 | D70: =B70*C70 -> 1
A71: =Referencias!B17 -> Embalagem Padrão | B71: 1 | C71: =Referencias!F17 -> 1.5 | D71: =B71*C71 -> 1.5
A72: Custo | D72: =SUM(D59:D71) -> 25.67
A73: Margem | B73: 0.55 | C73: =D72*B73 -> 14.1185 | D73: =D72+C73 -> 39.7885
A74: Pesquisa | B74: praper | C74: mp
A75: Valor | B75: 54.9 | C75: 54 | D75: 49
A78: Caça aos ovos | D78: 15
A79: =Referencias!B37 -> miolo 180gr A4 | B79: 6 | C79: =Referencias!F37 -> 0.32 | D79: =B79*C79 -> 1.92
A80: =Referencias!B22 -> Impressao Capa A4 | B80: 6 | C80: =Referencias!F22 -> 0.5 | D80: =B80*C80 -> 3
A81: =Referencias!B62 -> Frete | C81: =Referencias!F62 -> 0 | D81: =B81*C81 -> 0
A82: =Referencias!B14 -> Desgaste Bloquinho/Outros | B82: 1 | C82: =Referencias!F14 -> 0.5 | D82: =B82*C82 -> 0.5
A83: =Referencias!B17 -> Embalagem Padrão | B83: 1 | C83: =Referencias!F17 -> 1.5 | D83: =B83*C83 -> 1.5
A84: Custo | D84: =SUM(D79:D83) -> 6.92
A85: Margem | B85: 0.55 | C85: =D84*B85 -> 3.806 | D85: =D84+C85 -> 10.726
A86: Pesquisa
A87: Valor | D87: 20
A89: Caixa Presente de Páscoa | D89: 15
A90: =Referencias!B38 -> Papel 240g A4 | B90: 6 | C90: =Referencias!F38 -> 0.42 | D90: =B90*C90 -> 2.52
A91: =Referencias!B9 -> Fita cetim | B91: 0.6 | C91: =Referencias!F9 -> 0.13 | D91: =B91*C91 -> 0.078
A92: =Referencias!B22 -> Impressao Capa A4 | B92: 8 | C92: =Referencias!F22 -> 0.5 | D92: =B92*C92 -> 4
A93: =Referencias!B62 -> Frete | C93: =Referencias!F62 -> 0 | D93: =B93*C93 -> 0
A94: =Referencias!B14 -> Desgaste Bloquinho/Outros | B94: 1 | C94: =Referencias!F14 -> 0.5 | D94: =B94*C94 -> 0.5
A95: =Referencias!B17 -> Embalagem Padrão | B95: 1 | C95: =Referencias!F17 -> 1.5 | D95: =B95*C95 -> 1.5
A96: Custo | D96: =SUM(D90:D95) -> 8.598
A97: Margem | B97: 0.55 | C97: =D96*B97 -> 4.7289 | D97: =D96+C97 -> 13.3269
A98: Pesquisa
A99: Valor | D99: 15
A101: Sacolinha P | D101: 6
A102: =Referencias!B84 -> Papel 180gr A4 | B102: 2 | C102: =Referencias!F84 -> 0.32 | D102: =B102*C102 -> 0.64
A103: =Referencias!B85 -> Alça - Fio Nautico circulo branco | B103: 0.52 | C103: =Referencias!F85 -> 0.14 | D103: =B103*C103 -> 0.0728
A104: =Referencias!B83 -> Impressão A4 | B104: 2 | C104: =Referencias!F83 -> 0.5 | D104: =B104*C104 -> 1
A105: =Referencias!B62 -> Frete | C105: =Referencias!F62 -> 0 | D105: =B105*C105 -> 0
A106: =Referencias!B14 -> Desgaste Bloquinho/Outros | B106: 1 | C106: =Referencias!F14 -> 0.5 | D106: =B106*C106 -> 0.5
A107: =Referencias!B17 -> Embalagem Padrão | B107: 1 | C107: =Referencias!F17 -> 1.5 | D107: =B107*C107 -> 1.5
...

Sheet Mulher23
A1: Ecopad c/5 P | D1: 5
A2: =Referencias!B104 -> Barroco Natural 8 700g | B2: 30 | C2: =Referencias!F104 -> 0.03 | D2: =B2*C2 -> 0.9
A3: =Referencias!B62 -> Frete | C3: =Referencias!F62 -> 0 | D3: =B3*C3 -> 0
A4: =Referencias!B14 -> Desgaste Bloquinho/Outros | B4: 1 | C4: =Referencias!F14 -> 0.5 | D4: =B4*C4 -> 0.5
A5: =Referencias!B17 -> Embalagem Padrão | B5: 1 | C5: =Referencias!F17 -> 1.5 | D5: =B5*C5 -> 1.5
A6: Custo | D6: =SUM(D2:D5) -> 2.9
A7: Margem | B7: 0.55 | C7: =D6*B7 -> 1.595 | D7: =D6+C7 -> 4.495
A8: Pesquisa
A9: Valor | D9: 5
A11: Ecopad c/5 P com Bolsa | D11: 10
A12: =Referencias!B104 -> Barroco Natural 8 700g | B12: 70 | C12: =Referencias!F104 -> 0.03 | D12: =B12*C12 -> 2.1
A13: =Referencias!B62 -> Frete | C13: =Referencias!F62 -> 0 | D13: =B13*C13 -> 0
A14: =Referencias!B14 -> Desgaste Bloquinho/Outros | B14: 1 | C14: =Referencias!F14 -> 0.5 | D14: =B14*C14 -> 0.5
A15: =Referencias!B17 -> Embalagem Padrão | B15: 1 | C15: =Referencias!F17 -> 1.5 | D15: =B15*C15 -> 1.5
A16: Custo | D16: =SUM(D12:D15) -> 4.1
A17: Margem | B17: 0.55 | C17: =D16*B17 -> 2.255 | D17: =D16+C17 -> 6.355
A18: Pesquisa
A19: Valor | D19: 10
A21: Ecopad c/3 M | D21: 5
A22: =Referencias!B104 -> Barroco Natural 8 700g | B22: 30 | C22: =Referencias!F104 -> 0.03 | D22: =B22*C22 -> 0.9
A23: =Referencias!B62 -> Frete | C23: =Referencias!F62 -> 0 | D23: =B23*C23 -> 0
A24: =Referencias!B14 -> Desgaste Bloquinho/Outros | B24: 1 | C24: =Referencias!F14 -> 0.5 | D24: =B24*C24 -> 0.5
A25: =Referencias!B17 -> Embalagem Padrão | B25: 1 | C25: =Referencias!F17 -> 1.5 | D25: =B25*C25 -> 1.5
A26: Custo | D26: =SUM(D22:D25) -> 2.9
A27: Margem | B27: 0.55 | C27: =D26*B27 -> 1.595 | D27: =D26+C27 -> 4.495
A28: Pesquisa
A29: Valor | D29: 5
A31: Ecopad c/3 M com Bolsa | D31: 10
A32: =Referencias!B104 -> Barroco Natural 8 700g | B32: 70 | C32: =Referencias!F104 -> 0.03 | D32: =B32*C32 -> 2.1
A33: =Referencias!B62 -> Frete | C33: =Referencias!F62 -> 0 | D33: =B33*C33 -> 0
A34: =Referencias!B14 -> Desgaste Bloquinho/Outros | B34: 1 | C34: =Referencias!F14 -> 0.5 | D34: =B34*C34 -> 0.5
A35: =Referencias!B17 -> Embalagem Padrão | B35: 1 | C35: =Referencias!F17 -> 1.5 | D35: =B35*C35 -> 1.5
A36: Custo | D36: =SUM(D32:D35) -> 4.1
A37: Margem | B37: 0.55 | C37: =D36*B37 -> 2.255 | D37: =D36+C37 -> 6.355
A38: Pesquisa
A39: Valor | D39: 10
A41: Bolsa para Ecopad em Croche | D41: 7.5
A42: =Referencias!B104 -> Barroco Natural 8 700g | B42: 40 | C42: =Referencias!F104 -> 0.03 | D42: =B42*C42 -> 1.2
A43: =Referencias!B62 -> Frete | C43: =Referencias!F62 -> 0 | D43: =B43*C43 -> 0
A44: =Referencias!B14 -> Desgaste Bloquinho/Outros | B44: 1 | C44: =Referencias!F14 -> 0.5 | D44: =B44*C44 -> 0.5
A45: =Referencias!B17 -> Embalagem Padrão | B45: 1 | C45: =Referencias!F17 -> 1.5 | D45: =B45*C45 -> 1.5
A46: Custo | D46: =SUM(D42:D45) -> 3.2
A47: Margem | B47: 0.55 | C47: =D46*B47 -> 1.76 | D47: =D46+C47 -> 4.96
A48: Pesquisa
A49: Valor | D49: 7.5
A51: Esponja Massageadora em Crochê | D51: 8
A52: =Referencias!B105 -> Fio Anne 500 147g | B52: 24 | C52: =Referencias!F105 -> 0.12 | D52: =B52*C52 -> 2.88
A53: =Referencias!B62 -> Frete | C53: =Referencias!F62 -> 0 | D53: =B53*C53 -> 0
A54: =Referencias!B14 -> Desgaste Bloquinho/Outros | B54: 1 | C54: =Referencias!F14 -> 0.5 | D54: =B54*C54 -> 0.5
A55: =Referencias!B17 -> Embalagem Padrão | B55: 1 | C55: =Referencias!F17 -> 1.5 | D55: =B55*C55 -> 1.5
A56: Custo | D56: =SUM(D52:D55) -> 4.88
A57: Margem | B57: 0.55 | C57: =D56*B57 -> 2.684 | D57: =D56+C57 -> 7.564
A58: Pesquisa
A59: Valor | D59: 8
A61: Esponja Fru-fru | D61: 10
A62: =Referencias!B105 -> Fio Anne 500 147g | B62: 49 | C62: =Referencias!F105 -> 0.12 | D62: =B62*C62 -> 5.88
A63: =Referencias!B62 -> Frete | C63: =Referencias!F62 -> 0 | D63: =B63*C63 -> 0
A64: =Referencias!B14 -> Desgaste Bloquinho/Outros | B64: 1 | C64: =Referencias!F14 -> 0.5 | D64: =B64*C64 -> 0.5
A65: =Referencias!B17 -> Embalagem Padrão | B65: 1 | C65: =Referencias!F17 -> 1.5 | D65: =B65*C65 -> 1.5
A66: Custo | D66: =SUM(D62) -> 5.88
A67: Margem | B67: 0.55 | C67: =D66*B67 -> 3.234 | D67: =D66+C67 -> 9.114
A68: Pesquisa
A69: Valor | D69: 10
A71: Máscara de Limpeza Facial | D71: 3.5
A72: =Referencias!B101 -> Máscara Facial de Limpeza | B72: 1 | C72: =Referencias!F101 -> 1.02 | D72: =B72*C72 -> 1.02
A73: =Referencias!B100 -> Papel 180gr A6 | B73: 1 | C73: =Referencias!F100 -> 0.08 | D73: =B73*C73 -> 0.08
A74: =Referencias!B24 -> Impressao Capa A6 | B74: 1 | C74: =Referencias!F24 -> 0.13 | D74: =B74*C74 -> 0.13
A75: =Referencias!B62 -> Frete | C75: =Referencias!F62 -> 0 | D75: =B75*C75 -> 0
A76: =Referencias!B14 -> Desgaste Bloquinho/Outros | B76: 1 | C76: =Referencias!F14 -> 0.5 | D76: =B76*C76 -> 0.5
A77: =Referencias!B107 -> Embalagem Atacado | B77: 1 | C77: =Referencias!F107 -> 0.5 | D77: =B77*C77 -> 0.5
A78: Custo | D78: =SUM(D72:D77) -> 2.23
A79: Margem | B79: 0.55 | C79: =D78*B79 -> 1.2265 | D79: =D78+C79 -> 3.4565
A80: Pesquisa
A81: Valor | D81: 4
A83: Bloquinho 6x6 | D83: 3.5
A84: =Referencias!B106 -> Papel 180gr Capa 6x6 | B84: 1 | C84: =Referencias!F106 -> 0.08 | D84: =B84*C84 -> 0.08
A85: =Referencias!B39 -> miolo 75gr A4 | B85: 4 | C85: =Referencias!F39 -> 0.06 | D85: =B85*C85 -> 0.24
A86: =Referencias!B24 -> Impressao Capa A6 | B86: 1 | C86: =Referencias!F24 -> 0.13 | D86: =B86*C86 -> 0.13
A87: =Referencias!B62 -> Frete | C87: =Referencias!F62 -> 0 | D87: =B87*C87 -> 0
A88: =Referencias!B14 -> Desgaste Bloquinho/Outros | B88: 1 | C88: =Referencias!F14 -> 0.5 | D88: =B88*C88 -> 0.5
A89: =Referencias!B107 -> Embalagem Atacado | B89: 1 | C89: =Referencias!F107 -> 0.5 | D89: =B89*C89 -> 0.5
A90: Custo | D90: =SUM(D84:D89) -> 1.45
A91: Margem | B91: 0.55 | C91: =D90*B91 -> 0.7975 | D91: =D90+C91 -> 2.2475
A92: Pesquisa
A93: Valor | D93: 4
A95: Bloquinho 6x6 | D95: 3.5
A96: =Referencias!B84 -> Papel 180gr A4 | B96: 6 | C96: =Referencias!F55 -> 0.27 | D96: =B96*C96 -> 1.62
A97: Baton | B97: 1 | C97: =Referencias!F40 -> 0.03 | D97: =B97*C97 -> 0.03
A98: =Referencias!B22 -> Impressao Capa A4 | C98: =Referencias!F78 -> 27.8 | D98: =B98*C98 -> 0
A99: =Referencias!B62 -> Frete | C99: =Referencias!F62 -> 0 | D99: =B99*C99 -> 0
A100: =Referencias!B14 -> Desgaste Bloquinho/Outros | B100: 1 | C100: =Referencias!F14 -> 0.5 | D100: =B100*C100 -> 0.5
A101: =Referencias!B107 -> Embalagem Atacado | B101: 1 | C101: =Referencias!F107 -> 0.5 | D101: =B101*C101 -> 0.5
A102: Custo | D102: =SUM(D96:D101) -> 2.65
A103: Margem | B103: 0.55 | C103: =D102*B103 -> 1.4575 | D103: =D102+C103 -> 4.1075
A104: Pesquisa
A105: Valor | D105: 4
A107: Chocolate Baton Personalizado | D107: 3.35
A108: =Referencias!B110 -> Chocolate Baton 16g | B108: 1 | C108: =Referencias!F110 -> 0.93 | D108: =B108*C108 -> 0.93
A109: =Referencias!B111 -> Card OffSet 180gr | B109: 1 | C109: =Referencias!F111 -> 0.05 | D109: =B109*C109 -> 0.05
A110: =Referencias!B112 -> Impressao Card | B110: 1 | C110: =Referencias!F112 -> 0.08 | D110: =B110*C110 -> 0.08
...

Sheet VoltaAulas23
A1: Agenda Escolar 1 dia | D1: 37.9
A2: =Referencias!B58 -> Papelão 16x22 | B2: 2 | C2: =Referencias!F58 -> 1.5 | D2: =B2*C2 -> 3
A3: =Referencias!B53 -> Papel fotografico A4 | B3: 2 | C3: =Referencias!F53 -> 0.8 | D3: =B3*C3 -> 1.6
A4: =Referencias!B31 -> bopp | B4: =0.3*2 -> 0.6 | C4: =Referencias!F31 -> 0.45 | D4: =B4*C4 -> 0.27
A5: =Referencias!B48 -> Papel guarda 15,5x21,5 offset adesivo | B5: 2 | C5: =Referencias!F48 -> 0.75 | D5: =B5*C5 -> 1.5
A6: =Referencias!B40 -> miolo 75gr A5 | B6: 109 | C6: =Referencias!F40 -> 0.03 | D6: =B6*C6 -> 3.27
A7: =Referencias!B34 -> Bolso offset 180gr | B7: 1 | C7: =Referencias!F34 -> 0.32 | D7: =B7*C7 -> 0.32
A8: =Referencias!B19 -> Espiral 29mm | B8: 1 | C8: =Referencias!F19 -> 1.83 | D8: =B8*C8 -> 1.83
A9: =Referencias!B22 -> Impressao Capa A4 | B9: 2 | C9: =Referencias!F22 -> 0.5 | D9: =B9*C9 -> 1
A10: =Referencias!B29 -> Impressao Miolo Frente Verso A5 | B10: 109 | C10: =Referencias!F29 -> 0.06 | D10: =B10*C10 -> 6.54
A11: =Referencias!B21 -> Impressao Bolso A4 | B11: 1 | C11: =Referencias!F21 -> 1 | D11: =B11*C11 -> 1
A12: =Referencias!B62 -> Frete | C12: =Referencias!F62 -> 0 | D12: =B12*C12 -> 0
A13: =Referencias!B13 -> Desgaste Agenda | B13: 1 | C13: =Referencias!F13 -> 1 | D13: =B13*C13 -> 1
A14: =Referencias!B17 -> Embalagem Padrão | B14: 1 | C14: =Referencias!F17 -> 1.5 | D14: =B14*C14 -> 1.5
A15: Custo | D15: =SUM(D2:D14) -> 22.83
A16: Margem | B16: 0.55 | C16: =D15*B16 -> 12.5565 | D16: =D15+C16 -> 35.3865
A17: Pesquisa | B17: MP mimos
A18: Valor | B18: 55 | D18: 40
A20: Agenda Escolar 2 dias | D20: 30
A21: =Referencias!B58 -> Papelão 16x22 | B21: 2 | C21: =Referencias!F58 -> 1.5 | D21: =B21*C21 -> 3
A22: =Referencias!B53 -> Papel fotografico A4 | B22: 2 | C22: =Referencias!F53 -> 0.8 | D22: =B22*C22 -> 1.6
A23: =Referencias!B31 -> bopp | B23: =0.3*2 -> 0.6 | C23: =Referencias!F31 -> 0.45 | D23: =B23*C23 -> 0.27
A24: =Referencias!B48 -> Papel guarda 15,5x21,5 offset adesivo | B24: 2 | C24: =Referencias!F48 -> 0.75 | D24: =B24*C24 -> 1.5
A25: =Referencias!B45 -> miolo 90gr A5 | B25: 57 | C25: =Referencias!F45 -> 0.05 | D25: =B25*C25 -> 2.85
A26: =Referencias!B34 -> Bolso offset 180gr | B26: 1 | C26: =Referencias!F34 -> 0.32 | D26: =B26*C26 -> 0.32
A27: =Referencias!B69 -> Espiral 20mm | B27: 1 | C27: =Referencias!F69 -> 0.64 | D27: =B27*C27 -> 0.64
A28: =Referencias!B22 -> Impressao Capa A4 | B28: 2 | C28: =Referencias!F22 -> 0.5 | D28: =B28*C28 -> 1
A29: =Referencias!B29 -> Impressao Miolo Frente Verso A5 | B29: 57 | C29: =Referencias!F29 -> 0.06 | D29: =B29*C29 -> 3.42
A30: =Referencias!B21 -> Impressao Bolso A4 | B30: 1 | C30: =Referencias!F21 -> 1 | D30: =B30*C30 -> 1
A31: =Referencias!B62 -> Frete | C31: =Referencias!F62 -> 0 | D31: =B31*C31 -> 0
A32: =Referencias!B13 -> Desgaste Agenda | B32: 1 | C32: =Referencias!F13 -> 1 | D32: =B32*C32 -> 1
A33: =Referencias!B17 -> Embalagem Padrão | B33: 1 | C33: =Referencias!F17 -> 1.5 | D33: =B33*C33 -> 1.5
A34: Custo | D34: =SUM(D21:D33) -> 18.1
A35: Margem | B35: 0.55 | C35: =D34*B35 -> 9.955 | D35: =D34+C35 -> 28.055
A36: Pesquisa | B36: MP mimos
A37: Valor | B37: 39 | D37: 30
A39: Agenda creche | D39: 40
A40: =Referencias!B58 -> Papelão 16x22 | B40: 2 | C40: =Referencias!F58 -> 1.5 | D40: =B40*C40 -> 3
A41: =Referencias!B53 -> Papel fotografico A4 | B41: 2 | C41: =Referencias!F53 -> 0.8 | D41: =B41*C41 -> 1.6
A42: =Referencias!B31 -> bopp | B42: =0.3*2 -> 0.6 | C42: =Referencias!F31 -> 0.45 | D42: =B42*C42 -> 0.27
A43: =Referencias!B48 -> Papel guarda 15,5x21,5 offset adesivo | B43: 2 | C43: =Referencias!F48 -> 0.75 | D43: =B43*C43 -> 1.5
A44: =Referencias!B40 -> miolo 75gr A5 | B44: 130 | C44: =Referencias!F40 -> 0.03 | D44: =B44*C44 -> 3.9
A45: =Referencias!B34 -> Bolso offset 180gr | B45: 1 | C45: =Referencias!F34 -> 0.32 | D45: =B45*C45 -> 0.32
A46: =Referencias!B19 -> Espiral 29mm | B46: 1 | C46: =Referencias!F19 -> 1.83 | D46: =B46*C46 -> 1.83
A47: =Referencias!B22 -> Impressao Capa A4 | B47: 2 | C47: =Referencias!F22 -> 0.5 | D47: =B47*C47 -> 1
A48: =Referencias!B29 -> Impressao Miolo Frente Verso A5 | B48: 130 | C48: =Referencias!F29 -> 0.06 | D48: =B48*C48 -> 7.8
A49: =Referencias!B21 -> Impressao Bolso A4 | B49: 1 | C49: =Referencias!F21 -> 1 | D49: =B49*C49 -> 1
A50: =Referencias!B62 -> Frete | C50: =Referencias!F62 -> 0 | D50: =B50*C50 -> 0
A51: =Referencias!B13 -> Desgaste Agenda | B51: 1 | C51: =Referencias!F13 -> 1 | D51: =B51*C51 -> 1
A52: =Referencias!B17 -> Embalagem Padrão | B52: 1 | C52: =Referencias!F17 -> 1.5 | D52: =B52*C52 -> 1.5
A53: Custo | D53: =SUM(D40:D52) -> 24.72
A54: Margem | B54: 0.55 | C54: =D53*B54 -> 13.596 | D54: =D53+C54 -> 38.316
A55: Pesquisa
A56: Valor | D56: 40
A58: Desk Planner | D58: 35
A59: =Referencias!B58 -> Papelão 16x22 | B59: 2 | C59: =Referencias!F58 -> 1.5 | D59: =B59*C59 -> 3
A60: =Referencias!B53 -> Papel fotografico A4 | B60: 2 | C60: =Referencias!F53 -> 0.8 | D60: =B60*C60 -> 1.6
A61: =Referencias!B31 -> bopp | B61: =0.3*2 -> 0.6 | C61: =Referencias!F31 -> 0.45 | D61: =B61*C61 -> 0.27
A62: =Referencias!B48 -> Papel guarda 15,5x21,5 offset adesivo | B62: 2 | C62: =Referencias!F48 -> 0.75 | D62: =B62*C62 -> 1.5
A63: =Referencias!B45 -> miolo 90gr A5 | B63: 61 | C63: =Referencias!F45 -> 0.05 | D63: =B63*C63 -> 3.05
A64: =Referencias!B34 -> Bolso offset 180gr | B64: 1 | C64: =Referencias!F34 -> 0.32 | D64: =B64*C64 -> 0.32
A65: =Referencias!B69 -> Espiral 20mm | B65: 1 | C65: =Referencias!F69 -> 0.64 | D65: =B65*C65 -> 0.64
A66: =Referencias!B22 -> Impressao Capa A4 | B66: 2 | C66: =Referencias!F22 -> 0.5 | D66: =B66*C66 -> 1
A67: =Referencias!B29 -> Impressao Miolo Frente Verso A5 | B67: 61 | C67: =Referencias!F29 -> 0.06 | D67: =B67*C67 -> 3.66
A68: =Referencias!B21 -> Impressao Bolso A4 | B68: 1 | C68: =Referencias!F21 -> 1 | D68: =B68*C68 -> 1
A69: =Referencias!B62 -> Frete | C69: =Referencias!F62 -> 0 | D69: =B69*C69 -> 0
A70: =Referencias!B16 -> Desgaste Planner/Album/Caderno Universitario | B70: 1 | C70: =Referencias!F16 -> 3 | D70: =B70*C70 -> 3
A71: =Referencias!B17 -> Embalagem Padrão | B71: 1 | C71: =Referencias!F17 -> 1.5 | D71: =B71*C71 -> 1.5
A72: Custo | D72: =SUM(D59:D71) -> 20.54
A73: Margem | B73: 0.55 | C73: =D72*B73 -> 11.297 | D73: =D72+C73 -> 31.837
A74: Pesquisa | B74: MP mimos
A75: Valor | B75: 42.9 | D75: 35
A77: Caderno A5 | D77: 35
A78: =Referencias!B58 -> Papelão 16x22 | B78: 2 | C78: =Referencias!F58 -> 1.5 | D78: =B78*C78 -> 3
A79: =Referencias!B53 -> Papel fotografico A4 | B79: 2 | C79: =Referencias!F53 -> 0.8 | D79: =B79*C79 -> 1.6
A80: =Referencias!B31 -> bopp | B80: =0.3*2 -> 0.6 | C80: =Referencias!F31 -> 0.45 | D80: =B80*C80 -> 0.27
A81: =Referencias!B48 -> Papel guarda 15,5x21,5 offset adesivo | B81: 2 | C81: =Referencias!F48 -> 0.75 | D81: =B81*C81 -> 1.5
A82: =Referencias!B40 -> miolo 75gr A5 | B82: 80 | C82: =Referencias!F40 -> 0.03 | D82: =B82*C82 -> 2.4
A83: =Referencias!B69 -> Espiral 20mm | B83: 1 | C83: =Referencias!F69 -> 0.64 | D83: =B83*C83 -> 0.64
A84: =Referencias!B22 -> Impressao Capa A4 | B84: 2 | C84: =Referencias!F22 -> 0.5 | D84: =B84*C84 -> 1
A85: =Referencias!B29 -> Impressao Miolo Frente Verso A5 | B85: 80 | C85: =Referencias!F29 -> 0.06 | D85: =B85*C85 -> 4.8
A86: =Referencias!B62 -> Frete | C86: =Referencias!F62 -> 0 | D86: =B86*C86 -> 0
A87: =Referencias!B15 -> Desgaste Caderno A5 | B87: 1 | C87: =Referencias!F15 -> 2 | D87: =B87*C87 -> 2
A88: =Referencias!B17 -> Embalagem Padrão | B88: 1 | C88: =Referencias!F17 -> 1.5 | D88: =B88*C88 -> 1.5
A89: Custo | D89: =SUM(D78:D88) -> 18.71
A90: Margem | B90: 0.55 | C90: =D89*B90 -> 10.2905 | D90: =D89+C90 -> 29.0005
A91: Pesquisa | B91: MP mimos
A92: Valor | B92: 39 | D92: 40
A94: Caderno Universitário | D94: 45
A95: =Referencias!B72 -> Papelão 19x27 | B95: 2 | C95: =Referencias!F72 -> 1.5 | D95: =B95*C95 -> 3
A96: =Referencias!B53 -> Papel fotografico A4 | B96: 2 | C96: =Referencias!F53 -> 0.8 | D96: =B96*C96 -> 1.6
A97: =Referencias!B31 -> bopp | B97: =0.3*2 -> 0.6 | C97: =Referencias!F31 -> 0.45 | D97: =B97*C97 -> 0.27
A98: =Referencias!B73 -> Papel guarda 18,5x26,5 offset adesivo | B98: 2 | C98: =Referencias!F73 -> 0.75 | D98: =B98*C98 -> 1.5
A99: =Referencias!B74 -> miolo 75gr 18x26 | B99: 80 | C99: =Referencias!F74 -> 0.06 | D99: =B99*C99 -> 4.8
A100: =Referencias!B69 -> Espiral 20mm | B100: 1 | C100: =Referencias!F69 -> 0.64 | D100: =B100*C100 -> 0.64
A101: =Referencias!B22 -> Impressao Capa A4 | B101: 2 | C101: =Referencias!F22 -> 0.5 | D101: =B101*C101 -> 1
A102: =Referencias!B28 -> Impressao Miolo Frente Verso A4 | B102: 80 | C102: =Referencias!F28 -> 0.12 | D102: =B102*C102 -> 9.6
A103: =Referencias!B62 -> Frete | C103: =Referencias!F62 -> 0 | D103: =B103*C103 -> 0
A104: =Referencias!B16 -> Desgaste Planner/Album/Caderno Universitario | B104: 1 | C104: =Referencias!F16 -> 3 | D104: =B104*C104 -> 3
A105: =Referencias!B17 -> Embalagem Padrão | B105: 1 | C105: =Referencias!F17 -> 1.5 | D105: =B105*C105 -> 1.5
...

Sheet Coleção23
A1: Agenda 1 dia datada | D1: 79.9
A2: =Referencias!B58 -> Papelão 16x22 | B2: 2 | C2: =Referencias!F58 -> 1.5 | D2: =B2*C2 -> 3
A3: =Referencias!B53 -> Papel fotografico A4 | B3: 2 | C3: =Referencias!F53 -> 0.8 | D3: =B3*C3 -> 1.6
A4: =Referencias!B31 -> bopp | B4: =0.3*2 -> 0.6 | C4: =Referencias!F31 -> 0.45 | D4: =B4*C4 -> 0.27
A5: =Referencias!B48 -> Papel guarda 15,5x21,5 offset adesivo | B5: 2 | C5: =Referencias!F48 -> 0.75 | D5: =B5*C5 -> 1.5
A6: =Referencias!B40 -> miolo 75gr A5 | B6: 205 | C6: =Referencias!F40 -> 0.03 | D6: =B6*C6 -> 6.15
A7: =Referencias!B34 -> Bolso offset 180gr | B7: 1 | C7: =Referencias!F34 -> 0.32 | D7: =B7*C7 -> 0.32
A8: =Referencias!B20 -> Espiral 33mm | B8: 1 | C8: =Referencias!F20 -> 4 | D8: =B8*C8 -> 4
A9: =Referencias!B22 -> Impressao Capa A4 | B9: 2 | C9: =Referencias!F22 -> 0.5 | D9: =B9*C9 -> 1
A10: =Referencias!B29 -> Impressao Miolo Frente Verso A5 | B10: 205 | C10: =Referencias!F29 -> 0.06 | D10: =B10*C10 -> 12.3
A11: =Referencias!B21 -> Impressao Bolso A4 | B11: 1 | C11: =Referencias!F21 -> 1 | D11: =B11*C11 -> 1
A12: =Referencias!B62 -> Frete | C12: =Referencias!F62 -> 0 | D12: =B12*C12 -> 0
A13: =Referencias!B13 -> Desgaste Agenda | B13: 1 | C13: =Referencias!F13 -> 1 | D13: =B13*C13 -> 1
A14: =Referencias!B17 -> Embalagem Padrão | B14: 1 | C14: =Referencias!F17 -> 1.5 | D14: =B14*C14 -> 1.5
A15: Custo | D15: =SUM(D2:D14) -> 33.64
A16: Margem | B16: 0.55 | C16: =D15*B16 -> 18.502 | D16: =D15+C16 -> 52.142
A17: Pesquisa | B17: praper | C17: mp
A18: Valor | B18: 69 | C18: 69 | D18: 89.9
A20: Agenda 2 dias datada | D20: 55.9
A21: =Referencias!B57 -> Papelão 15x18,5 | B21: 2 | C21: =Referencias!F57 -> 1.5 | D21: =B21*C21 -> 3
A22: =Referencias!B53 -> Papel fotografico A4 | B22: 2 | C22: =Referencias!F53 -> 0.8 | D22: =B22*C22 -> 1.6
A23: =Referencias!B31 -> bopp | B23: =0.3*2 -> 0.6 | C23: =Referencias!F31 -> 0.45 | D23: =B23*C23 -> 0.27
A24: =Referencias!B47 -> Papel guarda 14,5x18 offset adesivo | B24: 2 | C24: =Referencias!F47 -> 0.75 | D24: =B24*C24 -> 1.5
A25: =Referencias!B46 -> miolo 90gr A5 14x18 | B25: 115 | C25: =Referencias!F46 -> 0.05 | D25: =B25*C25 -> 5.75
A26: =Referencias!B34 -> Bolso offset 180gr | B26: 1 | C26: =Referencias!F34 -> 0.32 | D26: =B26*C26 -> 0.32
A27: =Referencias!B19 -> Espiral 29mm | B27: 1 | C27: =Referencias!F19 -> 1.83 | D27: =B27*C27 -> 1.83
A28: =Referencias!B22 -> Impressao Capa A4 | B28: 2 | C28: =Referencias!F22 -> 0.5 | D28: =B28*C28 -> 1
A29: =Referencias!B29 -> Impressao Miolo Frente Verso A5 | B29: 115 | C29: =Referencias!F29 -> 0.06 | D29: =B29*C29 -> 6.9
A30: =Referencias!B21 -> Impressao Bolso A4 | B30: 1 | C30: =Referencias!F21 -> 1 | D30: =B30*C30 -> 1
A31: =Referencias!B62 -> Frete | C31: =Referencias!F62 -> 0 | D31: =B31*C31 -> 0
A32: =Referencias!B13 -> Desgaste Agenda | B32: 1 | C32: =Referencias!F13 -> 1 | D32: =B32*C32 -> 1
A33: =Referencias!B17 -> Embalagem Padrão | B33: 1 | C33: =Referencias!F17 -> 1.5 | D33: =B33*C33 -> 1.5
A34: Custo | D34: =SUM(D21:D33) -> 25.67
A35: Margem | B35: 0.55 | C35: =D34*B35 -> 14.1185 | D35: =D34+C35 -> 39.7885
A36: Pesquisa | B36: praper | C36: mp
A37: Valor | B37: 54.9 | C37: 54 | D37: 65.9
A39: Agenda Agendamento | D39: 85.9
A40: =Referencias!B58 -> Papelão 16x22 | B40: 2 | C40: =Referencias!F58 -> 1.5 | D40: =B40*C40 -> 3
A41: =Referencias!B53 -> Papel fotografico A4 | B41: 2 | C41: =Referencias!F53 -> 0.8 | D41: =B41*C41 -> 1.6
A42: =Referencias!B31 -> bopp | B42: =0.3*2 -> 0.6 | C42: =Referencias!F31 -> 0.45 | D42: =B42*C42 -> 0.27
A43: =Referencias!B48 -> Papel guarda 15,5x21,5 offset adesivo | B43: 2 | C43: =Referencias!F48 -> 0.75 | D43: =B43*C43 -> 1.5
A44: =Referencias!B40 -> miolo 75gr A5 | B44: 209 | C44: =Referencias!F40 -> 0.03 | D44: =B44*C44 -> 6.27
A45: =Referencias!B34 -> Bolso offset 180gr | B45: 1 | C45: =Referencias!F34 -> 0.32 | D45: =B45*C45 -> 0.32
A46: =Referencias!B20 -> Espiral 33mm | B46: 1 | C46: =Referencias!F20 -> 4 | D46: =B46*C46 -> 4
A47: =Referencias!B22 -> Impressao Capa A4 | B47: 2 | C47: =Referencias!F22 -> 0.5 | D47: =B47*C47 -> 1
A48: =Referencias!B29 -> Impressao Miolo Frente Verso A5 | B48: 209 | C48: =Referencias!F29 -> 0.06 | D48: =B48*C48 -> 12.54
A49: =Referencias!B21 -> Impressao Bolso A4 | B49: 1 | C49: =Referencias!F21 -> 1 | D49: =B49*C49 -> 1
A50: =Referencias!B62 -> Frete | C50: =Referencias!F62 -> 0 | D50: =B50*C50 -> 0
A51: =Referencias!B13 -> Desgaste Agenda | B51: 1 | C51: =Referencias!F13 -> 1 | D51: =B51*C51 -> 1
A52: =Referencias!B17 -> Embalagem Padrão | B52: 1 | C52: =Referencias!F17 -> 1.5 | D52: =B52*C52 -> 1.5
A53: Custo | D53: =SUM(D40:D52) -> 34
A54: Margem | B54: 0.55 | C54: =D53*B54 -> 18.7 | D54: =D53+C54 -> 52.7
A55: Pesquisa | B55: praper
A56: Valor | B56: 84.9 | D56: 85.9
A58: Calendario A5 | D58: 20
A59: =Referencias!B56 -> Papelão 15,5x21,5+2,5x21,5 | B59: 2 | C59: =Referencias!F56 -> 1.5 | D59: =B59*C59 -> 3
A60: =Referencias!B52 -> Papel offset adesivo A4 | B60: 2 | C60: =Referencias!F52 -> 0.75 | D60: =B60*C60 -> 1.5
A61: =Referencias!B31 -> bopp | B61: =0.3*2 -> 0.6 | C61: =Referencias!F31 -> 0.45 | D61: =B61*C61 -> 0.27
A62: =Referencias!B50 -> Papel guarda 20x20 offset adesivo | B62: 2 | C62: =Referencias!F50 -> 0.75 | D62: =B62*C62 -> 1.5
A63: =Referencias!B36 -> miolo 180g A5 | B63: 12 | C63: =Referencias!F36 -> 0.16 | D63: =B63*C63 -> 1.92
A64: =Referencias!B18 -> Espiral 17mm | B64: 1 | C64: =Referencias!F18 -> 0.52 | D64: =B64*C64 -> 0.52
A65: =Referencias!B22 -> Impressao Capa A4 | B65: 2 | C65: =Referencias!F22 -> 0.5 | D65: =B65*C65 -> 1
A66: =Referencias!B29 -> Impressao Miolo Frente Verso A5 | B66: 12 | C66: =Referencias!F29 -> 0.06 | D66: =B66*C66 -> 0.72
A67: =Referencias!B62 -> Frete | C67: =Referencias!F62 -> 0 | D67: =B67*C67 -> 0
A68: =Referencias!B14 -> Desgaste Bloquinho/Outros | B68: 1 | C68: =Referencias!F14 -> 0.5 | D68: =B68*C68 -> 0.5
A69: =Referencias!B17 -> Embalagem Padrão | B69: 1 | C69: =Referencias!F17 -> 1.5 | D69: =B69*C69 -> 1.5
A70: Custo | D70: =SUM(D59:D69) -> 12.43
A71: Margem | B71: 0.55 | C71: =D70*B71 -> 6.8365 | D71: =D70+C71 -> 19.2665
A72: Pesquisa | B72: praper
A73: Valor | B73: 24.9 | D73: 25
A75: Calendario 10x10 | D75: 15
A76: =Referencias!B61 -> Papelão 9,5x10,5+9,5x2 | B76: 1 | C76: =Referencias!F61 -> 1.5 | D76: =B76*C76 -> 1.5
A77: =Referencias!B51 -> Papel offset adesivo + guarda | B77: 1 | C77: =Referencias!F51 -> 0.75 | D77: =B77*C77 -> 0.75
A78: =Referencias!B31 -> bopp | B78: =0.3 -> 0.3 | C78: =Referencias!F31 -> 0.45 | D78: =B78*C78 -> 0.135
A79: =Referencias!B37 -> miolo 180gr A4 | B79: 3 | C79: =Referencias!F37 -> 0.32 | D79: =B79*C79 -> 0.96
A80: =Referencias!B18 -> Espiral 17mm | B80: 0.34 | C80: =Referencias!F18 -> 0.52 | D80: =B80*C80 -> 0.1768
A81: =Referencias!B22 -> Impressao Capa A4 | B81: 1 | C81: =Referencias!F22 -> 0.5 | D81: =B81*C81 -> 0.5
A82: =Referencias!B63 -> Impressao Miolo Frente A4 | B82: 3 | C82: =Referencias!F63 -> 0.06 | D82: =B82*C82 -> 0.18
A83: =Referencias!B62 -> Frete | C83: =Referencias!F62 -> 0 | D83: =B83*C83 -> 0
A84: =Referencias!B14 -> Desgaste Bloquinho/Outros | B84: 1 | C84: =Referencias!F14 -> 0.5 | D84: =B84*C84 -> 0.5
A85: =Referencias!B17 -> Embalagem Padrão | B85: 1 | C85: =Referencias!F17 -> 1.5 | D85: =B85*C85 -> 1.5
A86: Custo | D86: =SUM(D76:D85) -> 6.2018
A87: Margem | B87: 0.55 | C87: =D86*B87 -> 3.41099 | D87: =D86+C87 -> 9.61279
A88: Pesquisa | B88: praper | C88: mp
A89: Valor | B89: 18.9 | C89: 11.9 | D89: 15
A91: Calendario minizinho | D91: 10
A92: =Referencias!B60 -> Papelão 7,7x8,5+7,7x2,5 | B92: 1 | C92: =Referencias!F60 -> 0.75 | D92: =B92*C92 -> 0.75
A93: =Referencias!B51 -> Papel offset adesivo + guarda | B93: 1 | C93: =Referencias!F51 -> 0.75 | D93: =B93*C93 -> 0.75
A94: =Referencias!B31 -> bopp | B94: =0.3 -> 0.3 | C94: =Referencias!F31 -> 0.45 | D94: =B94*C94 -> 0.135
A95: =Referencias!B37 -> miolo 180gr A4 | B95: 2 | C95: =Referencias!F37 -> 0.32 | D95: =B95*C95 -> 0.64
A96: =Referencias!B18 -> Espiral 17mm | B96: 0.34 | C96: =Referencias!F18 -> 0.52 | D96: =B96*C96 -> 0.1768
A97: =Referencias!B22 -> Impressao Capa A4 | B97: 1 | C97: =Referencias!F22 -> 0.5 | D97: =B97*C97 -> 0.5
A98: =Referencias!B63 -> Impressao Miolo Frente A4 | B98: 2 | C98: =Referencias!F63 -> 0.06 | D98: =B98*C98 -> 0.12
A99: =Referencias!B62 -> Frete | C99: =Referencias!F62 -> 0 | D99: =B99*C99 -> 0
A100: =Referencias!B14 -> Desgaste Bloquinho/Outros | B100: 1 | C100: =Referencias!F14 -> 0.5 | D100: =B100*C100 -> 0.5
A101: =Referencias!B17 -> Embalagem Padrão | B101: 1 | C101: =Referencias!F17 -> 1.5 | D101: =B101*C101 -> 1.5
A102: Custo | D102: =SUM(D92:D101) -> 5.0718
A103: Margem | B103: 0.55 | C103: =D102*B103 -> 2.78949 | D103: =D102+C103 -> 7.86129
A104: Pesquisa | B104: praper
A105: Valor | B105: 9.9 | D105: 10
...

Sheet Natal22
A1: Caderno Devocional | D1: 50
A2: =Referencias!B58 -> Papelão 16x22 | B2: 2 | C2: =Referencias!F58 -> 1.5 | D2: =B2*C2 -> 3
A3: =Referencias!B53 -> Papel fotografico A4 | B3: 2 | C3: =Referencias!F53 -> 0.8 | D3: =B3*C3 -> 1.6
A4: =Referencias!B31 -> bopp | B4: =2*0.3 -> 0.6 | C4: =Referencias!F31 -> 0.45 | D4: =B4*C4 -> 0.27
A5: =Referencias!B48 -> Papel guarda 15,5x21,5 offset adesivo | B5: 2 | C5: =Referencias!F48 -> 0.75 | D5: =B5*C5 -> 1.5
A6: =Referencias!B45 -> miolo 90gr A5 | B6: 84 | C6: =Referencias!F45 -> 0.05 | D6: =B6*C6 -> 4.2
A7: =Referencias!B20 -> Espiral 33mm | B7: 1 | C7: =Referencias!F20 -> 4 | D7: =B7*C7 -> 4
A8: =Referencias!B22 -> Impressao Capa A4 | B8: 2 | C8: =Referencias!F22 -> 0.5 | D8: =B8*C8 -> 1
A9: =Referencias!B29 -> Impressao Miolo Frente Verso A5 | B9: 84 | C9: =Referencias!F29 -> 0.06 | D9: =B9*C9 -> 5.04
A10: =Referencias!B62 -> Frete | C10: =Referencias!F62 -> 0 | D10: =B10*C10 -> 0
A11: =Referencias!B15 -> Desgaste Caderno A5 | B11: 1 | C11: =Referencias!F15 -> 2 | D11: =B11*C11 -> 2
A12: =Referencias!B17 -> Embalagem Padrão | B12: 1 | C12: =Referencias!F17 -> 1.5 | D12: =B12*C12 -> 1.5
A13: Custo | D13: =SUM(D2:D12) -> 24.11
A14: Margem | B14: 0.55 | C14: =D13*B14 -> 13.2605 | D14: =D13+C14 -> 37.3705
A15: Pesquisa | B15: praper | C15: mp
A16: Valor | D16: 60
A18: Caderno de Orações | D18: 40
A19: =Referencias!B58 -> Papelão 16x22 | B19: 2 | C19: =Referencias!F58 -> 1.5 | D19: =B19*C19 -> 3
A20: =Referencias!B53 -> Papel fotografico A4 | B20: 2 | C20: =Referencias!F53 -> 0.8 | D20: =B20*C20 -> 1.6
A21: =Referencias!B31 -> bopp | B21: =2*0.3 -> 0.6 | C21: =Referencias!F31 -> 0.45 | D21: =B21*C21 -> 0.27
A22: =Referencias!B48 -> Papel guarda 15,5x21,5 offset adesivo | B22: 2 | C22: =Referencias!F48 -> 0.75 | D22: =B22*C22 -> 1.5
A23: =Referencias!B45 -> miolo 90gr A5 | B23: 50 | C23: =Referencias!F45 -> 0.05 | D23: =B23*C23 -> 2.5
A24: =Referencias!B19 -> Espiral 29mm | B24: 1 | C24: =Referencias!F19 -> 1.83 | D24: =B24*C24 -> 1.83
A25: =Referencias!B22 -> Impressao Capa A4 | B25: 2 | C25: =Referencias!F22 -> 0.5 | D25: =B25*C25 -> 1
A26: =Referencias!B29 -> Impressao Miolo Frente Verso A5 | B26: 50 | C26: =Referencias!F29 -> 0.06 | D26: =B26*C26 -> 3
A27: =Referencias!B62 -> Frete | C27: =Referencias!F62 -> 0 | D27: =B27*C27 -> 0
A28: =Referencias!B15 -> Desgaste Caderno A5 | B28: 1 | C28: =Referencias!F15 -> 2 | D28: =B28*C28 -> 2
A29: =Referencias!B17 -> Embalagem Padrão | B29: 1 | C29: =Referencias!F17 -> 1.5 | D29: =B29*C29 -> 1.5
A30: Custo | D30: =SUM(D19:D29) -> 18.2
A31: Margem | B31: 0.55 | C31: =D30*B31 -> 10.01 | D31: =D30+C31 -> 28.21
A32: Pesquisa | B32: praper | C32: mp
A33: Valor | D33: 50
A35: Bloquinho A7 | D35: 10
A36: =Referencias!B67 -> Papelão 10,5x7,5 | B36: 2 | C36: =Referencias!F67 -> 0.37 | D36: =B36*C36 -> 0.74
A37: =Referencias!B53 -> Papel fotografico A4 | B37: 0.5 | C37: =Referencias!F53 -> 0.8 | D37: =B37*C37 -> 0.4
A38: =Referencias!B31 -> bopp | B38: =2*0.1 -> 0.2 | C38: =Referencias!F31 -> 0.45 | D38: =B38*C38 -> 0.09
A39: =Referencias!B48 -> Papel guarda 15,5x21,5 offset adesivo | B39: 0.5 | C39: =Referencias!F48 -> 0.75 | D39: =B39*C39 -> 0.375
A40: =Referencias!B68 -> miolo 75gr A7 | B40: 80 | C40: =Referencias!F68 -> 0.01 | D40: =B40*C40 -> 0.8
A41: =Referencias!B23 -> Impressao Capa A5 | B41: 1 | C41: =Referencias!F23 -> 0.25 | D41: =B41*C41 -> 0.25
A42: =Referencias!B62 -> Frete | C42: =Referencias!F62 -> 0 | D42: =B42*C42 -> 0
A43: =Referencias!B14 -> Desgaste Bloquinho/Outros | B43: 1 | C43: =Referencias!F14 -> 0.5 | D43: =B43*C43 -> 0.5
A44: =Referencias!B17 -> Embalagem Padrão | B44: 1 | C44: =Referencias!F17 -> 1.5 | D44: =B44*C44 -> 1.5
A45: Custo | D45: =SUM(D36:D44) -> 4.655
A46: Margem | B46: 0.55 | C46: =D45*B46 -> 2.56025 | D46: =D45+C46 -> 7.21525
A47: Pesquisa | B47: praper
A48: Valor | D48: 15
A50: Bolinha 6,5 | D50: 7
A51: =Referencias!B3 -> Bolinha 6,5 | B51: 1 | C51: =Referencias!F3 -> 1.04 | D51: =B51*C51 -> 1.04
A52: =Referencias!B53 -> Papel fotografico A4 | B52: 0.17 | C52: =Referencias!F53 -> 0.8 | D52: =B52*C52 -> 0.136
A53: =Referencias!B8 -> Fita 7mm | B53: 0.3 | C53: =Referencias!F8 -> 0.1 | D53: =B53*C53 -> 0.03
A54: =Referencias!B4 -> Cordão Dourado | B54: 0.25 | C54: =Referencias!F4 -> 0.15 | D54: =B54*C54 -> 0.0375
A55: =Referencias!B22 -> Impressao Capa A4 | B55: 0.17 | C55: =Referencias!F22 -> 0.5 | D55: =B55*C55 -> 0.085
A56: =Referencias!B62 -> Frete | C56: =Referencias!F62 -> 0 | D56: =B56*C56 -> 0
A57: =Referencias!B14 -> Desgaste Bloquinho/Outros | B57: 1 | C57: =Referencias!F14 -> 0.5 | D57: =B57*C57 -> 0.5
A58: =Referencias!B17 -> Embalagem Padrão | B58: 1 | C58: =Referencias!F17 -> 1.5 | D58: =B58*C58 -> 1.5
A59: Custo | D59: =SUM(D51:D58) -> 3.3285
A60: Margem | B60: 0.55 | C60: =D59*B60 -> 1.830675 | D60: =D59+C60 -> 5.159175
A61: Pesquisa | B61: praper
A62: Valor | B62: 6 | C62: 7 | D62: 7
A64: Kit Porta Panelas com 3 | D64: 50
A65: =Referencias!B2 -> Barroco MultiColor 200g | B65: 216 | C65: =Referencias!F2 -> 0.09 | D65: =B65*C65 -> 19.44
A66: =Referencias!B62 -> Frete | C66: =Referencias!F62 -> 0 | D66: =B66*C66 -> 0
A67: =Referencias!B14 -> Desgaste Bloquinho/Outros | B67: 1 | C67: =Referencias!F14 -> 0.5 | D67: =B67*C67 -> 0.5
A68: =Referencias!B17 -> Embalagem Padrão | B68: 1 | C68: =Referencias!F17 -> 1.5 | D68: =B68*C68 -> 1.5
A69: Custo | D69: =SUM(D65:D68) -> 21.44
A70: Margem | B70: 0.55 | C70: =D69*B70 -> 11.792 | D70: =D69+C70 -> 33.232
A71: Pesquisa
A72: Valor | D72: 60
A74: Kit Pano de Prato Decorado com 2 | D74: 20
A75: =Referencias!B7 -> Fio Clea 1000 160g | B75: 20 | C75: =Referencias!F7 -> 0.11 | D75: =B75*C75 -> 2.2
A76: =Referencias!B11 -> Pano de Prato Pé de Galinha | B76: 2 | C76: =Referencias!F11 -> 4 | D76: =B76*C76 -> 8
A77: =Referencias!B62 -> Frete | C77: =Referencias!F62 -> 0 | D77: =B77*C77 -> 0
A78: =Referencias!B14 -> Desgaste Bloquinho/Outros | B78: 1 | C78: =Referencias!F14 -> 0.5 | D78: =B78*C78 -> 0.5
A79: =Referencias!B17 -> Embalagem Padrão | B79: 1 | C79: =Referencias!F17 -> 1.5 | D79: =B79*C79 -> 1.5
A80: Custo | D80: =SUM(D75:D79) -> 12.2
A81: Margem | B81: 0.55 | C81: =D80*B81 -> 6.71 | D81: =D80+C81 -> 18.91
A82: Pesquisa | B82: loja sabonete
A83: Valor | B83: 24 | D83: 25
